Workbook

Sheet 2022_VIE_ENG
A1: Mã tỉnh | B1: Mã tỉnh | C1: Thang điểm/Scale | D1: 1 | E1: 2 | F1: 4 | G1: 6 | H1: 8 | I1: 10 | J1: 11 | K1: 12 | L1: 14 | M1: 15 | N1: 17 | O1: 19 | P1: 20 | Q1: 22 | R1: 24 | S1: 25 | T1: 26 | U1: 27 | V1: 30 | W1: 31 | X1: 33 | Y1: 34 | Z1: 35 | AA1: 36 | AB1: 37 | AC1: 38 | AD1: 40 | AE1: 42 | AF1: 44 | AG1: 45 | AH1: 46 | AI1: 48 | AJ1: 49 | AK1: 51 | AL1: 52 | AM1: 54 | AN1: 56 | AO1: 58 | AP1: 60 | AQ1: 62 | AR1: 64 | AS1: 66 | AT1: 67 | AU1: 68 | AV1: 70 | AW1: 72 | AX1: 74 | AY1: 75 | AZ1: 77 | BA1: 79 | BB1: 80 | BC1: 82 | BD1: 83 | BE1: 84 | BF1: 86 | BG1: 87 | BH1: 89 | BI1: 91 | BJ1: 92 | BK1: 93 | BL1: 94 | BM1: 95 | BN1: 96
A2: Tỉnh/Thành phố trực thuộc trung ương | B2: Tỉnh/Thành phố trực thuộc trung ương | D2: Hà Nội | E2: Hà Giang | F2: Cao Bằng | G2: Bắc Kạn | H2: Tuyên Quang | I2: Lào Cai | J2: Điện Biên | K2: Lai Châu | L2: Sơn La | M2: Yên Bái | N2: Hòa Bình | O2: Thái Nguyên | P2: Lạng Sơn | Q2: Quảng Ninh | R2: Bắc Giang | S2: Phú Thọ | T2: Vĩnh Phúc | U2: Bắc Ninh | V2: Hải Dương | W2: Hải Phòng | X2: Hưng Yên | Y2: Thái Bình | Z2: Hà Nam | AA2: Nam Định | AB2: Ninh Bình | AC2: Thanh Hóa | AD2: Nghệ An | AE2: Hà Tĩnh | AF2: Quảng Bình | AG2: Quảng Trị | AH2: Thừa Thiên-Huế | AI2: Đà Nẵng | AJ2: Quảng Nam | AK2: Quảng Ngãi | AL2: Bình Định | AM2: Phú Yên | AN2: Khánh Hòa | AO2: Ninh Thuận | AP2: Bình Thuận | AQ2: Kon Tum | AR2: Gia Lai | AS2: Đắk Lắk | AT2: Đắk Nông | AU2: Lâm Đồng | AV2: Bình Phước | AW2: Tây Ninh | AX2: Bình Dương | AY2: Đồng Nai | AZ2: Bà Rịa-Vũng Tàu | BA2: TP. Hồ Chí Minh | BB2: Long An | BC2: Tiền Giang | BD2: Bến Tre | BE2: Trà Vinh | BF2: Vĩnh Long | BG2: Đồng Tháp | BH2: An Giang | BI2: Kiên Giang | BJ2: Cần Thơ | BK2: Hậu Giang | BL2: Sóc Trăng | BM2: Bạc Liêu | BN2: Cà Mau
A3: Weighted PAPI Score | B3: Chỉ số PAPI tổng hợp (có trọng số) | C3: 10-80 điểm/points
A4: PAPI 95% CI Low | B4: Chỉ số PAPI tổng hợp (có trọng số) - điểm tối thiểu trong khoảng tin cậy 95%
A5: PAPI 95% CI High | B5: Chỉ số PAPI tổng hợp (có trọng số) - điểm tối đa trong khoảng tin cậy 95%
A6: PAPI Standard Error | B6: Chỉ số PAPI tổng hợp (có trọng số) - sai số
A7: Unweighted PAPI Score | B7: Chỉ số PAPI tổng hợp (không có trọng số) | C7: 10-80 điểm/points | D7: =VLOOKUP(A7,'2022_PAPI_Indicators'!A3:B183,2,FALSE) -> 43.90493 | E7: =VLOOKUP(A7,'2022_PAPI_Indicators'!A3:C183,3,FALSE) -> 41.146988 | F7: 38.803738 | G7: 42.436947 | H7: 43.109154 | I7: 40.397507 | J7: 39.668663 | K7: 42.690647 | L7: 40.869358 | M7: 41.83152 | N7: 41.007774 | O7: 43.016243 | P7: 43.847515 | Q7: 47.876301 | R7: 0 | S7: 44.246758 | T7: 44.308403 | U7: 0 | V7: 42.14352 | W7: 43.603531 | X7: 44.183117 | Y7: 43.514046 | Z7: 42.733124 | AA7: 43.152493 | AB7: 43.164555 | AC7: 46.015366 | AD7: 43.249977 | AE7: 44.313824 | AF7: 42.761436 | AG7: 41.7742 | AH7: 45.384464 | AI7: 42.570354 | AJ7: 42.237701 | AK7: 42.92836 | AL7: 41.660088 | AM7: 40.742329 | AN7: 43.436882 | AO7: 46.000217 | AP7: 44.539753 | AQ7: 39.975605 | AR7: 39.67363 | AS7: 41.122337 | AT7: 40.527431 | AU7: 40.709713 | AV7: 39.934429 | AW7: 39.417038 | AX7: 47.448799 | AY7: 41.263165 | AZ7: 41.992939 | BA7: 41.020382 | BB7: 39.809238 | BC7: 40.976799 | BD7: 40.597153 | BE7: 40.717228 | BF7: 43.024712 | BG7: 42.149784 | BH7: 41.002136 | BI7: 40.040089 | BJ7: 39.974747 | BK7: 42.591606 | BL7: 42.855907 | BM7: 44.911423 | BN7: 41.874588
A8: Unweighted 95% CI Low | B8: Chỉ số PAPI tổng hợp (không có trọng số) - điểm tối thiểu trong khoảng tin cậy 95% | D8: =VLOOKUP(A8,'2022_PAPI_Indicators'!A4:B184,2,FALSE) -> 43.518097 | E8: =VLOOKUP(A8,'2022_PAPI_Indicators'!A3:C183,3,FALSE) -> 40.69569 | F8: =VLOOKUP(A8,'2022_PAPI_Indicators'!A3:D183,4,FALSE) -> 38.151661 | G8: =VLOOKUP(A8,'2022_PAPI_Indicators'!A3:E183,5,FALSE) -> 40.999649 | H8: =VLOOKUP(A8,'2022_PAPI_Indicators'!A3:F183,6,FALSE) -> 42.630917 | I8: =VLOOKUP(A8,'2022_PAPI_Indicators'!A3:G183,7,FALSE) -> 39.353958 | J8: =VLOOKUP(A8,'2022_PAPI_Indicators'!A3:H183,8,FALSE) -> 36.878681 | K8: =VLOOKUP(A8,'2022_PAPI_Indicators'!A3:I183,9,FALSE) -> 42.063129 | L8: =VLOOKUP(A8,'2022_PAPI_Indicators'!A3:J183,10,FALSE) -> 38.007645 | M8: =VLOOKUP(A8,'2022_PAPI_Indicators'!A3:K183,11,FALSE) -> 39.764709 | N8: =VLOOKUP(A8,'2022_PAPI_Indicators'!A3:L183,12,FALSE) -> 39.618702 | O8: =VLOOKUP(A8,'2022_PAPI_Indicators'!A3:M183,13,FALSE) -> 42.748577 | P8: =VLOOKUP(A8,'2022_PAPI_Indicators'!A3:N183,14,FALSE) -> 42.599697 | Q8: =VLOOKUP(A8,'2022_PAPI_Indicators'!A3:O183,15,FALSE) -> 46.555725 | R8: =VLOOKUP(A8,'2022_PAPI_Indicators'!A3:P183,16,FALSE) -> 0 | S8: =VLOOKUP(A8,'2022_PAPI_Indicators'!A3:R183,17,FALSE) -> 43.080505 | T8: =VLOOKUP(A8,'2022_PAPI_Indicators'!A3:S183,18,FALSE) -> 43.282104 | U8: =VLOOKUP(A8,'2022_PAPI_Indicators'!A3:T183,19,FALSE) -> 0 | V8: =VLOOKUP(A8,'2022_PAPI_Indicators'!A3:U183,20,FALSE) -> 41.623455 | W8: =VLOOKUP(A8,'2022_PAPI_Indicators'!A3:V183,21,FALSE) -> 43.264462 | X8: =VLOOKUP(A8,'2022_PAPI_Indicators'!A3:W183,22,FALSE) -> 43.04599 | Y8: =VLOOKUP(A8,'2022_PAPI_Indicators'!A3:X183,23,FALSE) -> 42.72879 | Z8: =VLOOKUP(A8,'2022_PAPI_Indicators'!A3:Y183,24,FALSE) -> 41.536163 | AA8: =VLOOKUP(A8,'2022_PAPI_Indicators'!A3:Z183,25,FALSE) -> 42.756363 | AB8: =VLOOKUP(A8,'2022_PAPI_Indicators'!A3:AA183,26,FALSE) -> 42.757893 | AC8: =VLOOKUP(A8,'2022_PAPI_Indicators'!A3:AB183,27,FALSE) -> 45.726723 | AD8: =VLOOKUP(A8,'2022_PAPI_Indicators'!A3:AC183,28,FALSE) -> 42.832211 | AE8: =VLOOKUP(A8,'2022_PAPI_Indicators'!A3:AD183,29,FALSE) -> 43.135738 | AF8: =VLOOKUP(A8,'2022_PAPI_Indicators'!A3:AE183,30,FALSE) -> 42.095692 | AG8: =VLOOKUP(A8,'2022_PAPI_Indicators'!A3:AF183,31,FALSE) -> 39.958164 | AH8: =VLOOKUP(A8,'2022_PAPI_Indicators'!A3:AG183,32,FALSE) -> 44.921993 | AI8: =VLOOKUP(A8,'2022_PAPI_Indicators'!A3:AH183,33,FALSE) -> 42.100521 | AJ8: =VLOOKUP(A8,'2022_PAPI_Indicators'!A3:AI183,34,FALSE) -> 41.421711 | AK8: =VLOOKUP(A8,'2022_PAPI_Indicators'!A3:AJ183,35,FALSE) -> 42.542549 | AL8: =VLOOKUP(A8,'2022_PAPI_Indicators'!A3:AK183,36,FALSE) -> 40.291451 | AM8: =VLOOKUP(A8,'2022_PAPI_Indicators'!A3:AL183,37,FALSE) -> 39.31916 | AN8: =VLOOKUP(A8,'2022_PAPI_Indicators'!A3:AM183,38,FALSE) -> 42.348782 | AO8: =VLOOKUP(A8,'2022_PAPI_Indicators'!A3:AN183,39,FALSE) -> 42.67308 | AP8: =VLOOKUP(A8,'2022_PAPI_Indicators'!A3:AO183,40,FALSE) -> 41.32695 | AQ8: =VLOOKUP(A8,'2022_PAPI_Indicators'!A3:AP183,41,FALSE) -> 39.081516 | AR8: =VLOOKUP(A8,'2022_PAPI_Indicators'!A3:AQ183,42,FALSE) -> 38.064156 | AS8: =VLOOKUP(A8,'2022_PAPI_Indicators'!A3:AR183,43,FALSE) -> 38.267181 | AT8: =VLOOKUP(A8,'2022_PAPI_Indicators'!A3:AS183,44,FALSE) -> 39.406395 | AU8: =VLOOKUP(A8,'2022_PAPI_Indicators'!A3:AT183,45,FALSE) -> 40.062408 | AV8: =VLOOKUP(A8,'2022_PAPI_Indicators'!A3:AU183,46,FALSE) -> 39.20129 | AW8: =VLOOKUP(A8,'2022_PAPI_Indicators'!A3:AV183,47,FALSE) -> 38.418488 | AX8: =VLOOKUP(A8,'2022_PAPI_Indicators'!A3:AW183,48,FALSE) -> 45.451958 | AY8: =VLOOKUP(A8,'2022_PAPI_Indicators'!A3:AX183,49,FALSE) -> 40.673058 | AZ8: =VLOOKUP(A8,'2022_PAPI_Indicators'!A3:AY183,50,FALSE) -> 40.823223 | BA8: =VLOOKUP(A8,'2022_PAPI_Indicators'!A3:AZ183,51,FALSE) -> 40.478935 | BB8: =VLOOKUP(A8,'2022_PAPI_Indicators'!A3:BA183,52,FALSE) -> 39.311646 | BC8: =VLOOKUP(A8,'2022_PAPI_Indicators'!A3:BB183,53,FALSE) -> 38.709946 | BD8: =VLOOKUP(A8,'2022_PAPI_Indicators'!A3:BC183,54,FALSE) -> 38.188801 | BE8: =VLOOKUP(A8,'2022_PAPI_Indicators'!A3:BD183,55,FALSE) -> 39.409874 | BF8: =VLOOKUP(A8,'2022_PAPI_Indicators'!A3:BE183,56,FALSE) -> 42.217731 | BG8: =VLOOKUP(A8,'2022_PAPI_Indicators'!A3:BF183,57,FALSE) -> 40.934998 | BH8: =VLOOKUP(A8,'2022_PAPI_Indicators'!A3:BG183,58,FALSE) -> 40.546349 | BI8: =VLOOKUP(A8,'2022_PAPI_Indicators'!A3:BH183,59,FALSE) -> 39.395382 | BJ8: =VLOOKUP(A8,'2022_PAPI_Indicators'!A3:BI183,60,FALSE) -> 39.463318 | BK8: =VLOOKUP(A8,'2022_PAPI_Indicators'!A3:BJ183,61,FALSE) -> 41.10535 | BL8: =VLOOKUP(A8,'2022_PAPI_Indicators'!A3:BK183,62,FALSE) -> 42.855907 | BM8: =VLOOKUP(A8,'2022_PAPI_Indicators'!A3:BL183,63,FALSE) -> 44.911423 | BN8: =VLOOKUP(A8,'2022_PAPI_Indicators'!A3:BM183,64,FALSE) -> 41.874588
A9: Unweighted 95% CI High | B9: Chỉ số PAPI tổng hợp (không có trọng số) - điểm tối đa trong khoảng tin cậy 95% | D9: =VLOOKUP(A9,'2022_PAPI_Indicators'!A5:B185,2,FALSE) -> 44.291763 | E9: =VLOOKUP(A9,'2022_PAPI_Indicators'!A4:C184,3,FALSE) -> 41.598286 | F9: =VLOOKUP(A9,'2022_PAPI_Indicators'!A4:D184,4,FALSE) -> 39.455814 | G9: =VLOOKUP(A9,'2022_PAPI_Indicators'!A4:E184,5,FALSE) -> 43.874245 | H9: =VLOOKUP(A9,'2022_PAPI_Indicators'!A4:F184,6,FALSE) -> 43.587391 | I9: =VLOOKUP(A9,'2022_PAPI_Indicators'!A4:G184,7,FALSE) -> 41.441055 | J9: =VLOOKUP(A9,'2022_PAPI_Indicators'!A4:H184,8,FALSE) -> 42.458645 | K9: =VLOOKUP(A9,'2022_PAPI_Indicators'!A4:I184,9,FALSE) -> 43.318165 | L9: =VLOOKUP(A9,'2022_PAPI_Indicators'!A4:J184,10,FALSE) -> 43.731071 | M9: =VLOOKUP(A9,'2022_PAPI_Indicators'!A4:K184,11,FALSE) -> 43.898331 | N9: =VLOOKUP(A9,'2022_PAPI_Indicators'!A4:L184,12,FALSE) -> 42.396847 | O9: =VLOOKUP(A9,'2022_PAPI_Indicators'!A4:M184,13,FALSE) -> 43.283909 | P9: =VLOOKUP(A9,'2022_PAPI_Indicators'!A4:N184,14,FALSE) -> 45.095333 | Q9: =VLOOKUP(A9,'2022_PAPI_Indicators'!A4:O184,15,FALSE) -> 49.196877 | R9: =VLOOKUP(A9,'2022_PAPI_Indicators'!A4:P184,16,FALSE) -> 0 | S9: =VLOOKUP(A9,'2022_PAPI_Indicators'!A4:R184,17,FALSE) -> 45.41301 | T9: =VLOOKUP(A9,'2022_PAPI_Indicators'!A4:S184,18,FALSE) -> 45.334702 | U9: =VLOOKUP(A9,'2022_PAPI_Indicators'!A4:T184,19,FALSE) -> 0 | V9: =VLOOKUP(A9,'2022_PAPI_Indicators'!A4:U184,20,FALSE) -> 42.663586 | W9: =VLOOKUP(A9,'2022_PAPI_Indicators'!A4:V184,21,FALSE) -> 43.9426 | X9: =VLOOKUP(A9,'2022_PAPI_Indicators'!A4:W184,22,FALSE) -> 45.320244 | Y9: =VLOOKUP(A9,'2022_PAPI_Indicators'!A4:X184,23,FALSE) -> 44.299301 | Z9: =VLOOKUP(A9,'2022_PAPI_Indicators'!A4:Y184,24,FALSE) -> 43.930084 | AA9: =VLOOKUP(A9,'2022_PAPI_Indicators'!A4:Z184,25,FALSE) -> 43.548622 | AB9: =VLOOKUP(A9,'2022_PAPI_Indicators'!A4:AA184,26,FALSE) -> 43.571217 | AC9: =VLOOKUP(A9,'2022_PAPI_Indicators'!A4:AB184,27,FALSE) -> 46.304008 | AD9: =VLOOKUP(A9,'2022_PAPI_Indicators'!A4:AC184,28,FALSE) -> 43.667744 | AE9: =VLOOKUP(A9,'2022_PAPI_Indicators'!A4:AD184,29,FALSE) -> 45.491909 | AF9: =VLOOKUP(A9,'2022_PAPI_Indicators'!A4:AE184,30,FALSE) -> 43.427181 | AG9: =VLOOKUP(A9,'2022_PAPI_Indicators'!A4:AF184,31,FALSE) -> 43.590237 | AH9: =VLOOKUP(A9,'2022_PAPI_Indicators'!A4:AG184,32,FALSE) -> 45.846935 | AI9: =VLOOKUP(A9,'2022_PAPI_Indicators'!A4:AH184,33,FALSE) -> 43.040188 | AJ9: =VLOOKUP(A9,'2022_PAPI_Indicators'!A4:AI184,34,FALSE) -> 43.053692 | AK9: =VLOOKUP(A9,'2022_PAPI_Indicators'!A4:AJ184,35,FALSE) -> 43.314171 | AL9: =VLOOKUP(A9,'2022_PAPI_Indicators'!A4:AK184,36,FALSE) -> 43.028725 | AM9: =VLOOKUP(A9,'2022_PAPI_Indicators'!A4:AL184,37,FALSE) -> 42.165497 | AN9: =VLOOKUP(A9,'2022_PAPI_Indicators'!A4:AM184,38,FALSE) -> 44.524982 | AO9: =VLOOKUP(A9,'2022_PAPI_Indicators'!A4:AN184,39,FALSE) -> 49.327354 | AP9: =VLOOKUP(A9,'2022_PAPI_Indicators'!A4:AO184,40,FALSE) -> 47.752556 | AQ9: =VLOOKUP(A9,'2022_PAPI_Indicators'!A4:AP184,41,FALSE) -> 40.869694 | AR9: =VLOOKUP(A9,'2022_PAPI_Indicators'!A4:AQ184,42,FALSE) -> 41.283104 | AS9: =VLOOKUP(A9,'2022_PAPI_Indicators'!A4:AR184,43,FALSE) -> 43.977493 | AT9: =VLOOKUP(A9,'2022_PAPI_Indicators'!A4:AS184,44,FALSE) -> 41.648468 | AU9: =VLOOKUP(A9,'2022_PAPI_Indicators'!A4:AT184,45,FALSE) -> 41.357018 | AV9: =VLOOKUP(A9,'2022_PAPI_Indicators'!A4:AU184,46,FALSE) -> 40.667568 | AW9: =VLOOKUP(A9,'2022_PAPI_Indicators'!A4:AV184,47,FALSE) -> 40.415588 | AX9: =VLOOKUP(A9,'2022_PAPI_Indicators'!A4:AW184,48,FALSE) -> 49.445641 | AY9: =VLOOKUP(A9,'2022_PAPI_Indicators'!A4:AX184,49,FALSE) -> 41.853271 | AZ9: =VLOOKUP(A9,'2022_PAPI_Indicators'!A4:AY184,50,FALSE) -> 43.162655 | BA9: =VLOOKUP(A9,'2022_PAPI_Indicators'!A4:AZ184,51,FALSE) -> 41.561829 | BB9: =VLOOKUP(A9,'2022_PAPI_Indicators'!A4:BA184,52,FALSE) -> 40.306831 | BC9: =VLOOKUP(A9,'2022_PAPI_Indicators'!A4:BB184,53,FALSE) -> 43.243652 | BD9: =VLOOKUP(A9,'2022_PAPI_Indicators'!A4:BC184,54,FALSE) -> 43.005505 | BE9: =VLOOKUP(A9,'2022_PAPI_Indicators'!A4:BD184,55,FALSE) -> 42.024582 | BF9: =VLOOKUP(A9,'2022_PAPI_Indicators'!A4:BE184,56,FALSE) -> 43.831692 | BG9: =VLOOKUP(A9,'2022_PAPI_Indicators'!A4:BF184,57,FALSE) -> 43.364571 | BH9: =VLOOKUP(A9,'2022_PAPI_Indicators'!A4:BG184,58,FALSE) -> 41.457924 | BI9: =VLOOKUP(A9,'2022_PAPI_Indicators'!A4:BH184,59,FALSE) -> 40.684795 | BJ9: =VLOOKUP(A9,'2022_PAPI_Indicators'!A4:BI184,60,FALSE) -> 40.486176 | BK9: =VLOOKUP(A9,'2022_PAPI_Indicators'!A4:BJ184,61,FALSE) -> 44.077862 | BL9: =VLOOKUP(A9,'2022_PAPI_Indicators'!A4:BK184,62,FALSE) -> 42.855907 | BM9: =VLOOKUP(A9,'2022_PAPI_Indicators'!A4:BL184,63,FALSE) -> 44.911423 | BN9: =VLOOKUP(A9,'2022_PAPI_Indicators'!A4:BM184,64,FALSE) -> 41.874588
A10: Unweighted Standard Error | B10: Chỉ số PAPI tổng hợp (không có trọng số) - sai số | D10: =VLOOKUP(A10,'2022_PAPI_Indicators'!A6:B186,2,FALSE) -> 0.23516178 | E10: =VLOOKUP(A10,'2022_PAPI_Indicators'!A5:C185,3,FALSE) -> 0.27435118 | F10: =VLOOKUP(A10,'2022_PAPI_Indicators'!A5:D185,4,FALSE) -> 0.39640722 | G10: =VLOOKUP(A10,'2022_PAPI_Indicators'!A5:E185,5,FALSE) -> 0.87375492 | H10: =VLOOKUP(A10,'2022_PAPI_Indicators'!A5:F185,6,FALSE) -> 0.29072669 | I10: =VLOOKUP(A10,'2022_PAPI_Indicators'!A5:G185,7,FALSE) -> 0.63439029 | J10: =VLOOKUP(A10,'2022_PAPI_Indicators'!A5:H185,8,FALSE) -> 1.6960737 | K10: =VLOOKUP(A10,'2022_PAPI_Indicators'!A5:I185,9,FALSE) -> 0.38147748 | L10: =VLOOKUP(A10,'2022_PAPI_Indicators'!A5:J185,10,FALSE) -> 1.7396802 | M10: =VLOOKUP(A10,'2022_PAPI_Indicators'!A5:K185,11,FALSE) -> 1.2564471 | N10: =VLOOKUP(A10,'2022_PAPI_Indicators'!A5:L185,12,FALSE) -> 0.84443939 | O10: =VLOOKUP(A10,'2022_PAPI_Indicators'!A5:M185,13,FALSE) -> 0.16271915 | P10: =VLOOKUP(A10,'2022_PAPI_Indicators'!A5:N185,14,FALSE) -> 0.75856733 | Q10: =VLOOKUP(A10,'2022_PAPI_Indicators'!A5:O185,15,FALSE) -> 0.80279803 | R10: =VLOOKUP(A10,'2022_PAPI_Indicators'!A5:P185,16,FALSE) -> 0 | S10: =VLOOKUP(A10,'2022_PAPI_Indicators'!A5:R185,17,FALSE) -> 0.70898169 | T10: =VLOOKUP(A10,'2022_PAPI_Indicators'!A5:S185,18,FALSE) -> 0.62390369 | U10: =VLOOKUP(A10,'2022_PAPI_Indicators'!A5:T185,19,FALSE) -> 0 | V10: =VLOOKUP(A10,'2022_PAPI_Indicators'!A5:U185,20,FALSE) -> 0.3161568 | W10: =VLOOKUP(A10,'2022_PAPI_Indicators'!A5:V185,21,FALSE) -> 0.20612636 | X10: =VLOOKUP(A10,'2022_PAPI_Indicators'!A5:W185,22,FALSE) -> 0.6912778 | Y10: =VLOOKUP(A10,'2022_PAPI_Indicators'!A5:X185,23,FALSE) -> 0.47736824 | Z10: =VLOOKUP(A10,'2022_PAPI_Indicators'!A5:Y185,24,FALSE) -> 0.7276504 | AA10: =VLOOKUP(A10,'2022_PAPI_Indicators'!A5:Z185,25,FALSE) -> 0.24081306 | AB10: =VLOOKUP(A10,'2022_PAPI_Indicators'!A5:AA185,26,FALSE) -> 0.24721676 | AC10: =VLOOKUP(A10,'2022_PAPI_Indicators'!A5:AB185,27,FALSE) -> 0.1754698 | AD10: =VLOOKUP(A10,'2022_PAPI_Indicators'!A5:AC185,28,FALSE) -> 0.25396627 | AE10: =VLOOKUP(A10,'2022_PAPI_Indicators'!A5:AD185,29,FALSE) -> 0.71617573 | AF10: =VLOOKUP(A10,'2022_PAPI_Indicators'!A5:AE185,30,FALSE) -> 0.40471655 | AG10: =VLOOKUP(A10,'2022_PAPI_Indicators'!A5:AF185,31,FALSE) -> 1.1039977 | AH10: =VLOOKUP(A10,'2022_PAPI_Indicators'!A5:AG185,32,FALSE) -> 0.28114432 | AI10: =VLOOKUP(A10,'2022_PAPI_Indicators'!A5:AH185,33,FALSE) -> 0.28562003 | AJ10: =VLOOKUP(A10,'2022_PAPI_Indicators'!A5:AI185,34,FALSE) -> 0.4960534 | AK10: =VLOOKUP(A10,'2022_PAPI_Indicators'!A5:AJ185,35,FALSE) -> 0.23454149 | AL10: =VLOOKUP(A10,'2022_PAPI_Indicators'!A5:AK185,36,FALSE) -> 0.83201498 | AM10: =VLOOKUP(A10,'2022_PAPI_Indicators'!A5:AL185,37,FALSE) -> 0.86516559 | AN10: =VLOOKUP(A10,'2022_PAPI_Indicators'!A5:AM185,38,FALSE) -> 0.66147268 | AO10: =VLOOKUP(A10,'2022_PAPI_Indicators'!A5:AN185,39,FALSE) -> 2.0226173 | AP10: =VLOOKUP(A10,'2022_PAPI_Indicators'!A5:AO185,40,FALSE) -> 1.953112 | AQ10: =VLOOKUP(A10,'2022_PAPI_Indicators'!A5:AP185,41,FALSE) -> 0.54353112 | AR10: =VLOOKUP(A10,'2022_PAPI_Indicators'!A5:AQ185,42,FALSE) -> 0.97842455 | AS10: =VLOOKUP(A10,'2022_PAPI_Indicators'!A5:AR185,43,FALSE) -> 1.7356935 | AT10: =VLOOKUP(A10,'2022_PAPI_Indicators'!A5:AS185,44,FALSE) -> 0.68149513 | AU10: =VLOOKUP(A10,'2022_PAPI_Indicators'!A5:AT185,45,FALSE) -> 0.39350551 | AV10: =VLOOKUP(A10,'2022_PAPI_Indicators'!A5:AU185,46,FALSE) -> 0.44568712 | AW10: =VLOOKUP(A10,'2022_PAPI_Indicators'!A5:AV185,47,FALSE) -> 0.60703444 | AX10: =VLOOKUP(A10,'2022_PAPI_Indicators'!A5:AW185,48,FALSE) -> 1.213912 | AY10: =VLOOKUP(A10,'2022_PAPI_Indicators'!A5:AX185,49,FALSE) -> 0.3587358 | AZ10: =VLOOKUP(A10,'2022_PAPI_Indicators'!A5:AY185,50,FALSE) -> 0.71108896 | BA10: =VLOOKUP(A10,'2022_PAPI_Indicators'!A5:AZ185,51,FALSE) -> 0.32915464 | BB10: =VLOOKUP(A10,'2022_PAPI_Indicators'!A5:BA185,52,FALSE) -> 0.30249527 | BC10: =VLOOKUP(A10,'2022_PAPI_Indicators'!A5:BB185,53,FALSE) -> 1.3780559 | BD10: =VLOOKUP(A10,'2022_PAPI_Indicators'!A5:BC185,54,FALSE) -> 1.4640754 | BE10: =VLOOKUP(A10,'2022_PAPI_Indicators'!A5:BD185,55,FALSE) -> 0.79476118 | BF10: =VLOOKUP(A10,'2022_PAPI_Indicators'!A5:BE185,56,FALSE) -> 0.4905751 | BG10: =VLOOKUP(A10,'2022_PAPI_Indicators'!A5:BF185,57,FALSE) -> 0.73848695 | BH10: =VLOOKUP(A10,'2022_PAPI_Indicators'!A5:BG185,58,FALSE) -> 0.27707952 | BI10: =VLOOKUP(A10,'2022_PAPI_Indicators'!A5:BH185,59,FALSE) -> 0.39192814 | BJ10: =VLOOKUP(A10,'2022_PAPI_Indicators'!A5:BI185,60,FALSE) -> 0.31090513 | BK10: =VLOOKUP(A10,'2022_PAPI_Indicators'!A5:BJ185,61,FALSE) -> 0.90351772 | BL10: =VLOOKUP(A10,'2022_PAPI_Indicators'!A5:BK185,62,FALSE) -> 0 | BM10: =VLOOKUP(A10,'2022_PAPI_Indicators'!A5:BL185,63,FALSE) -> 0 | BN10: =VLOOKUP(A10,'2022_PAPI_Indicators'!A5:BM185,64,FALSE) -> 0
A11: Dimension 1: Participation | B11: Chỉ số nội dung 1: Tham gia của người dân ở cấp cơ sở | C11: 1-10 điểm/points | D11: =VLOOKUP(A11,'2022_PAPI_Indicators'!A6:B186,2,) -> 5.8254476 | E11: =VLOOKUP(A11,'2022_PAPI_Indicators'!A6:C186,3,FALSE) -> 4.9973364 | F11: =VLOOKUP(A11,'2022_PAPI_Indicators'!A6:D186,4,FALSE) -> 4.4906936 | G11: =VLOOKUP(A11,'2022_PAPI_Indicators'!A6:E186,5,FALSE) -> 5.3885055 | H11: =VLOOKUP(A11,'2022_PAPI_Indicators'!A6:F186,6,FALSE) -> 5.2460127 | I11: =VLOOKUP(A11,'2022_PAPI_Indicators'!A6:G186,7,FALSE) -> 5.0275598 | J11: =VLOOKUP(A11,'2022_PAPI_Indicators'!A6:H186,8,FALSE) -> 4.438293 | K11: =VLOOKUP(A11,'2022_PAPI_Indicators'!A6:I186,9,FALSE) -> 5.5805297 | L11: =VLOOKUP(A11,'2022_PAPI_Indicators'!A6:J186,10,FALSE) -> 4.7769065 | M11: =VLOOKUP(A11,'2022_PAPI_Indicators'!A6:K186,11,FALSE) -> 4.9544053 | N11: =VLOOKUP(A11,'2022_PAPI_Indicators'!A6:L186,12,FALSE) -> 5.0889664 | O11: =VLOOKUP(A11,'2022_PAPI_Indicators'!A6:M186,13,FALSE) -> 5.3816071 | P11: =VLOOKUP(A11,'2022_PAPI_Indicators'!A6:N186,14,FALSE) -> 5.8164401 | Q11: =VLOOKUP(A11,'2022_PAPI_Indicators'!A6:O186,15,FALSE) -> 5.7475762 | R11: =VLOOKUP(A11,'2022_PAPI_Indicators'!A6:P186,16,FALSE) -> 0 | S11: =VLOOKUP(A11,'2022_PAPI_Indicators'!A6:R186,17,FALSE) -> 5.7516823 | T11: =VLOOKUP(A11,'2022_PAPI_Indicators'!A6:S186,18,FALSE) -> 5.4361572 | U11: =VLOOKUP(A11,'2022_PAPI_Indicators'!A6:T186,19,FALSE) -> 5.8174157 | V11: =VLOOKUP(A11,'2022_PAPI_Indicators'!A6:U186,20,FALSE) -> 5.334476 | W11: =VLOOKUP(A11,'2022_PAPI_Indicators'!A6:V186,21,FALSE) -> 5.3938642 | X11: =VLOOKUP(A11,'2022_PAPI_Indicators'!A6:W186,22,FALSE) -> 5.4940963 | Y11: =VLOOKUP(A11,'2022_PAPI_Indicators'!A6:X186,23,FALSE) -> 5.3871198 | Z11: =VLOOKUP(A11,'2022_PAPI_Indicators'!A6:Y186,24,FALSE) -> 5.0631166 | AA11: =VLOOKUP(A11,'2022_PAPI_Indicators'!A6:Z186,25,FALSE) -> 5.6298561 | AB11: =VLOOKUP(A11,'2022_PAPI_Indicators'!A6:AA186,26,FALSE) -> 5.2587337 | AC11: =VLOOKUP(A11,'2022_PAPI_Indicators'!A6:AB186,27,FALSE) -> 6.1073642 | AD11: =VLOOKUP(A11,'2022_PAPI_Indicators'!A6:AC186,28,FALSE) -> 5.6093493 | AE11: =VLOOKUP(A11,'2022_PAPI_Indicators'!A6:AD186,29,FALSE) -> 5.3757567 | AF11: =VLOOKUP(A11,'2022_PAPI_Indicators'!A6:AE186,30,FALSE) -> 4.9196992 | AG11: =VLOOKUP(A11,'2022_PAPI_Indicators'!A6:AF186,31,FALSE) -> 4.9741263 | AH11: =VLOOKUP(A11,'2022_PAPI_Indicators'!A6:AG186,32,FALSE) -> 5.7721181 | AI11: =VLOOKUP(A11,'2022_PAPI_Indicators'!A6:AH186,33,FALSE) -> 4.4935174 | AJ11: =VLOOKUP(A11,'2022_PAPI_Indicators'!A6:AI186,34,FALSE) -> 4.7812653 | AK11: =VLOOKUP(A11,'2022_PAPI_Indicators'!A6:AJ186,35,FALSE) -> 5.0435991 | AL11: =VLOOKUP(A11,'2022_PAPI_Indicators'!A6:AK186,36,FALSE) -> 4.3365436 | AM11: =VLOOKUP(A11,'2022_PAPI_Indicators'!A6:AL186,37,FALSE) -> 4.3876119 | AN11: =VLOOKUP(A11,'2022_PAPI_Indicators'!A6:AM186,38,FALSE) -> 4.4982848 | AO11: =VLOOKUP(A11,'2022_PAPI_Indicators'!A6:AN186,39,FALSE) -> 5.4048333 | AP11: =VLOOKUP(A11,'2022_PAPI_Indicators'!A6:AO186,40,FALSE) -> 5.4278936 | AQ11: =VLOOKUP(A11,'2022_PAPI_Indicators'!A6:AP186,41,FALSE) -> 4.7477837 | AR11: =VLOOKUP(A11,'2022_PAPI_Indicators'!A6:AQ186,42,FALSE) -> 5.0252843 | AS11: =VLOOKUP(A11,'2022_PAPI_Indicators'!A6:AR186,43,FALSE) -> 5.1387873 | AT11: =VLOOKUP(A11,'2022_PAPI_Indicators'!A6:AS186,44,FALSE) -> 4.7923436 | AU11: =VLOOKUP(A11,'2022_PAPI_Indicators'!A6:AT186,45,FALSE) -> 5.0606523 | AV11: =VLOOKUP(A11,'2022_PAPI_Indicators'!A6:AU186,46,FALSE) -> 5.0272536 | AW11: =VLOOKUP(A11,'2022_PAPI_Indicators'!A6:AV186,47,FALSE) -> 4.2720084 | AX11: =VLOOKUP(A11,'2022_PAPI_Indicators'!A6:AW186,48,FALSE) -> 5.9493718 | AY11: =VLOOKUP(A11,'2022_PAPI_Indicators'!A6:AX186,49,FALSE) -> 4.7767591 | AZ11: =VLOOKUP(A11,'2022_PAPI_Indicators'!A6:AY186,50,FALSE) -> 4.3234725 | BA11: =VLOOKUP(A11,'2022_PAPI_Indicators'!A6:AZ186,51,FALSE) -> 4.5682454 | BB11: =VLOOKUP(A11,'2022_PAPI_Indicators'!A6:BA186,52,FALSE) -> 4.8123226 | BC11: =VLOOKUP(A11,'2022_PAPI_Indicators'!A6:BB186,53,FALSE) -> 4.063168 | BD11: =VLOOKUP(A11,'2022_PAPI_Indicators'!A6:BC186,54,FALSE) -> 4.2259784 | BE11: =VLOOKUP(A11,'2022_PAPI_Indicators'!A6:BD186,55,FALSE) -> 4.1161256 | BF11: =VLOOKUP(A11,'2022_PAPI_Indicators'!A6:BE186,56,FALSE) -> 4.5832973 | BG11: =VLOOKUP(A11,'2022_PAPI_Indicators'!A6:BF186,57,FALSE) -> 4.3295116 | BH11: =VLOOKUP(A11,'2022_PAPI_Indicators'!A6:BG186,58,FALSE) -> 4.4517913 | BI11: =VLOOKUP(A11,'2022_PAPI_Indicators'!A6:BH186,59,FALSE) -> 3.7754788 | BJ11: =VLOOKUP(A11,'2022_PAPI_Indicators'!A6:BI186,60,FALSE) -> 3.711127 | BK11: =VLOOKUP(A11,'2022_PAPI_Indicators'!A6:BJ186,61,FALSE) -> 4.2705483 | BL11: =VLOOKUP(A11,'2022_PAPI_Indicators'!A6:BK186,62,FALSE) -> 4.492063 | BM11: =VLOOKUP(A11,'2022_PAPI_Indicators'!A6:BL186,63,FALSE) -> 5.0389547 | BN11: =VLOOKUP(A11,'2022_PAPI_Indicators'!A6:BM186,64,FALSE) -> 4.177804
A12: Civic Knowledge | B12: 1.1: Tri thức công dân | C12: 0.25-2.5 điểm | D12: =VLOOKUP(A12,'2022_PAPI_Indicators'!A7:B187,2,) -> 1.2902536 | E12: =VLOOKUP(A12,'2022_PAPI_Indicators'!A7:C187,3,FALSE) -> 0.8524285 | F12: =VLOOKUP(A12,'2022_PAPI_Indicators'!A7:D187,4,FALSE) -> 0.85104495 | G12: =VLOOKUP(A12,'2022_PAPI_Indicators'!A7:E187,5,FALSE) -> 1.0590185 | H12: =VLOOKUP(A12,'2022_PAPI_Indicators'!A7:F187,6,FALSE) -> 0.92048329 | I12: =VLOOKUP(A12,'2022_PAPI_Indicators'!A7:G187,7,FALSE) -> 0.92007864 | J12: =VLOOKUP(A12,'2022_PAPI_Indicators'!A7:H187,8,FALSE) -> 0.67026371 | K12: =VLOOKUP(A12,'2022_PAPI_Indicators'!A7:I187,9,FALSE) -> 1.1388193 | L12: =VLOOKUP(A12,'2022_PAPI_Indicators'!A7:J187,10,FALSE) -> 0.8984074 | M12: =VLOOKUP(A12,'2022_PAPI_Indicators'!A7:K187,11,FALSE) -> 0.93147165 | N12: =VLOOKUP(A12,'2022_PAPI_Indicators'!A7:L187,12,FALSE) -> 0.88282299 | O12: =VLOOKUP(A12,'2022_PAPI_Indicators'!A7:M187,13,FALSE) -> 1.1097713 | P12: =VLOOKUP(A12,'2022_PAPI_Indicators'!A7:N187,14,FALSE) -> 1.0883383 | Q12: =VLOOKUP(A12,'2022_PAPI_Indicators'!A7:O187,15,FALSE) -> 1.3968127 | R12: =VLOOKUP(A12,'2022_PAPI_Indicators'!A7:P187,16,FALSE) -> 0 | S12: =VLOOKUP(A12,'2022_PAPI_Indicators'!A7:R187,17,FALSE) -> 1.1729802 | T12: =VLOOKUP(A12,'2022_PAPI_Indicators'!A7:S187,18,FALSE) -> 1.1823511 | U12: =VLOOKUP(A12,'2022_PAPI_Indicators'!A7:T187,19,FALSE) -> 1.3509467 | V12: =VLOOKUP(A12,'2022_PAPI_Indicators'!A7:U187,20,FALSE) -> 1.0244768 | W12: =VLOOKUP(A12,'2022_PAPI_Indicators'!A7:V187,21,FALSE) -> 0.9929195 | X12: =VLOOKUP(A12,'2022_PAPI_Indicators'!A7:W187,22,FALSE) -> 1.126838 | Y12: =VLOOKUP(A12,'2022_PAPI_Indicators'!A7:X187,23,FALSE) -> 1.1201975 | Z12: =VLOOKUP(A12,'2022_PAPI_Indicators'!A7:Y187,24,FALSE) -> 0.99119818 | AA12: =VLOOKUP(A12,'2022_PAPI_Indicators'!A7:Z187,25,FALSE) -> 1.0403043 | AB12: =VLOOKUP(A12,'2022_PAPI_Indicators'!A7:AA187,26,FALSE) -> 1.0206527 | AC12: =VLOOKUP(A12,'2022_PAPI_Indicators'!A7:AB187,27,FALSE) -> 1.2935107 | AD12: =VLOOKUP(A12,'2022_PAPI_Indicators'!A7:AC187,28,FALSE) -> 1.1703758 | AE12: =VLOOKUP(A12,'2022_PAPI_Indicators'!A7:AD187,29,FALSE) -> 1.0169487 | AF12: =VLOOKUP(A12,'2022_PAPI_Indicators'!A7:AE187,30,FALSE) -> 0.9764145 | AG12: =VLOOKUP(A12,'2022_PAPI_Indicators'!A7:AF187,31,FALSE) -> 0.93942249 | AH12: =VLOOKUP(A12,'2022_PAPI_Indicators'!A7:AG187,32,FALSE) -> 1.1248075 | AI12: =VLOOKUP(A12,'2022_PAPI_Indicators'!A7:AH187,33,FALSE) -> 1.1115048 | AJ12: =VLOOKUP(A12,'2022_PAPI_Indicators'!A7:AI187,34,FALSE) -> 1.112101 | AK12: =VLOOKUP(A12,'2022_PAPI_Indicators'!A7:AJ187,35,FALSE) -> 1.1002645 | AL12: =VLOOKUP(A12,'2022_PAPI_Indicators'!A7:AK187,36,FALSE) -> 0.88206303 | AM12: =VLOOKUP(A12,'2022_PAPI_Indicators'!A7:AL187,37,FALSE) -> 0.87195921 | AN12: =VLOOKUP(A12,'2022_PAPI_Indicators'!A7:AM187,38,FALSE) -> 1.0463156 | AO12: =VLOOKUP(A12,'2022_PAPI_Indicators'!A7:AN187,39,FALSE) -> 1.2066787 | AP12: =VLOOKUP(A12,'2022_PAPI_Indicators'!A7:AO187,40,FALSE) -> 0.9538914 | AQ12: =VLOOKUP(A12,'2022_PAPI_Indicators'!A7:AP187,41,FALSE) -> 0.83089882 | AR12: =VLOOKUP(A12,'2022_PAPI_Indicators'!A7:AQ187,42,FALSE) -> 0.90518898 | AS12: =VLOOKUP(A12,'2022_PAPI_Indicators'!A7:AR187,43,FALSE) -> 0.99547279 | AT12: =VLOOKUP(A12,'2022_PAPI_Indicators'!A7:AS187,44,FALSE) -> 0.96308303 | AU12: =VLOOKUP(A12,'2022_PAPI_Indicators'!A7:AT187,45,FALSE) -> 1.0140576 | AV12: =VLOOKUP(A12,'2022_PAPI_Indicators'!A7:AU187,46,FALSE) -> 1.0476226 | AW12: =VLOOKUP(A12,'2022_PAPI_Indicators'!A7:AV187,47,FALSE) -> 0.85741973 | AX12: =VLOOKUP(A12,'2022_PAPI_Indicators'!A7:AW187,48,FALSE) -> 1.2565695 | AY12: =VLOOKUP(A12,'2022_PAPI_Indicators'!A7:AX187,49,FALSE) -> 1.0599449 | AZ12: =VLOOKUP(A12,'2022_PAPI_Indicators'!A7:AY187,50,FALSE) -> 1.1245034 | BA12: =VLOOKUP(A12,'2022_PAPI_Indicators'!A7:AZ187,51,FALSE) -> 0.92631185 | BB12: =VLOOKUP(A12,'2022_PAPI_Indicators'!A7:BA187,52,FALSE) -> 0.9038102 | BC12: =VLOOKUP(A12,'2022_PAPI_Indicators'!A7:BB187,53,FALSE) -> 0.84060413 | BD12: =VLOOKUP(A12,'2022_PAPI_Indicators'!A7:BC187,54,FALSE) -> 0.7469399 | BE12: =VLOOKUP(A12,'2022_PAPI_Indicators'!A7:BD187,55,FALSE) -> 0.86559451 | BF12: =VLOOKUP(A12,'2022_PAPI_Indicators'!A7:BE187,56,FALSE) -> 1.0388256 | BG12: =VLOOKUP(A12,'2022_PAPI_Indicators'!A7:BF187,57,FALSE) -> 0.79635429 | BH12: =VLOOKUP(A12,'2022_PAPI_Indicators'!A7:BG187,58,FALSE) -> 0.75430393 | BI12: =VLOOKUP(A12,'2022_PAPI_Indicators'!A7:BH187,59,FALSE) -> 0.76570642 | BJ12: =VLOOKUP(A12,'2022_PAPI_Indicators'!A7:BI187,60,FALSE) -> 0.70996755 | BK12: =VLOOKUP(A12,'2022_PAPI_Indicators'!A7:BJ187,61,FALSE) -> 0.93277735 | BL12: =VLOOKUP(A12,'2022_PAPI_Indicators'!A7:BK187,62,FALSE) -> 0.88113147 | BM12: =VLOOKUP(A12,'2022_PAPI_Indicators'!A7:BL187,63,FALSE) -> 1.1367943 | BN12: =VLOOKUP(A12,'2022_PAPI_Indicators'!A7:BM187,64,FALSE) -> 0.98122859
A13: Proportion with Civic Knowledge | B13: Hiểu biết về chính sách hiện hành (%) | C13: 0%-100% | D13: =VLOOKUP(A13,'2022_PAPI_Indicators'!A8:B188,2, FALSE) -> 0.67658985 | E13: 0.43581903 | F13: 0.44629556 | G13: 0.57596636 | H13: 0.46699661 | I13: 0.48171157 | J13: 0.31916142 | K13: 0.52844673 | L13: 0.46629402 | M13: 0.50095612 | N13: 0.46893588 | O13: 0.54792607 | P13: 0.53961515 | Q13: 0.69288844 | R13: =VLOOKUP(A13,'2022_PAPI_Indicators'!A8:P188,16,FALSE) -> 0 | S13: 0.53720683 | T13: 0.57189351 | U13: 0.81537098 | V13: 0.46294346 | W13: 0.41227141 | X13: 0.55237967 | Y13: 0.4691762 | Z13: 0.44025752 | AA13: 0.52450961 | AB13: 0.38741013 | AC13: 0.63067544 | AD13: 0.66341233 | AE13: 0.52679646 | AF13: 0.54764712 | AG13: 0.55660522 | AH13: 0.62320167 | AI13: 0.61847615 | AJ13: 0.57207859 | AK13: 0.60019684 | AL13: 0.42103681 | AM13: 0.39798355 | AN13: 0.6487866 | AO13: 0.69148958 | AP13: 0.63496542 | AQ13: 0.4686417 | AR13: 0.50565881 | AS13: 0.48533183 | AT13: 0.55154967 | AU13: 0.64805692 | AV13: 0.39637375 | AW13: 0.38860178 | AX13: 0.80665302 | AY13: 0.562859 | AZ13: 0.60105675 | BA13: 0.49248683 | BB13: 0.45162779 | BC13: 0.39247626 | BD13: 0.30962282 | BE13: 0.38950348 | BF13: 0.56799775 | BG13: 0.39571807 | BH13: 0.34405887 | BI13: 0.34905931 | BJ13: 0.37604687 | BK13: 0.461418 | BL13: 0.39220703 | BM13: 0.60810333 | BN13: 0.51529181
A14: Knowledge of Leaders | B14: Hiểu biết về vị trí lãnh đạo (%) | C14: 0%-100% | D14: =VLOOKUP(A14,'2022_PAPI_Indicators'!A9:B189,2, FALSE) -> 0.586375 | E14: =VLOOKUP(A14,'2022_PAPI_Indicators'!A9:C189,3,FALSE) -> 0.31758249 | F14: =VLOOKUP(A14,'2022_PAPI_Indicators'!A9:D189,4,FALSE) -> 0.3111144 | G14: =VLOOKUP(A14,'2022_PAPI_Indicators'!A9:E189,5,FALSE) -> 0.43114442 | H14: =VLOOKUP(A14,'2022_PAPI_Indicators'!A9:F189,6,FALSE) -> 0.36248684 | I14: =VLOOKUP(A14,'2022_PAPI_Indicators'!A9:G189,7,FALSE) -> 0.35476965 | J14: =VLOOKUP(A14,'2022_PAPI_Indicators'!A9:H189,8,FALSE) -> 0.21398705 | K14: =VLOOKUP(A14,'2022_PAPI_Indicators'!A9:I189,9,FALSE) -> 0.52583826 | L14: =VLOOKUP(A14,'2022_PAPI_Indicators'!A9:J189,10,FALSE) -> 0.34321511 | M14: =VLOOKUP(A14,'2022_PAPI_Indicators'!A9:K189,11,FALSE) -> 0.35527453 | N14: =VLOOKUP(A14,'2022_PAPI_Indicators'!A9:L189,12,FALSE) -> 0.32804137 | O14: =VLOOKUP(A14,'2022_PAPI_Indicators'!A9:M189,13,FALSE) -> 0.49027807 | P14: =VLOOKUP(A14,'2022_PAPI_Indicators'!A9:N189,14,FALSE) -> 0.475382 | Q14: =VLOOKUP(A14,'2022_PAPI_Indicators'!A9:O189,15,FALSE) -> 0.67294484 | R14: =VLOOKUP(A14,'2022_PAPI_Indicators'!A9:P189,16,FALSE) -> 0 | S14: =VLOOKUP(A14,'2022_PAPI_Indicators'!A9:R189,17,FALSE) -> 0.55182344 | T14: =VLOOKUP(A14,'2022_PAPI_Indicators'!A9:S189,18,FALSE) -> 0.54280978 | U14: =VLOOKUP(A14,'2022_PAPI_Indicators'!A9:T189,19,FALSE) -> 0.57093376 | V14: =VLOOKUP(A14,'2022_PAPI_Indicators'!A9:U189,20,FALSE) -> 0.4569521 | W14: =VLOOKUP(A14,'2022_PAPI_Indicators'!A9:V189,21,FALSE) -> 0.45423722 | X14: =VLOOKUP(A14,'2022_PAPI_Indicators'!A9:W189,22,FALSE) -> 0.50322169 | Y14: =VLOOKUP(A14,'2022_PAPI_Indicators'!A9:X189,23,FALSE) -> 0.53892082 | Z14: =VLOOKUP(A14,'2022_PAPI_Indicators'!A9:Y189,24,FALSE) -> 0.43871406 | AA14: =VLOOKUP(A14,'2022_PAPI_Indicators'!A9:Z189,25,FALSE) -> 0.44023794 | AB14: =VLOOKUP(A14,'2022_PAPI_Indicators'!A9:AA189,26,FALSE) -> 0.49131957 | AC14: =VLOOKUP(A14,'2022_PAPI_Indicators'!A9:AB189,27,FALSE) -> 0.61222732 | AD14: =VLOOKUP(A14,'2022_PAPI_Indicators'!A9:AC189,28,FALSE) -> 0.48640567 | AE14: =VLOOKUP(A14,'2022_PAPI_Indicators'!A9:AD189,29,FALSE) -> 0.41833395 | AF14: =VLOOKUP(A14,'2022_PAPI_Indicators'!A9:AE189,30,FALSE) -> 0.37187824 | AG14: =VLOOKUP(A14,'2022_PAPI_Indicators'!A9:AF189,31,FALSE) -> 0.33451739 | AH14: =VLOOKUP(A14,'2022_PAPI_Indicators'!A9:AG189,32,FALSE) -> 0.46600586 | AI14: =VLOOKUP(A14,'2022_PAPI_Indicators'!A9:AH189,33,FALSE) -> 0.45654395 | AJ14: =VLOOKUP(A14,'2022_PAPI_Indicators'!A9:AI189,34,FALSE) -> 0.48027265 | AK14: =VLOOKUP(A14,'2022_PAPI_Indicators'!A9:AJ189,35,FALSE) -> 0.45569226 | AL14: =VLOOKUP(A14,'2022_PAPI_Indicators'!A9:AK189,36,FALSE) -> 0.35131538 | AM14: =VLOOKUP(A14,'2022_PAPI_Indicators'!A9:AL189,37,FALSE) -> 0.35386086 | AN14: =VLOOKUP(A14,'2022_PAPI_Indicators'!A9:AM189,38,FALSE) -> 0.38344273 | AO14: =VLOOKUP(A14,'2022_PAPI_Indicators'!A9:AN189,39,FALSE) -> 0.50463635 | AP14: =VLOOKUP(A14,'2022_PAPI_Indicators'!A9:AO189,40,FALSE) -> 0.30819854 | AQ14: =VLOOKUP(A14,'2022_PAPI_Indicators'!A9:AP189,41,FALSE) -> 0.28203365 | AR14: =VLOOKUP(A14,'2022_PAPI_Indicators'!A9:AQ189,42,FALSE) -> 0.32956079 | AS14: =VLOOKUP(A14,'2022_PAPI_Indicators'!A9:AR189,43,FALSE) -> 0.41997656 | AT14: =VLOOKUP(A14,'2022_PAPI_Indicators'!A9:AS189,44,FALSE) -> 0.35807675 | AU14: =VLOOKUP(A14,'2022_PAPI_Indicators'!A9:AT189,45,FALSE) -> 0.35513392 | AV14: =VLOOKUP(A14,'2022_PAPI_Indicators'!A9:AU189,46,FALSE) -> 0.51081097 | AW14: =VLOOKUP(A14,'2022_PAPI_Indicators'!A9:AV189,47,FALSE) -> 0.34562773 | AX14: =VLOOKUP(A14,'2022_PAPI_Indicators'!A9:AW189,48,FALSE) -> 0.49140191 | AY14: =VLOOKUP(A14,'2022_PAPI_Indicators'!A9:AX189,49,FALSE) -> 0.43852153 | AZ14: =VLOOKUP(A14,'2022_PAPI_Indicators'!A9:AY189,50,FALSE) -> 0.47680795 | BA14: =VLOOKUP(A14,'2022_PAPI_Indicators'!A9:AZ189,51,FALSE) -> 0.35492265 | BB14: =VLOOKUP(A14,'2022_PAPI_Indicators'!A9:BA189,52,FALSE) -> 0.3553507 | BC14: =VLOOKUP(A14,'2022_PAPI_Indicators'!A9:BB189,53,FALSE) -> 0.32874331 | BD14: =VLOOKUP(A14,'2022_PAPI_Indicators'!A9:BC189,54,FALSE) -> 0.28691295 | BE14: =VLOOKUP(A14,'2022_PAPI_Indicators'!A9:BD189,55,FALSE) -> 0.3524434 | BF14: =VLOOKUP(A14,'2022_PAPI_Indicators'!A9:BE189,56,FALSE) -> 0.41717947 | BG14: =VLOOKUP(A14,'2022_PAPI_Indicators'!A9:BF189,57,FALSE) -> 0.28778923 | BH14: =VLOOKUP(A14,'2022_PAPI_Indicators'!A9:BG189,58,FALSE) -> 0.27624071 | BI14: =VLOOKUP(A14,'2022_PAPI_Indicators'!A9:BH189,59,FALSE) -> 0.28387603 | BJ14: =VLOOKUP(A14,'2022_PAPI_Indicators'!A9:BI189,60,FALSE) -> 0.22083662 | BK14: =VLOOKUP(A14,'2022_PAPI_Indicators'!A9:BJ189,61,FALSE) -> 0.37620419 | BL14: =VLOOKUP(A14,'2022_PAPI_Indicators'!A9:BK189,62,FALSE) -> 0.36490226 | BM14: =VLOOKUP(A14,'2022_PAPI_Indicators'!A9:BL189,63,FALSE) -> 0.48420998 | BN14: =VLOOKUP(A14,'2022_PAPI_Indicators'!A9:BM189,64,FALSE) -> 0.39233506
A15: Opportunties for Participation in Elections | B15: 1.2: Cơ hội tham gia | C15: 0.25-2.5 điểm/points | D15: =VLOOKUP(A15,'2022_PAPI_Indicators'!A10:B190,2, FALSE) -> 1.6858891 | E15: =VLOOKUP(A15,'2022_PAPI_Indicators'!A10:C190,3,FALSE) -> 1.6748725 | F15: =VLOOKUP(A15,'2022_PAPI_Indicators'!A10:D190,4,FALSE) -> 1.4802313 | G15: =VLOOKUP(A15,'2022_PAPI_Indicators'!A10:E190,5,FALSE) -> 1.7379497 | H15: =VLOOKUP(A15,'2022_PAPI_Indicators'!A10:F190,6,FALSE) -> 1.4591824 | I15: =VLOOKUP(A15,'2022_PAPI_Indicators'!A10:G190,7,FALSE) -> 1.5429832 | J15: =VLOOKUP(A15,'2022_PAPI_Indicators'!A10:H190,8,FALSE) -> 1.4482298 | K15: =VLOOKUP(A15,'2022_PAPI_Indicators'!A10:I190,9,FALSE) -> 1.6255341 | L15: =VLOOKUP(A15,'2022_PAPI_Indicators'!A10:J190,10,FALSE) -> 1.491834 | M15: =VLOOKUP(A15,'2022_PAPI_Indicators'!A10:K190,11,FALSE) -> 1.4510061 | N15: =VLOOKUP(A15,'2022_PAPI_Indicators'!A10:L190,12,FALSE) -> 1.6131388 | O15: =VLOOKUP(A15,'2022_PAPI_Indicators'!A10:M190,13,FALSE) -> 1.646663 | P15: =VLOOKUP(A15,'2022_PAPI_Indicators'!A10:N190,14,FALSE) -> 1.8705709 | Q15: =VLOOKUP(A15,'2022_PAPI_Indicators'!A10:O190,15,FALSE) -> 1.7197329 | R15: =VLOOKUP(A15,'2022_PAPI_Indicators'!A10:P190,16,FALSE) -> 0 | S15: =VLOOKUP(A15,'2022_PAPI_Indicators'!A10:R190,17,FALSE) -> 1.6887547 | T15: =VLOOKUP(A15,'2022_PAPI_Indicators'!A10:S190,18,FALSE) -> 1.5847507 | U15: =VLOOKUP(A15,'2022_PAPI_Indicators'!A10:T190,19,FALSE) -> 1.6553538 | V15: =VLOOKUP(A15,'2022_PAPI_Indicators'!A10:U190,20,FALSE) -> 1.5862805 | W15: =VLOOKUP(A15,'2022_PAPI_Indicators'!A10:V190,21,FALSE) -> 1.6587526 | X15: =VLOOKUP(A15,'2022_PAPI_Indicators'!A10:W190,22,FALSE) -> 1.7242151 | Y15: =VLOOKUP(A15,'2022_PAPI_Indicators'!A10:X190,23,FALSE) -> 1.6582761 | Z15: =VLOOKUP(A15,'2022_PAPI_Indicators'!A10:Y190,24,FALSE) -> 1.3520112 | AA15: =VLOOKUP(A15,'2022_PAPI_Indicators'!A10:Z190,25,FALSE) -> 1.8323445 | AB15: =VLOOKUP(A15,'2022_PAPI_Indicators'!A10:AA190,26,FALSE) -> 1.5946207 | AC15: =VLOOKUP(A15,'2022_PAPI_Indicators'!A10:AB190,27,FALSE) -> 1.8365793 | AD15: =VLOOKUP(A15,'2022_PAPI_Indicators'!A10:AC190,28,FALSE) -> 1.6218816 | AE15: =VLOOKUP(A15,'2022_PAPI_Indicators'!A10:AD190,29,FALSE) -> 1.555583 | AF15: =VLOOKUP(A15,'2022_PAPI_Indicators'!A10:AE190,30,FALSE) -> 1.4092005 | AG15: =VLOOKUP(A15,'2022_PAPI_Indicators'!A10:AF190,31,FALSE) -> 1.619221 | AH15: =VLOOKUP(A15,'2022_PAPI_Indicators'!A10:AG190,32,FALSE) -> 1.7578712 | AI15: =VLOOKUP(A15,'2022_PAPI_Indicators'!A10:AH190,33,FALSE) -> 1.2245728 | AJ15: =VLOOKUP(A15,'2022_PAPI_Indicators'!A10:AI190,34,FALSE) -> 1.4838569 | AK15: =VLOOKUP(A15,'2022_PAPI_Indicators'!A10:AJ190,35,FALSE) -> 1.3661906 | AL15: =VLOOKUP(A15,'2022_PAPI_Indicators'!A10:AK190,36,FALSE) -> 1.2528048 | AM15: =VLOOKUP(A15,'2022_PAPI_Indicators'!A10:AL190,37,FALSE) -> 1.2769681 | AN15: =VLOOKUP(A15,'2022_PAPI_Indicators'!A10:AM190,38,FALSE) -> 1.2934741 | AO15: =VLOOKUP(A15,'2022_PAPI_Indicators'!A10:AN190,39,FALSE) -> 1.5693754 | AP15: =VLOOKUP(A15,'2022_PAPI_Indicators'!A10:AO190,40,FALSE) -> 1.4772862 | AQ15: =VLOOKUP(A15,'2022_PAPI_Indicators'!A10:AP190,41,FALSE) -> 1.2758796 | AR15: =VLOOKUP(A15,'2022_PAPI_Indicators'!A10:AQ190,42,FALSE) -> 1.3779695 | AS15: =VLOOKUP(A15,'2022_PAPI_Indicators'!A10:AR190,43,FALSE) -> 1.2940778 | AT15: =VLOOKUP(A15,'2022_PAPI_Indicators'!A10:AS190,44,FALSE) -> 1.3254147 | AU15: =VLOOKUP(A15,'2022_PAPI_Indicators'!A10:AT190,45,FALSE) -> 1.6073618 | AV15: =VLOOKUP(A15,'2022_PAPI_Indicators'!A10:AU190,46,FALSE) -> 1.4291593 | AW15: =VLOOKUP(A15,'2022_PAPI_Indicators'!A10:AV190,47,FALSE) -> 1.3203039 | AX15: =VLOOKUP(A15,'2022_PAPI_Indicators'!A10:AW190,48,FALSE) -> 1.6840084 | AY15: =VLOOKUP(A15,'2022_PAPI_Indicators'!A10:AX190,49,FALSE) -> 1.2321833 | AZ15: =VLOOKUP(A15,'2022_PAPI_Indicators'!A10:AY190,50,FALSE) -> 1.1562206 | BA15: =VLOOKUP(A15,'2022_PAPI_Indicators'!A10:AZ190,51,FALSE) -> 1.1008694 | BB15: =VLOOKUP(A15,'2022_PAPI_Indicators'!A10:BA190,52,FALSE) -> 1.2320647 | BC15: =VLOOKUP(A15,'2022_PAPI_Indicators'!A10:BB190,53,FALSE) -> 1.0187954 | BD15: =VLOOKUP(A15,'2022_PAPI_Indicators'!A10:BC190,54,FALSE) -> 1.2090013 | BE15: =VLOOKUP(A15,'2022_PAPI_Indicators'!A10:BD190,55,FALSE) -> 1.0226616 | BF15: =VLOOKUP(A15,'2022_PAPI_Indicators'!A10:BE190,56,FALSE) -> 1.2073089 | BG15: =VLOOKUP(A15,'2022_PAPI_Indicators'!A10:BF190,57,FALSE) -> 1.0155619 | BH15: =VLOOKUP(A15,'2022_PAPI_Indicators'!A10:BG190,58,FALSE) -> 1.1896967 | BI15: =VLOOKUP(A15,'2022_PAPI_Indicators'!A10:BH190,59,FALSE) -> 1.030609 | BJ15: =VLOOKUP(A15,'2022_PAPI_Indicators'!A10:BI190,60,FALSE) -> 0.93527645 | BK15: =VLOOKUP(A15,'2022_PAPI_Indicators'!A10:BJ190,61,FALSE) -> 1.080825 | BL15: =VLOOKUP(A15,'2022_PAPI_Indicators'!A10:BK190,62,FALSE) -> 1.0260128 | BM15: =VLOOKUP(A15,'2022_PAPI_Indicators'!A10:BL190,63,FALSE) -> 1.3811184 | BN15: =VLOOKUP(A15,'2022_PAPI_Indicators'!A10:BM190,64,FALSE) -> 1.0920784
A16: Participated in Formal Associations | B16: Tham gia vào các tổ chức chính trị, chính trị-xã hội, đoàn thể (%) | C16: 0%-100% | D16: =VLOOKUP(A16,'2022_PAPI_Indicators'!A11:B191,2,) -> 0.52566236 | E16: =VLOOKUP(A16,'2022_PAPI_Indicators'!A11:C191,3,FALSE) -> 0.48129657 | F16: =VLOOKUP(A16,'2022_PAPI_Indicators'!A11:D191,4,FALSE) -> 0.45272407 | G16: =VLOOKUP(A16,'2022_PAPI_Indicators'!A11:E191,5,FALSE) -> 0.51974356 | H16: =VLOOKUP(A16,'2022_PAPI_Indicators'!A11:F191,6,FALSE) -> 0.68701881 | I16: =VLOOKUP(A16,'2022_PAPI_Indicators'!A11:G191,7,FALSE) -> 0.50485867 | J16: =VLOOKUP(A16,'2022_PAPI_Indicators'!A11:H191,8,FALSE) -> 0.56712836 | K16: =VLOOKUP(A16,'2022_PAPI_Indicators'!A11:I191,9,FALSE) -> 0.46878967 | L16: =VLOOKUP(A16,'2022_PAPI_Indicators'!A11:J191,10,FALSE) -> 0.50693107 | M16: =VLOOKUP(A16,'2022_PAPI_Indicators'!A11:K191,11,FALSE) -> 0.69093895 | N16: =VLOOKUP(A16,'2022_PAPI_Indicators'!A11:L191,12,FALSE) -> 0.55138361 | O16: =VLOOKUP(A16,'2022_PAPI_Indicators'!A11:M191,13,FALSE) -> 0.65295714 | P16: =VLOOKUP(A16,'2022_PAPI_Indicators'!A11:N191,14,FALSE) -> 0.58380204 | Q16: =VLOOKUP(A16,'2022_PAPI_Indicators'!A11:O191,15,FALSE) -> 0.67091429 | R16: =VLOOKUP(A16,'2022_PAPI_Indicators'!A11:P191,16,FALSE) -> 0 | S16: =VLOOKUP(A16,'2022_PAPI_Indicators'!A11:R191,17,FALSE) -> 0.59723258 | T16: =VLOOKUP(A16,'2022_PAPI_Indicators'!A11:S191,18,FALSE) -> 0.56564224 | U16: =VLOOKUP(A16,'2022_PAPI_Indicators'!A11:T191,19,FALSE) -> 0.53478014 | V16: =VLOOKUP(A16,'2022_PAPI_Indicators'!A11:U191,20,FALSE) -> 0.55125588 | W16: =VLOOKUP(A16,'2022_PAPI_Indicators'!A11:V191,21,FALSE) -> 0.51898491 | X16: =VLOOKUP(A16,'2022_PAPI_Indicators'!A11:W191,22,FALSE) -> 0.66233784 | Y16: =VLOOKUP(A16,'2022_PAPI_Indicators'!A11:X191,23,FALSE) -> 0.69022465 | Z16: =VLOOKUP(A16,'2022_PAPI_Indicators'!A11:Y191,24,FALSE) -> 0.45192742 | AA16: =VLOOKUP(A16,'2022_PAPI_Indicators'!A11:Z191,25,FALSE) -> 0.65854812 | AB16: =VLOOKUP(A16,'2022_PAPI_Indicators'!A11:AA191,26,FALSE) -> 0.5508616 | AC16: =VLOOKUP(A16,'2022_PAPI_Indicators'!A11:AB191,27,FALSE) -> 0.61385465 | AD16: =VLOOKUP(A16,'2022_PAPI_Indicators'!A11:AC191,28,FALSE) -> 0.67189449 | AE16: =VLOOKUP(A16,'2022_PAPI_Indicators'!A11:AD191,29,FALSE) -> 0.67384642 | AF16: =VLOOKUP(A16,'2022_PAPI_Indicators'!A11:AE191,30,FALSE) -> 0.44953349 | AG16: =VLOOKUP(A16,'2022_PAPI_Indicators'!A11:AF191,31,FALSE) -> 0.54843676 | AH16: =VLOOKUP(A16,'2022_PAPI_Indicators'!A11:AG191,32,FALSE) -> 0.65091664 | AI16: =VLOOKUP(A16,'2022_PAPI_Indicators'!A11:AH191,33,FALSE) -> 0.35081804 | AJ16: =VLOOKUP(A16,'2022_PAPI_Indicators'!A11:AI191,34,FALSE) -> 0.31073239 | AK16: =VLOOKUP(A16,'2022_PAPI_Indicators'!A11:AJ191,35,FALSE) -> 0.39753115 | AL16: =VLOOKUP(A16,'2022_PAPI_Indicators'!A11:AK191,36,FALSE) -> 0.3755984 | AM16: =VLOOKUP(A16,'2022_PAPI_Indicators'!A11:AL191,37,FALSE) -> 0.33180428 | AN16: =VLOOKUP(A16,'2022_PAPI_Indicators'!A11:AM191,38,FALSE) -> 0.48141867 | AO16: =VLOOKUP(A16,'2022_PAPI_Indicators'!A11:AN191,39,FALSE) -> 0.40470031 | AP16: =VLOOKUP(A16,'2022_PAPI_Indicators'!A11:AO191,40,FALSE) -> 0.38609645 | AQ16: =VLOOKUP(A16,'2022_PAPI_Indicators'!A11:AP191,41,FALSE) -> 0.38821992 | AR16: =VLOOKUP(A16,'2022_PAPI_Indicators'!A11:AQ191,42,FALSE) -> 0.54527056 | AS16: =VLOOKUP(A16,'2022_PAPI_Indicators'!A11:AR191,43,FALSE) -> 0.38720459 | AT16: =VLOOKUP(A16,'2022_PAPI_Indicators'!A11:AS191,44,FALSE) -> 0.42482138 | AU16: =VLOOKUP(A16,'2022_PAPI_Indicators'!A11:AT191,45,FALSE) -> 0.42008302 | AV16: =VLOOKUP(A16,'2022_PAPI_Indicators'!A11:AU191,46,FALSE) -> 0.47275978 | AW16: =VLOOKUP(A16,'2022_PAPI_Indicators'!A11:AV191,47,FALSE) -> 0.23596448 | AX16: =VLOOKUP(A16,'2022_PAPI_Indicators'!A11:AW191,48,FALSE) -> 0.34234366 | AY16: =VLOOKUP(A16,'2022_PAPI_Indicators'!A11:AX191,49,FALSE) -> 0.31424996 | AZ16: =VLOOKUP(A16,'2022_PAPI_Indicators'!A11:AY191,50,FALSE) -> 0.30161712 | BA16: =VLOOKUP(A16,'2022_PAPI_Indicators'!A11:AZ191,51,FALSE) -> 0.24093547 | BB16: =VLOOKUP(A16,'2022_PAPI_Indicators'!A11:BA191,52,FALSE) -> 0.17811303 | BC16: =VLOOKUP(A16,'2022_PAPI_Indicators'!A11:BB191,53,FALSE) -> 0.17473339 | BD16: =VLOOKUP(A16,'2022_PAPI_Indicators'!A11:BC191,54,FALSE) -> 0.37331843 | BE16: =VLOOKUP(A16,'2022_PAPI_Indicators'!A11:BD191,55,FALSE) -> 0.26923525 | BF16: =VLOOKUP(A16,'2022_PAPI_Indicators'!A11:BE191,56,FALSE) -> 0.38646275 | BG16: =VLOOKUP(A16,'2022_PAPI_Indicators'!A11:BF191,57,FALSE) -> 0.29203346 | BH16: =VLOOKUP(A16,'2022_PAPI_Indicators'!A11:BG191,58,FALSE) -> 0.1811879 | BI16: =VLOOKUP(A16,'2022_PAPI_Indicators'!A11:BH191,59,FALSE) -> 0.25242013 | BJ16: =VLOOKUP(A16,'2022_PAPI_Indicators'!A11:BI191,60,FALSE) -> 0.15665367 | BK16: =VLOOKUP(A16,'2022_PAPI_Indicators'!A11:BJ191,61,FALSE) -> 0.27813601 | BL16: =VLOOKUP(A16,'2022_PAPI_Indicators'!A11:BK191,62,FALSE) -> 0.25828972 | BM16: =VLOOKUP(A16,'2022_PAPI_Indicators'!A11:BL191,63,FALSE) -> 0.29723966 | BN16: =VLOOKUP(A16,'2022_PAPI_Indicators'!A11:BM191,64,FALSE) -> 0.39738056
A17: Participated in Informal Associations | B17: Tham gia vào các tổ chức xã hội, hội, nhóm, câu lạc bộ tự lập (%) | C17: 0%-100% | D17: =VLOOKUP(A17,'2022_PAPI_Indicators'!A12:B192,2,) -> 0.21529262 | E17: =VLOOKUP(A17,'2022_PAPI_Indicators'!A12:C192,3,FALSE) -> 0.1416005 | F17: =VLOOKUP(A17,'2022_PAPI_Indicators'!A12:D192,4,FALSE) -> 0.063408643 | G17: =VLOOKUP(A17,'2022_PAPI_Indicators'!A12:E192,5,FALSE) -> 0.16764528 | H17: =VLOOKUP(A17,'2022_PAPI_Indicators'!A12:F192,6,FALSE) -> 0.18536884 | I17: =VLOOKUP(A17,'2022_PAPI_Indicators'!A12:G192,7,FALSE) -> 0.2141833 | J17: =VLOOKUP(A17,'2022_PAPI_Indicators'!A12:H192,8,FALSE) -> 0.14865138 | K17: =VLOOKUP(A17,'2022_PAPI_Indicators'!A12:I192,9,FALSE) -> 0.10830277 | L17: =VLOOKUP(A17,'2022_PAPI_Indicators'!A12:J192,10,FALSE) -> 0.11076121 | M17: =VLOOKUP(A17,'2022_PAPI_Indicators'!A12:K192,11,FALSE) -> 0.20469046 | N17: =VLOOKUP(A17,'2022_PAPI_Indicators'!A12:L192,12,FALSE) -> 0.14050679 | O17: =VLOOKUP(A17,'2022_PAPI_Indicators'!A12:M192,13,FALSE) -> 0.17394799 | P17: =VLOOKUP(A17,'2022_PAPI_Indicators'!A12:N192,14,FALSE) -> 0.15009549 | Q17: =VLOOKUP(A17,'2022_PAPI_Indicators'!A12:O192,15,FALSE) -> 0.28384075 | R17: =VLOOKUP(A17,'2022_PAPI_Indicators'!A12:P192,16,FALSE) -> 0 | S17: =VLOOKUP(A17,'2022_PAPI_Indicators'!A12:R192,17,FALSE) -> 0.22493558 | T17: =VLOOKUP(A17,'2022_PAPI_Indicators'!A12:S192,18,FALSE) -> 0.17097297 | U17: =VLOOKUP(A17,'2022_PAPI_Indicators'!A12:T192,19,FALSE) -> 0.30540964 | V17: =VLOOKUP(A17,'2022_PAPI_Indicators'!A12:U192,20,FALSE) -> 0.15984136 | W17: =VLOOKUP(A17,'2022_PAPI_Indicators'!A12:V192,21,FALSE) -> 0.1269387 | X17: =VLOOKUP(A17,'2022_PAPI_Indicators'!A12:W192,22,FALSE) -> 0.22197172 | Y17: =VLOOKUP(A17,'2022_PAPI_Indicators'!A12:X192,23,FALSE) -> 0.10595744 | Z17: =VLOOKUP(A17,'2022_PAPI_Indicators'!A12:Y192,24,FALSE) -> 0.13277367 | AA17: =VLOOKUP(A17,'2022_PAPI_Indicators'!A12:Z192,25,FALSE) -> 0.24444713 | AB17: =VLOOKUP(A17,'2022_PAPI_Indicators'!A12:AA192,26,FALSE) -> 0.21257718 | AC17: =VLOOKUP(A17,'2022_PAPI_Indicators'!A12:AB192,27,FALSE) -> 0.23494346 | AD17: =VLOOKUP(A17,'2022_PAPI_Indicators'!A12:AC192,28,FALSE) -> 0.23169768 | AE17: =VLOOKUP(A17,'2022_PAPI_Indicators'!A12:AD192,29,FALSE) -> 0.23831788 | AF17: =VLOOKUP(A17,'2022_PAPI_Indicators'!A12:AE192,30,FALSE) -> 0.22905476 | AG17: =VLOOKUP(A17,'2022_PAPI_Indicators'!A12:AF192,31,FALSE) -> 0.125 | AH17: =VLOOKUP(A17,'2022_PAPI_Indicators'!A12:AG192,32,FALSE) -> 0.17572054 | AI17: =VLOOKUP(A17,'2022_PAPI_Indicators'!A12:AH192,33,FALSE) -> 0.10579033 | AJ17: =VLOOKUP(A17,'2022_PAPI_Indicators'!A12:AI192,34,FALSE) -> 0.10249674 | AK17: =VLOOKUP(A17,'2022_PAPI_Indicators'!A12:AJ192,35,FALSE) -> 0.094414383 | AL17: =VLOOKUP(A17,'2022_PAPI_Indicators'!A12:AK192,36,FALSE) -> 0.068271555 | AM17: =VLOOKUP(A17,'2022_PAPI_Indicators'!A12:AL192,37,FALSE) -> 0.125 | AN17: =VLOOKUP(A17,'2022_PAPI_Indicators'!A12:AM192,38,FALSE) -> 0.085443251 | AO17: =VLOOKUP(A17,'2022_PAPI_Indicators'!A12:AN192,39,FALSE) -> 0.092847072 | AP17: =VLOOKUP(A17,'2022_PAPI_Indicators'!A12:AO192,40,FALSE) -> 0.080389269 | AQ17: =VLOOKUP(A17,'2022_PAPI_Indicators'!A12:AP192,41,FALSE) -> 0.183053 | AR17: =VLOOKUP(A17,'2022_PAPI_Indicators'!A12:AQ192,42,FALSE) -> 0.14197646 | AS17: =VLOOKUP(A17,'2022_PAPI_Indicators'!A12:AR192,43,FALSE) -> 0.047440119 | AT17: =VLOOKUP(A17,'2022_PAPI_Indicators'!A12:AS192,44,FALSE) -> 0.12188566 | AU17: =VLOOKUP(A17,'2022_PAPI_Indicators'!A12:AT192,45,FALSE) -> 0.11246698 | AV17: =VLOOKUP(A17,'2022_PAPI_Indicators'!A12:AU192,46,FALSE) -> 0.10320074 | AW17: =VLOOKUP(A17,'2022_PAPI_Indicators'!A12:AV192,47,FALSE) -> 0.046489753 | AX17: =VLOOKUP(A17,'2022_PAPI_Indicators'!A12:AW192,48,FALSE) -> 0.11278021 | AY17: =VLOOKUP(A17,'2022_PAPI_Indicators'!A12:AX192,49,FALSE) -> 0.090927698 | AZ17: =VLOOKUP(A17,'2022_PAPI_Indicators'!A12:AY192,50,FALSE) -> 0.10356939 | BA17: =VLOOKUP(A17,'2022_PAPI_Indicators'!A12:AZ192,51,FALSE) -> 0.066570714 | BB17: =VLOOKUP(A17,'2022_PAPI_Indicators'!A12:BA192,52,FALSE) -> 0.050726984 | BC17: =VLOOKUP(A17,'2022_PAPI_Indicators'!A12:BB192,53,FALSE) -> 0.074875973 | BD17: =VLOOKUP(A17,'2022_PAPI_Indicators'!A12:BC192,54,FALSE) -> 0.12232926 | BE17: =VLOOKUP(A17,'2022_PAPI_Indicators'!A12:BD192,55,FALSE) -> 0.10454214 | BF17: =VLOOKUP(A17,'2022_PAPI_Indicators'!A12:BE192,56,FALSE) -> 0.10268801 | BG17: =VLOOKUP(A17,'2022_PAPI_Indicators'!A12:BF192,57,FALSE) -> 0.13069038 | BH17: =VLOOKUP(A17,'2022_PAPI_Indicators'!A12:BG192,58,FALSE) -> 0.12772396 | BI17: =VLOOKUP(A17,'2022_PAPI_Indicators'!A12:BH192,59,FALSE) -> 0.075922273 | BJ17: =VLOOKUP(A17,'2022_PAPI_Indicators'!A12:BI192,60,FALSE) -> 0.18827076 | BK17: =VLOOKUP(A17,'2022_PAPI_Indicators'!A12:BJ192,61,FALSE) -> 0.13504754 | BL17: =VLOOKUP(A17,'2022_PAPI_Indicators'!A12:BK192,62,FALSE) -> 0.10149556 | BM17: =VLOOKUP(A17,'2022_PAPI_Indicators'!A12:BL192,63,FALSE) -> 0.12244929 | BN17: =VLOOKUP(A17,'2022_PAPI_Indicators'!A12:BM192,64,FALSE) -> 0.1004942
A18: Voted in Last Communce People's Council Election | B18: Tỷ lệ người trả lời đã tham gia bầu cử đại biểu Hội đồng Nhân dân lần gần đây nhất (%) | C18: 0%-100% | D18: =VLOOKUP(A18,'2022_PAPI_Indicators'!A13:B193,2,) -> 0.74945217 | E18: =VLOOKUP(A18,'2022_PAPI_Indicators'!A13:C193,3,FALSE) -> 0.78490156 | F18: =VLOOKUP(A18,'2022_PAPI_Indicators'!A13:D193,4,FALSE) -> 0.70206487 | G18: =VLOOKUP(A18,'2022_PAPI_Indicators'!A13:E193,5,FALSE) -> 0.7780605 | H18: =VLOOKUP(A18,'2022_PAPI_Indicators'!A13:F193,6,FALSE) -> 0.57972807 | I18: =VLOOKUP(A18,'2022_PAPI_Indicators'!A13:G193,7,FALSE) -> 0.71120441 | J18: =VLOOKUP(A18,'2022_PAPI_Indicators'!A13:H193,8,FALSE) -> 0.57454067 | K18: =VLOOKUP(A18,'2022_PAPI_Indicators'!A13:I193,9,FALSE) -> 0.77319324 | L18: =VLOOKUP(A18,'2022_PAPI_Indicators'!A13:J193,10,FALSE) -> 0.75557578 | M18: =VLOOKUP(A18,'2022_PAPI_Indicators'!A13:K193,11,FALSE) -> 0.54948944 | N18: =VLOOKUP(A18,'2022_PAPI_Indicators'!A13:L193,12,FALSE) -> 0.75360602 | O18: =VLOOKUP(A18,'2022_PAPI_Indicators'!A13:M193,13,FALSE) -> 0.72394592 | P18: =VLOOKUP(A18,'2022_PAPI_Indicators'!A13:N193,14,FALSE) -> 0.82326102 | Q18: =VLOOKUP(A18,'2022_PAPI_Indicators'!A13:O193,15,FALSE) -> 0.77582473 | R18: =VLOOKUP(A18,'2022_PAPI_Indicators'!A13:P193,16,FALSE) -> 0 | S18: =VLOOKUP(A18,'2022_PAPI_Indicators'!A13:R193,17,FALSE) -> 0.71761078 | T18: =VLOOKUP(A18,'2022_PAPI_Indicators'!A13:S193,18,FALSE) -> 0.79972136 | U18: =VLOOKUP(A18,'2022_PAPI_Indicators'!A13:T193,19,FALSE) -> 0.80611944 | V18: =VLOOKUP(A18,'2022_PAPI_Indicators'!A13:U193,20,FALSE) -> 0.68382573 | W18: =VLOOKUP(A18,'2022_PAPI_Indicators'!A13:V193,21,FALSE) -> 0.57827544 | X18: =VLOOKUP(A18,'2022_PAPI_Indicators'!A13:W193,22,FALSE) -> 0.78605717 | Y18: =VLOOKUP(A18,'2022_PAPI_Indicators'!A13:X193,23,FALSE) -> 0.75141448 | Z18: =VLOOKUP(A18,'2022_PAPI_Indicators'!A13:Y193,24,FALSE) -> 0.81099421 | AA18: =VLOOKUP(A18,'2022_PAPI_Indicators'!A13:Z193,25,FALSE) -> 0.7079677 | AB18: =VLOOKUP(A18,'2022_PAPI_Indicators'!A13:AA193,26,FALSE) -> 0.66199976 | AC18: =VLOOKUP(A18,'2022_PAPI_Indicators'!A13:AB193,27,FALSE) -> 0.66692263 | AD18: =VLOOKUP(A18,'2022_PAPI_Indicators'!A13:AC193,28,FALSE) -> 0.80546135 | AE18: =VLOOKUP(A18,'2022_PAPI_Indicators'!A13:AD193,29,FALSE) -> 0.79755926 | AF18: =VLOOKUP(A18,'2022_PAPI_Indicators'!A13:AE193,30,FALSE) -> 0.58251774 | AG18: =VLOOKUP(A18,'2022_PAPI_Indicators'!A13:AF193,31,FALSE) -> 0.72376513 | AH18: =VLOOKUP(A18,'2022_PAPI_Indicators'!A13:AG193,32,FALSE) -> 0.62310815 | AI18: =VLOOKUP(A18,'2022_PAPI_Indicators'!A13:AH193,33,FALSE) -> 0.60801739 | AJ18: =VLOOKUP(A18,'2022_PAPI_Indicators'!A13:AI193,34,FALSE) -> 0.63452303 | AK18: =VLOOKUP(A18,'2022_PAPI_Indicators'!A13:AJ193,35,FALSE) -> 0.57710814 | AL18: =VLOOKUP(A18,'2022_PAPI_Indicators'!A13:AK193,36,FALSE) -> 0.72496796 | AM18: =VLOOKUP(A18,'2022_PAPI_Indicators'!A13:AL193,37,FALSE) -> 0.67858714 | AN18: =VLOOKUP(A18,'2022_PAPI_Indicators'!A13:AM193,38,FALSE) -> 0.57040071 | AO18: =VLOOKUP(A18,'2022_PAPI_Indicators'!A13:AN193,39,FALSE) -> 0.60393029 | AP18: =VLOOKUP(A18,'2022_PAPI_Indicators'!A13:AO193,40,FALSE) -> 0.61632484 | AQ18: =VLOOKUP(A18,'2022_PAPI_Indicators'!A13:AP193,41,FALSE) -> 0.60337746 | AR18: =VLOOKUP(A18,'2022_PAPI_Indicators'!A13:AQ193,42,FALSE) -> 0.71357143 | AS18: =VLOOKUP(A18,'2022_PAPI_Indicators'!A13:AR193,43,FALSE) -> 0.679061 | AT18: =VLOOKUP(A18,'2022_PAPI_Indicators'!A13:AS193,44,FALSE) -> 0.66793531 | AU18: =VLOOKUP(A18,'2022_PAPI_Indicators'!A13:AT193,45,FALSE) -> 0.77918816 | AV18: =VLOOKUP(A18,'2022_PAPI_Indicators'!A13:AU193,46,FALSE) -> 0.57612455 | AW18: =VLOOKUP(A18,'2022_PAPI_Indicators'!A13:AV193,47,FALSE) -> 0.5179643 | AX18: =VLOOKUP(A18,'2022_PAPI_Indicators'!A13:AW193,48,FALSE) -> 0.5167073 | AY18: =VLOOKUP(A18,'2022_PAPI_Indicators'!A13:AX193,49,FALSE) -> 0.64657575 | AZ18: =VLOOKUP(A18,'2022_PAPI_Indicators'!A13:AY193,50,FALSE) -> 0.55870593 | BA18: =VLOOKUP(A18,'2022_PAPI_Indicators'!A13:AZ193,51,FALSE) -> 0.59736276 | BB18: =VLOOKUP(A18,'2022_PAPI_Indicators'!A13:BA193,52,FALSE) -> 0.5052675 | BC18: =VLOOKUP(A18,'2022_PAPI_Indicators'!A13:BB193,53,FALSE) -> 0.56855392 | BD18: =VLOOKUP(A18,'2022_PAPI_Indicators'!A13:BC193,54,FALSE) -> 0.48033282 | BE18: =VLOOKUP(A18,'2022_PAPI_Indicators'!A13:BD193,55,FALSE) -> 0.56879324 | BF18: =VLOOKUP(A18,'2022_PAPI_Indicators'!A13:BE193,56,FALSE) -> 0.47233474 | BG18: =VLOOKUP(A18,'2022_PAPI_Indicators'!A13:BF193,57,FALSE) -> 0.42368892 | BH18: =VLOOKUP(A18,'2022_PAPI_Indicators'!A13:BG193,58,FALSE) -> 0.53832972 | BI18: =VLOOKUP(A18,'2022_PAPI_Indicators'!A13:BH193,59,FALSE) -> 0.47403485 | BJ18: =VLOOKUP(A18,'2022_PAPI_Indicators'!A13:BI193,60,FALSE) -> 0.59213096 | BK18: =VLOOKUP(A18,'2022_PAPI_Indicators'!A13:BJ193,61,FALSE) -> 0.47905722 | BL18: =VLOOKUP(A18,'2022_PAPI_Indicators'!A13:BK193,62,FALSE) -> 0 | BM18: =VLOOKUP(A18,'2022_PAPI_Indicators'!A13:BL193,63,FALSE) -> 0 | BN18: =VLOOKUP(A18,'2022_PAPI_Indicators'!A13:BM193,64,FALSE) -> 0
A19: Voted in Last National Assembly Election | B19: Tỷ lệ người trả lời đã tham gia bầu cử đại biểu Quốc hội lần gần đây nhất (%) | C19: 0%-100% | D19: =VLOOKUP(A19,'2022_PAPI_Indicators'!A14:B194,2,) -> 0.74786282 | E19: =VLOOKUP(A19,'2022_PAPI_Indicators'!A14:C194,3,FALSE) -> 0.81020534 | F19: =VLOOKUP(A19,'2022_PAPI_Indicators'!A14:D194,4,FALSE) -> 0.65154463 | G19: =VLOOKUP(A19,'2022_PAPI_Indicators'!A14:E194,5,FALSE) -> 0.79713488 | H19: =VLOOKUP(A19,'2022_PAPI_Indicators'!A14:F194,6,FALSE) -> 0.64028108 | I19: =VLOOKUP(A19,'2022_PAPI_Indicators'!A14:G194,7,FALSE) -> 0.63832635 | J19: =VLOOKUP(A19,'2022_PAPI_Indicators'!A14:H194,8,FALSE) -> 0.65302241 | K19: =VLOOKUP(A19,'2022_PAPI_Indicators'!A14:I194,9,FALSE) -> 0.68732178 | L19: =VLOOKUP(A19,'2022_PAPI_Indicators'!A14:J194,10,FALSE) -> 0.5729453 | M19: =VLOOKUP(A19,'2022_PAPI_Indicators'!A14:K194,11,FALSE) -> 0.63508314 | N19: =VLOOKUP(A19,'2022_PAPI_Indicators'!A14:L194,12,FALSE) -> 0.7390244 | O19: =VLOOKUP(A19,'2022_PAPI_Indicators'!A14:M194,13,FALSE) -> 0.70200348 | P19: =VLOOKUP(A19,'2022_PAPI_Indicators'!A14:N194,14,FALSE) -> 0.87235683 | Q19: =VLOOKUP(A19,'2022_PAPI_Indicators'!A14:O194,15,FALSE) -> 0.71905935 | R19: =VLOOKUP(A19,'2022_PAPI_Indicators'!A14:P194,16,FALSE) -> 0 | S19: =VLOOKUP(A19,'2022_PAPI_Indicators'!A14:R194,17,FALSE) -> 0.66345316 | T19: =VLOOKUP(A19,'2022_PAPI_Indicators'!A14:S194,18,FALSE) -> 0.6677416 | U19: =VLOOKUP(A19,'2022_PAPI_Indicators'!A14:T194,19,FALSE) -> 0.66360033 | V19: =VLOOKUP(A19,'2022_PAPI_Indicators'!A14:U194,20,FALSE) -> 0.69982827 | W19: =VLOOKUP(A19,'2022_PAPI_Indicators'!A14:V194,21,FALSE) -> 0.63248181 | X19: =VLOOKUP(A19,'2022_PAPI_Indicators'!A14:W194,22,FALSE) -> 0.8169812 | Y19: =VLOOKUP(A19,'2022_PAPI_Indicators'!A14:X194,23,FALSE) -> 0.60431832 | Z19: =VLOOKUP(A19,'2022_PAPI_Indicators'!A14:Y194,24,FALSE) -> 0.78528416 | AA19: =VLOOKUP(A19,'2022_PAPI_Indicators'!A14:Z194,25,FALSE) -> 0.595653 | AB19: =VLOOKUP(A19,'2022_PAPI_Indicators'!A14:AA194,26,FALSE) -> 0.62172562 | AC19: =VLOOKUP(A19,'2022_PAPI_Indicators'!A14:AB194,27,FALSE) -> 0.53379136 | AD19: =VLOOKUP(A19,'2022_PAPI_Indicators'!A14:AC194,28,FALSE) -> 0.6280638 | AE19: =VLOOKUP(A19,'2022_PAPI_Indicators'!A14:AD194,29,FALSE) -> 0.73459566 | AF19: =VLOOKUP(A19,'2022_PAPI_Indicators'!A14:AE194,30,FALSE) -> 0.53900278 | AG19: =VLOOKUP(A19,'2022_PAPI_Indicators'!A14:AF194,31,FALSE) -> 0.64591604 | AH19: =VLOOKUP(A19,'2022_PAPI_Indicators'!A14:AG194,32,FALSE) -> 0.59006464 | AI19: =VLOOKUP(A19,'2022_PAPI_Indicators'!A14:AH194,33,FALSE) -> 0.50648636 | AJ19: =VLOOKUP(A19,'2022_PAPI_Indicators'!A14:AI194,34,FALSE) -> 0.52722281 | AK19: =VLOOKUP(A19,'2022_PAPI_Indicators'!A14:AJ194,35,FALSE) -> 0.5925349 | AL19: =VLOOKUP(A19,'2022_PAPI_Indicators'!A14:AK194,36,FALSE) -> 0.72001624 | AM19: =VLOOKUP(A19,'2022_PAPI_Indicators'!A14:AL194,37,FALSE) -> 0.64033097 | AN19: =VLOOKUP(A19,'2022_PAPI_Indicators'!A14:AM194,38,FALSE) -> 0.507801 | AO19: =VLOOKUP(A19,'2022_PAPI_Indicators'!A14:AN194,39,FALSE) -> 0.58055681 | AP19: =VLOOKUP(A19,'2022_PAPI_Indicators'!A14:AO194,40,FALSE) -> 0.59338021 | AQ19: =VLOOKUP(A19,'2022_PAPI_Indicators'!A14:AP194,41,FALSE) -> 0.59001821 | AR19: =VLOOKUP(A19,'2022_PAPI_Indicators'!A14:AQ194,42,FALSE) -> 0.77508092 | AS19: =VLOOKUP(A19,'2022_PAPI_Indicators'!A14:AR194,43,FALSE) -> 0.60980207 | AT19: =VLOOKUP(A19,'2022_PAPI_Indicators'!A14:AS194,44,FALSE) -> 0.60837555 | AU19: =VLOOKUP(A19,'2022_PAPI_Indicators'!A14:AT194,45,FALSE) -> 0.79589576 | AV19: =VLOOKUP(A19,'2022_PAPI_Indicators'!A14:AU194,46,FALSE) -> 0.58272934 | AW19: =VLOOKUP(A19,'2022_PAPI_Indicators'!A14:AV194,47,FALSE) -> 0.51297748 | AX19: =VLOOKUP(A19,'2022_PAPI_Indicators'!A14:AW194,48,FALSE) -> 0.56269956 | AY19: =VLOOKUP(A19,'2022_PAPI_Indicators'!A14:AX194,49,FALSE) -> 0.58700371 | AZ19: =VLOOKUP(A19,'2022_PAPI_Indicators'!A14:AY194,50,FALSE) -> 0.44138122 | BA19: =VLOOKUP(A19,'2022_PAPI_Indicators'!A14:AZ194,51,FALSE) -> 0.49736574 | BB19: =VLOOKUP(A19,'2022_PAPI_Indicators'!A14:BA194,52,FALSE) -> 0.41325012 | BC19: =VLOOKUP(A19,'2022_PAPI_Indicators'!A14:BB194,53,FALSE) -> 0.47878551 | BD19: =VLOOKUP(A19,'2022_PAPI_Indicators'!A14:BC194,54,FALSE) -> 0.49789798 | BE19: =VLOOKUP(A19,'2022_PAPI_Indicators'!A14:BD194,55,FALSE) -> 0.59215063 | BF19: =VLOOKUP(A19,'2022_PAPI_Indicators'!A14:BE194,56,FALSE) -> 0.48060468 | BG19: =VLOOKUP(A19,'2022_PAPI_Indicators'!A14:BF194,57,FALSE) -> 0.40239909 | BH19: =VLOOKUP(A19,'2022_PAPI_Indicators'!A14:BG194,58,FALSE) -> 0.45561001 | BI19: =VLOOKUP(A19,'2022_PAPI_Indicators'!A14:BH194,59,FALSE) -> 0.55975407 | BJ19: =VLOOKUP(A19,'2022_PAPI_Indicators'!A14:BI194,60,FALSE) -> 0.65752059 | BK19: =VLOOKUP(A19,'2022_PAPI_Indicators'!A14:BJ194,61,FALSE) -> 0.49570414 | BL19: =VLOOKUP(A19,'2022_PAPI_Indicators'!A14:BK194,62,FALSE) -> 0 | BM19: =VLOOKUP(A19,'2022_PAPI_Indicators'!A14:BL194,63,FALSE) -> 0 | BN19: =VLOOKUP(A19,'2022_PAPI_Indicators'!A14:BM194,64,FALSE) -> 0
A20: Village Chief Elected | B20: Tỷ lệ người trả lời cho biết trưởng thôn/tổ trưởng tổ dân phố là do dân bầu (%) | C20: 0%-100% | D20: =VLOOKUP(A20,'2022_PAPI_Indicators'!A15:B195,2,) -> 0.86841863 | E20: =VLOOKUP(A20,'2022_PAPI_Indicators'!A15:C195,3,FALSE) -> 0.79100943 | F20: =VLOOKUP(A20,'2022_PAPI_Indicators'!A15:D195,4,FALSE) -> 0.79261017 | G20: =VLOOKUP(A20,'2022_PAPI_Indicators'!A15:E195,5,FALSE) -> 0.92215699 | H20: =VLOOKUP(A20,'2022_PAPI_Indicators'!A15:F195,6,FALSE) -> 0.87788785 | I20: =VLOOKUP(A20,'2022_PAPI_Indicators'!A15:G195,7,FALSE) -> 0.86809897 | J20: =VLOOKUP(A20,'2022_PAPI_Indicators'!A15:H195,8,FALSE) -> 0.86338818 | K20: =VLOOKUP(A20,'2022_PAPI_Indicators'!A15:I195,9,FALSE) -> 0.83012336 | L20: =VLOOKUP(A20,'2022_PAPI_Indicators'!A15:J195,10,FALSE) -> 0.83767027 | M20: =VLOOKUP(A20,'2022_PAPI_Indicators'!A15:K195,11,FALSE) -> 0.84792078 | N20: =VLOOKUP(A20,'2022_PAPI_Indicators'!A15:L195,12,FALSE) -> 0.78130352 | O20: =VLOOKUP(A20,'2022_PAPI_Indicators'!A15:M195,13,FALSE) -> 0.89617026 | P20: =VLOOKUP(A20,'2022_PAPI_Indicators'!A15:N195,14,FALSE) -> 0.88557583 | Q20: =VLOOKUP(A20,'2022_PAPI_Indicators'!A15:O195,15,FALSE) -> 0.95623273 | R20: =VLOOKUP(A20,'2022_PAPI_Indicators'!A15:P195,16,FALSE) -> 0 | S20: =VLOOKUP(A20,'2022_PAPI_Indicators'!A15:R195,17,FALSE) -> 0.92063791 | T20: =VLOOKUP(A20,'2022_PAPI_Indicators'!A15:S195,18,FALSE) -> 0.91736865 | U20: =VLOOKUP(A20,'2022_PAPI_Indicators'!A15:T195,19,FALSE) -> 0.91506881 | V20: =VLOOKUP(A20,'2022_PAPI_Indicators'!A15:U195,20,FALSE) -> 0.89457482 | W20: =VLOOKUP(A20,'2022_PAPI_Indicators'!A15:V195,21,FALSE) -> 0.95623517 | X20: =VLOOKUP(A20,'2022_PAPI_Indicators'!A15:W195,22,FALSE) -> 0.84585518 | Y20: =VLOOKUP(A20,'2022_PAPI_Indicators'!A15:X195,23,FALSE) -> 0.93753016 | Z20: =VLOOKUP(A20,'2022_PAPI_Indicators'!A15:Y195,24,FALSE) -> 0.85152841 | AA20: =VLOOKUP(A20,'2022_PAPI_Indicators'!A15:Z195,25,FALSE) -> 0.882851 | AB20: =VLOOKUP(A20,'2022_PAPI_Indicators'!A15:AA195,26,FALSE) -> 0.93203443 | AC20: =VLOOKUP(A20,'2022_PAPI_Indicators'!A15:AB195,27,FALSE) -> 0.91861081 | AD20: =VLOOKUP(A20,'2022_PAPI_Indicators'!A15:AC195,28,FALSE) -> 0.93023455 | AE20: =VLOOKUP(A20,'2022_PAPI_Indicators'!A15:AD195,29,FALSE) -> 0.89456785 | AF20: =VLOOKUP(A20,'2022_PAPI_Indicators'!A15:AE195,30,FALSE) -> 0.90103036 | AG20: =VLOOKUP(A20,'2022_PAPI_Indicators'!A15:AF195,31,FALSE) -> 0.86782676 | AH20: =VLOOKUP(A20,'2022_PAPI_Indicators'!A15:AG195,32,FALSE) -> 0.90665448 | AI20: =VLOOKUP(A20,'2022_PAPI_Indicators'!A15:AH195,33,FALSE) -> 0.88017267 | AJ20: =VLOOKUP(A20,'2022_PAPI_Indicators'!A15:AI195,34,FALSE) -> 0.91964418 | AK20: =VLOOKUP(A20,'2022_PAPI_Indicators'!A15:AJ195,35,FALSE) -> 0.85373199 | AL20: =VLOOKUP(A20,'2022_PAPI_Indicators'!A15:AK195,36,FALSE) -> 0.8360644 | AM20: =VLOOKUP(A20,'2022_PAPI_Indicators'!A15:AL195,37,FALSE) -> 0.80147171 | AN20: =VLOOKUP(A20,'2022_PAPI_Indicators'!A15:AM195,38,FALSE) -> 0.84614408 | AO20: =VLOOKUP(A20,'2022_PAPI_Indicators'!A15:AN195,39,FALSE) -> 0.85885632 | AP20: =VLOOKUP(A20,'2022_PAPI_Indicators'!A15:AO195,40,FALSE) -> 0.85326123 | AQ20: =VLOOKUP(A20,'2022_PAPI_Indicators'!A15:AP195,41,FALSE) -> 0.87643987 | AR20: =VLOOKUP(A20,'2022_PAPI_Indicators'!A15:AQ195,42,FALSE) -> 0.88775343 | AS20: =VLOOKUP(A20,'2022_PAPI_Indicators'!A15:AR195,43,FALSE) -> 0.86428684 | AT20: =VLOOKUP(A20,'2022_PAPI_Indicators'!A15:AS195,44,FALSE) -> 0.83208424 | AU20: =VLOOKUP(A20,'2022_PAPI_Indicators'!A15:AT195,45,FALSE) -> 0.79304695 | AV20: =VLOOKUP(A20,'2022_PAPI_Indicators'!A15:AU195,46,FALSE) -> 0.83342791 | AW20: =VLOOKUP(A20,'2022_PAPI_Indicators'!A15:AV195,47,FALSE) -> 0.76661068 | AX20: =VLOOKUP(A20,'2022_PAPI_Indicators'!A15:AW195,48,FALSE) -> 0.88706273 | AY20: =VLOOKUP(A20,'2022_PAPI_Indicators'!A15:AX195,49,FALSE) -> 0.74251306 | AZ20: =VLOOKUP(A20,'2022_PAPI_Indicators'!A15:AY195,50,FALSE) -> 0.79556155 | BA20: =VLOOKUP(A20,'2022_PAPI_Indicators'!A15:AZ195,51,FALSE) -> 0.64379507 | BB20: =VLOOKUP(A20,'2022_PAPI_Indicators'!A15:BA195,52,FALSE) -> 0.7286073 | BC20: =VLOOKUP(A20,'2022_PAPI_Indicators'!A15:BB195,53,FALSE) -> 0.78942537 | BD20: =VLOOKUP(A20,'2022_PAPI_Indicators'!A15:BC195,54,FALSE) -> 0.74082124 | BE20: =VLOOKUP(A20,'2022_PAPI_Indicators'!A15:BD195,55,FALSE) -> 0.79280752 | BF20: =VLOOKUP(A20,'2022_PAPI_Indicators'!A15:BE195,56,FALSE) -> 0.84337717 | BG20: =VLOOKUP(A20,'2022_PAPI_Indicators'!A15:BF195,57,FALSE) -> 0.73692155 | BH20: =VLOOKUP(A20,'2022_PAPI_Indicators'!A15:BG195,58,FALSE) -> 0.81287128 | BI20: =VLOOKUP(A20,'2022_PAPI_Indicators'!A15:BH195,59,FALSE) -> 0.74273956 | BJ20: =VLOOKUP(A20,'2022_PAPI_Indicators'!A15:BI195,60,FALSE) -> 0.79330426 | BK20: =VLOOKUP(A20,'2022_PAPI_Indicators'!A15:BJ195,61,FALSE) -> 0.7644698 | BL20: =VLOOKUP(A20,'2022_PAPI_Indicators'!A15:BK195,62,FALSE) -> 0.78372502 | BM20: =VLOOKUP(A20,'2022_PAPI_Indicators'!A15:BL195,63,FALSE) -> 0.87556231 | BN20: =VLOOKUP(A20,'2022_PAPI_Indicators'!A15:BM195,64,FALSE) -> 0.77537405
A21: Participated in Election | B21: Tỷ lệ người trả lời trực tiếp bầu trưởng thôn/tổ trưởng tổ dân phố (%) | C21: 0%-100% | D21: =VLOOKUP(A21,'2022_PAPI_Indicators'!A16:B196,2,) -> 0.6651966 | E21: =VLOOKUP(A21,'2022_PAPI_Indicators'!A16:C196,3,FALSE) -> 0.63672322 | F21: =VLOOKUP(A21,'2022_PAPI_Indicators'!A16:D196,4,FALSE) -> 0.75196129 | G21: =VLOOKUP(A21,'2022_PAPI_Indicators'!A16:E196,5,FALSE) -> 0.62307429 | H21: =VLOOKUP(A21,'2022_PAPI_Indicators'!A16:F196,6,FALSE) -> 0.56721342 | I21: =VLOOKUP(A21,'2022_PAPI_Indicators'!A16:G196,7,FALSE) -> 0.65176493 | J21: =VLOOKUP(A21,'2022_PAPI_Indicators'!A16:H196,8,FALSE) -> 0.70107913 | K21: =VLOOKUP(A21,'2022_PAPI_Indicators'!A16:I196,9,FALSE) -> 0.78290594 | L21: =VLOOKUP(A21,'2022_PAPI_Indicators'!A16:J196,10,FALSE) -> 0.64704716 | M21: =VLOOKUP(A21,'2022_PAPI_Indicators'!A16:K196,11,FALSE) -> 0.64127576 | N21: =VLOOKUP(A21,'2022_PAPI_Indicators'!A16:L196,12,FALSE) -> 0.600734 | O21: =VLOOKUP(A21,'2022_PAPI_Indicators'!A16:M196,13,FALSE) -> 0.60382378 | P21: =VLOOKUP(A21,'2022_PAPI_Indicators'!A16:N196,14,FALSE) -> 0.69285917 | Q21: =VLOOKUP(A21,'2022_PAPI_Indicators'!A16:O196,15,FALSE) -> 0.69863999 | R21: =VLOOKUP(A21,'2022_PAPI_Indicators'!A16:P196,16,FALSE) -> 0 | S21: =VLOOKUP(A21,'2022_PAPI_Indicators'!A16:R196,17,FALSE) -> 0.53766197 | T21: =VLOOKUP(A21,'2022_PAPI_Indicators'!A16:S196,18,FALSE) -> 0.72016352 | U21: =VLOOKUP(A21,'2022_PAPI_Indicators'!A16:T196,19,FALSE) -> 0.77022594 | V21: =VLOOKUP(A21,'2022_PAPI_Indicators'!A16:U196,20,FALSE) -> 0.66666669 | W21: =VLOOKUP(A21,'2022_PAPI_Indicators'!A16:V196,21,FALSE) -> 0.64929253 | X21: =VLOOKUP(A21,'2022_PAPI_Indicators'!A16:W196,22,FALSE) -> 0.67914337 | Y21: =VLOOKUP(A21,'2022_PAPI_Indicators'!A16:X196,23,FALSE) -> 0.74724221 | Z21: =VLOOKUP(A21,'2022_PAPI_Indicators'!A16:Y196,24,FALSE) -> 0.63288188 | AA21: =VLOOKUP(A21,'2022_PAPI_Indicators'!A16:Z196,25,FALSE) -> 0.64689916 | AB21: =VLOOKUP(A21,'2022_PAPI_Indicators'!A16:AA196,26,FALSE) -> 0.6476773 | AC21: =VLOOKUP(A21,'2022_PAPI_Indicators'!A16:AB196,27,FALSE) -> 0.68651551 | AD21: =VLOOKUP(A21,'2022_PAPI_Indicators'!A16:AC196,28,FALSE) -> 0.70454365 | AE21: =VLOOKUP(A21,'2022_PAPI_Indicators'!A16:AD196,29,FALSE) -> 0.60355723 | AF21: =VLOOKUP(A21,'2022_PAPI_Indicators'!A16:AE196,30,FALSE) -> 0.61232644 | AG21: =VLOOKUP(A21,'2022_PAPI_Indicators'!A16:AF196,31,FALSE) -> 0.68768889 | AH21: =VLOOKUP(A21,'2022_PAPI_Indicators'!A16:AG196,32,FALSE) -> 0.6570344 | AI21: =VLOOKUP(A21,'2022_PAPI_Indicators'!A16:AH196,33,FALSE) -> 0.56233191 | AJ21: =VLOOKUP(A21,'2022_PAPI_Indicators'!A16:AI196,34,FALSE) -> 0.68186152 | AK21: =VLOOKUP(A21,'2022_PAPI_Indicators'!A16:AJ196,35,FALSE) -> 0.7334128 | AL21: =VLOOKUP(A21,'2022_PAPI_Indicators'!A16:AK196,36,FALSE) -> 0.72657406 | AM21: =VLOOKUP(A21,'2022_PAPI_Indicators'!A16:AL196,37,FALSE) -> 0.69053477 | AN21: =VLOOKUP(A21,'2022_PAPI_Indicators'!A16:AM196,38,FALSE) -> 0.56208456 | AO21: =VLOOKUP(A21,'2022_PAPI_Indicators'!A16:AN196,39,FALSE) -> 0.73108965 | AP21: =VLOOKUP(A21,'2022_PAPI_Indicators'!A16:AO196,40,FALSE) -> 0.80758691 | AQ21: =VLOOKUP(A21,'2022_PAPI_Indicators'!A16:AP196,41,FALSE) -> 0.69507921 | AR21: =VLOOKUP(A21,'2022_PAPI_Indicators'!A16:AQ196,42,FALSE) -> 0.60754347 | AS21: =VLOOKUP(A21,'2022_PAPI_Indicators'!A16:AR196,43,FALSE) -> 0.58688432 | AT21: =VLOOKUP(A21,'2022_PAPI_Indicators'!A16:AS196,44,FALSE) -> 0.64359015 | AU21: =VLOOKUP(A21,'2022_PAPI_Indicators'!A16:AT196,45,FALSE) -> 0.76414096 | AV21: =VLOOKUP(A21,'2022_PAPI_Indicators'!A16:AU196,46,FALSE) -> 0.65574706 | AW21: =VLOOKUP(A21,'2022_PAPI_Indicators'!A16:AV196,47,FALSE) -> 0.72671622 | AX21: =VLOOKUP(A21,'2022_PAPI_Indicators'!A16:AW196,48,FALSE) -> 0.76275361 | AY21: =VLOOKUP(A21,'2022_PAPI_Indicators'!A16:AX196,49,FALSE) -> 0.70866477 | AZ21: =VLOOKUP(A21,'2022_PAPI_Indicators'!A16:AY196,50,FALSE) -> 0.73915893 | BA21: =VLOOKUP(A21,'2022_PAPI_Indicators'!A16:AZ196,51,FALSE) -> 0.74930495 | BB21: =VLOOKUP(A21,'2022_PAPI_Indicators'!A16:BA196,52,FALSE) -> 0.71157587 | BC21: =VLOOKUP(A21,'2022_PAPI_Indicators'!A16:BB196,53,FALSE) -> 0.56058335 | BD21: =VLOOKUP(A21,'2022_PAPI_Indicators'!A16:BC196,54,FALSE) -> 0.63682318 | BE21: =VLOOKUP(A21,'2022_PAPI_Indicators'!A16:BD196,55,FALSE) -> 0.65179086 | BF21: =VLOOKUP(A21,'2022_PAPI_Indicators'!A16:BE196,56,FALSE) -> 0.65227455 | BG21: =VLOOKUP(A21,'2022_PAPI_Indicators'!A16:BF196,57,FALSE) -> 0.49787572 | BH21: =VLOOKUP(A21,'2022_PAPI_Indicators'!A16:BG196,58,FALSE) -> 0.61846924 | BI21: =VLOOKUP(A21,'2022_PAPI_Indicators'!A16:BH196,59,FALSE) -> 0.70756251 | BJ21: =VLOOKUP(A21,'2022_PAPI_Indicators'!A16:BI196,60,FALSE) -> 0.64835352 | BK21: =VLOOKUP(A21,'2022_PAPI_Indicators'!A16:BJ196,61,FALSE) -> 0.62529922 | BL21: =VLOOKUP(A21,'2022_PAPI_Indicators'!A16:BK196,62,FALSE) -> 0.46180752 | BM21: =VLOOKUP(A21,'2022_PAPI_Indicators'!A16:BL196,63,FALSE) -> 0.76559585 | BN21: =VLOOKUP(A21,'2022_PAPI_Indicators'!A16:BM196,64,FALSE) -> 0.62808263
A22: Quality of Village Head Elections | B22: 1.3: Chất lượng bầu cử | C22: 0.25-2.5 điểm/points | D22: 1.57 | E22: 1.4906292 | F22: 1.3542999 | G22: 1.5870527 | H22: 1.6415495 | I22: 1.5213792 | J22: 1.5614797 | K22: 1.657256 | L22: 1.5888326 | M22: 1.5982707 | N22: 1.6678363 | O22: 1.5258307 | P22: 1.6278515 | Q22: 1.6884692 | R22: 0 | S22: 1.6228775 | T22: 1.5597568 | U22: 1.5488508 | V22: 1.4370353 | W22: 1.706248 | X22: 1.4634694 | Y22: 1.6134049 | Z22: 1.5275015 | AA22: 1.7182655 | AB22: 1.8106496 | AC22: 1.6811701 | AD22: 1.6509942 | AE22: 1.5570338 | AF22: 1.5893122 | AG22: 1.5230404 | AH22: 1.6185719 | AI22: 1.5182261 | AJ22: 1.5303782 | AK22: 1.5352372 | AL22: 1.241479 | AM22: 1.3686322 | AN22: 1.441408 | AO22: 1.4235345 | AP22: 1.4136415 | AQ22: 1.4477218 | AR22: 1.6083517 | AS22: 1.4718841 | AT22: 1.4108943 | AU22: 1.5181446 | AV22: 1.5657417 | AW22: 1.3207926 | AX22: 1.525982 | AY22: 1.361022 | AZ22: 1.4413327 | BA22: 1.3544251 | BB22: 1.3185577 | BC22: 1.1143625 | BD22: 1.116073 | BE22: 1.3639846 | BF22: 1.2757531 | BG22: 1.5323896 | BH22: 1.3957666 | BI22: 1.126509 | BJ22: 1.0979491 | BK22: 1.2464675 | BL22: 1.3379438 | BM22: 1.2676733 | BN22: 1.3707789
A23: More than 1 Candidate to Select | B23: Tỷ lệ người trả lời cho biết có từ hai ứng cử viên trở lên để dân bầu trưởng thôn/tổ trưởng tổ dân phố (%) | C23: 0%-100% | D23: =VLOOKUP(A23,'2022_PAPI_Indicators'!A18:B198,2,) -> 0.47496507 | E23: =VLOOKUP(A23,'2022_PAPI_Indicators'!A18:C198,3,FALSE) -> 0.34724215 | F23: =VLOOKUP(A23,'2022_PAPI_Indicators'!A18:D198,4,FALSE) -> 0.28284243 | G23: =VLOOKUP(A23,'2022_PAPI_Indicators'!A18:E198,5,FALSE) -> 0.56758052 | H23: =VLOOKUP(A23,'2022_PAPI_Indicators'!A18:F198,6,FALSE) -> 0.56160617 | I23: =VLOOKUP(A23,'2022_PAPI_Indicators'!A18:G198,7,FALSE) -> 0.42795104 | J23: =VLOOKUP(A23,'2022_PAPI_Indicators'!A18:H198,8,FALSE) -> 0.51302963 | K23: =VLOOKUP(A23,'2022_PAPI_Indicators'!A18:I198,9,FALSE) -> 0.63742346 | L23: =VLOOKUP(A23,'2022_PAPI_Indicators'!A18:J198,10,FALSE) -> 0.50815904 | M23: =VLOOKUP(A23,'2022_PAPI_Indicators'!A18:K198,11,FALSE) -> 0.54509658 | N23: =VLOOKUP(A23,'2022_PAPI_Indicators'!A18:L198,12,FALSE) -> 0.580607 | O23: =VLOOKUP(A23,'2022_PAPI_Indicators'!A18:M198,13,FALSE) -> 0.44983822 | P23: =VLOOKUP(A23,'2022_PAPI_Indicators'!A18:N198,14,FALSE) -> 0.54860818 | Q23: =VLOOKUP(A23,'2022_PAPI_Indicators'!A18:O198,15,FALSE) -> 0.57543844 | R23: =VLOOKUP(A23,'2022_PAPI_Indicators'!A18:P198,16,FALSE) -> 0 | S23: =VLOOKUP(A23,'2022_PAPI_Indicators'!A18:R198,17,FALSE) -> 0.50146586 | T23: =VLOOKUP(A23,'2022_PAPI_Indicators'!A18:S198,18,FALSE) -> 0.55993199 | U23: =VLOOKUP(A23,'2022_PAPI_Indicators'!A18:T198,19,FALSE) -> 0.63951588 | V23: =VLOOKUP(A23,'2022_PAPI_Indicators'!A18:U198,20,FALSE) -> 0.46688285 | W23: =VLOOKUP(A23,'2022_PAPI_Indicators'!A18:V198,21,FALSE) -> 0.65859294 | X23: =VLOOKUP(A23,'2022_PAPI_Indicators'!A18:W198,22,FALSE) -> 0.39671284 | Y23: =VLOOKUP(A23,'2022_PAPI_Indicators'!A18:X198,23,FALSE) -> 0.56613404 | Z23: =VLOOKUP(A23,'2022_PAPI_Indicators'!A18:Y198,24,FALSE) -> 0.42241383 | AA23: =VLOOKUP(A23,'2022_PAPI_Indicators'!A18:Z198,25,FALSE) -> 0.64343989 | AB23: =VLOOKUP(A23,'2022_PAPI_Indicators'!A18:AA198,26,FALSE) -> 0.71469891 | AC23: =VLOOKUP(A23,'2022_PAPI_Indicators'!A18:AB198,27,FALSE) -> 0.63660783 | AD23: =VLOOKUP(A23,'2022_PAPI_Indicators'!A18:AC198,28,FALSE) -> 0.6008482 | AE23: =VLOOKUP(A23,'2022_PAPI_Indicators'!A18:AD198,29,FALSE) -> 0.54399109 | AF23: =VLOOKUP(A23,'2022_PAPI_Indicators'!A18:AE198,30,FALSE) -> 0.62677884 | AG23: =VLOOKUP(A23,'2022_PAPI_Indicators'!A18:AF198,31,FALSE) -> 0.5919739 | AH23: =VLOOKUP(A23,'2022_PAPI_Indicators'!A18:AG198,32,FALSE) -> 0.63903189 | AI23: =VLOOKUP(A23,'2022_PAPI_Indicators'!A18:AH198,33,FALSE) -> 0.54137158 | AJ23: =VLOOKUP(A23,'2022_PAPI_Indicators'!A18:AI198,34,FALSE) -> 0.57283789 | AK23: =VLOOKUP(A23,'2022_PAPI_Indicators'!A18:AJ198,35,FALSE) -> 0.49849081 | AL23: =VLOOKUP(A23,'2022_PAPI_Indicators'!A18:AK198,36,FALSE) -> 0.38908494 | AM23: =VLOOKUP(A23,'2022_PAPI_Indicators'!A18:AL198,37,FALSE) -> 0.40318552 | AN23: =VLOOKUP(A23,'2022_PAPI_Indicators'!A18:AM198,38,FALSE) -> 0.37204367 | AO23: =VLOOKUP(A23,'2022_PAPI_Indicators'!A18:AN198,39,FALSE) -> 0.53304315 | AP23: =VLOOKUP(A23,'2022_PAPI_Indicators'!A18:AO198,40,FALSE) -> 0.49230105 | AQ23: =VLOOKUP(A23,'2022_PAPI_Indicators'!A18:AP198,41,FALSE) -> 0.46067789 | AR23: =VLOOKUP(A23,'2022_PAPI_Indicators'!A18:AQ198,42,FALSE) -> 0.53116566 | AS23: =VLOOKUP(A23,'2022_PAPI_Indicators'!A18:AR198,43,FALSE) -> 0.43949637 | AT23: =VLOOKUP(A23,'2022_PAPI_Indicators'!A18:AS198,44,FALSE) -> 0.46742961 | AU23: =VLOOKUP(A23,'2022_PAPI_Indicators'!A18:AT198,45,FALSE) -> 0.50445747 | AV23: =VLOOKUP(A23,'2022_PAPI_Indicators'!A18:AU198,46,FALSE) -> 0.4672834 | AW23: =VLOOKUP(A23,'2022_PAPI_Indicators'!A18:AV198,47,FALSE) -> 0.26250136 | AX23: =VLOOKUP(A23,'2022_PAPI_Indicators'!A18:AW198,48,FALSE) -> 0.63730252 | AY23: =VLOOKUP(A23,'2022_PAPI_Indicators'!A18:AX198,49,FALSE) -> 0.32003403 | AZ23: =VLOOKUP(A23,'2022_PAPI_Indicators'!A18:AY198,50,FALSE) -> 0.51563883 | BA23: =VLOOKUP(A23,'2022_PAPI_Indicators'!A18:AZ198,51,FALSE) -> 0.24404645 | BB23: =VLOOKUP(A23,'2022_PAPI_Indicators'!A18:BA198,52,FALSE) -> 0.33738762 | BC23: =VLOOKUP(A23,'2022_PAPI_Indicators'!A18:BB198,53,FALSE) -> 0.23846634 | BD23: =VLOOKUP(A23,'2022_PAPI_Indicators'!A18:BC198,54,FALSE) -> 0.23540126 | BE23: =VLOOKUP(A23,'2022_PAPI_Indicators'!A18:BD198,55,FALSE) -> 0.53747404 | BF23: =VLOOKUP(A23,'2022_PAPI_Indicators'!A18:BE198,56,FALSE) -> 0.48977366 | BG23: =VLOOKUP(A23,'2022_PAPI_Indicators'!A18:BF198,57,FALSE) -> 0.39546654 | BH23: =VLOOKUP(A23,'2022_PAPI_Indicators'!A18:BG198,58,FALSE) -> 0.57574356 | BI23: =VLOOKUP(A23,'2022_PAPI_Indicators'!A18:BH198,59,FALSE) -> 0.30913588 | BJ23: =VLOOKUP(A23,'2022_PAPI_Indicators'!A18:BI198,60,FALSE) -> 0.24468236 | BK23: =VLOOKUP(A23,'2022_PAPI_Indicators'!A18:BJ198,61,FALSE) -> 0.32154146 | BL23: =VLOOKUP(A23,'2022_PAPI_Indicators'!A18:BK198,62,FALSE) -> 0.56858242 | BM23: =VLOOKUP(A23,'2022_PAPI_Indicators'!A18:BL198,63,FALSE) -> 0.47554567 | BN23: =VLOOKUP(A23,'2022_PAPI_Indicators'!A18:BM198,64,FALSE) -> 0.53378034
A24: Invited to Participate | B24: Tỷ lệ người trả lời cho biết gia đình được mời đi bầu trưởng thôn/tổ trưởng tổ dân phố (%) | C24: 0%-100% | D24: =VLOOKUP(A24,'2022_PAPI_Indicators'!A19:B199,2,) -> 0.55430651 | E24: =VLOOKUP(A24,'2022_PAPI_Indicators'!A19:C199,3,FALSE) -> 0.4177801 | F24: =VLOOKUP(A24,'2022_PAPI_Indicators'!A19:D199,4,FALSE) -> 0.33414358 | G24: =VLOOKUP(A24,'2022_PAPI_Indicators'!A19:E199,5,FALSE) -> 0.61308318 | H24: =VLOOKUP(A24,'2022_PAPI_Indicators'!A19:F199,6,FALSE) -> 0.67106748 | I24: =VLOOKUP(A24,'2022_PAPI_Indicators'!A19:G199,7,FALSE) -> 0.50878578 | J24: =VLOOKUP(A24,'2022_PAPI_Indicators'!A19:H199,8,FALSE) -> 0.65204936 | K24: =VLOOKUP(A24,'2022_PAPI_Indicators'!A19:I199,9,FALSE) -> 0.72957194 | L24: =VLOOKUP(A24,'2022_PAPI_Indicators'!A19:J199,10,FALSE) -> 0.60798877 | M24: =VLOOKUP(A24,'2022_PAPI_Indicators'!A19:K199,11,FALSE) -> 0.59973311 | N24: =VLOOKUP(A24,'2022_PAPI_Indicators'!A19:L199,12,FALSE) -> 0.73679084 | O24: =VLOOKUP(A24,'2022_PAPI_Indicators'!A19:M199,13,FALSE) -> 0.5987916 | P24: =VLOOKUP(A24,'2022_PAPI_Indicators'!A19:N199,14,FALSE) -> 0.68702251 | Q24: =VLOOKUP(A24,'2022_PAPI_Indicators'!A19:O199,15,FALSE) -> 0.74699944 | R24: =VLOOKUP(A24,'2022_PAPI_Indicators'!A19:P199,16,FALSE) -> 0 | S24: =VLOOKUP(A24,'2022_PAPI_Indicators'!A19:R199,17,FALSE) -> 0.76709086 | T24: =VLOOKUP(A24,'2022_PAPI_Indicators'!A19:S199,18,FALSE) -> 0.67409432 | U24: =VLOOKUP(A24,'2022_PAPI_Indicators'!A19:T199,19,FALSE) -> 0.7087971 | V24: =VLOOKUP(A24,'2022_PAPI_Indicators'!A19:U199,20,FALSE) -> 0.74396747 | W24: =VLOOKUP(A24,'2022_PAPI_Indicators'!A19:V199,21,FALSE) -> 0.86726636 | X24: =VLOOKUP(A24,'2022_PAPI_Indicators'!A19:W199,22,FALSE) -> 0.60042101 | Y24: =VLOOKUP(A24,'2022_PAPI_Indicators'!A19:X199,23,FALSE) -> 0.65217972 | Z24: =VLOOKUP(A24,'2022_PAPI_Indicators'!A19:Y199,24,FALSE) -> 0.51701558 | AA24: =VLOOKUP(A24,'2022_PAPI_Indicators'!A19:Z199,25,FALSE) -> 0.7616995 | AB24: =VLOOKUP(A24,'2022_PAPI_Indicators'!A19:AA199,26,FALSE) -> 0.84992284 | AC24: =VLOOKUP(A24,'2022_PAPI_Indicators'!A19:AB199,27,FALSE) -> 0.75453067 | AD24: =VLOOKUP(A24,'2022_PAPI_Indicators'!A19:AC199,28,FALSE) -> 0.74071503 | AE24: =VLOOKUP(A24,'2022_PAPI_Indicators'!A19:AD199,29,FALSE) -> 0.66504824 | AF24: =VLOOKUP(A24,'2022_PAPI_Indicators'!A19:AE199,30,FALSE) -> 0.69574028 | AG24: =VLOOKUP(A24,'2022_PAPI_Indicators'!A19:AF199,31,FALSE) -> 0.67904824 | AH24: =VLOOKUP(A24,'2022_PAPI_Indicators'!A19:AG199,32,FALSE) -> 0.6843574 | AI24: =VLOOKUP(A24,'2022_PAPI_Indicators'!A19:AH199,33,FALSE) -> 0.67762625 | AJ24: =VLOOKUP(A24,'2022_PAPI_Indicators'!A19:AI199,34,FALSE) -> 0.7202372 | AK24: =VLOOKUP(A24,'2022_PAPI_Indicators'!A19:AJ199,35,FALSE) -> 0.62614012 | AL24: =VLOOKUP(A24,'2022_PAPI_Indicators'!A19:AK199,36,FALSE) -> 0.42954454 | AM24: =VLOOKUP(A24,'2022_PAPI_Indicators'!A19:AL199,37,FALSE) -> 0.49203619 | AN24: =VLOOKUP(A24,'2022_PAPI_Indicators'!A19:AM199,38,FALSE) -> 0.46931225 | AO24: =VLOOKUP(A24,'2022_PAPI_Indicators'!A19:AN199,39,FALSE) -> 0.55654466 | AP24: =VLOOKUP(A24,'2022_PAPI_Indicators'!A19:AO199,40,FALSE) -> 0.49547145 | AQ24: =VLOOKUP(A24,'2022_PAPI_Indicators'!A19:AP199,41,FALSE) -> 0.52694952 | AR24: =VLOOKUP(A24,'2022_PAPI_Indicators'!A19:AQ199,42,FALSE) -> 0.74569261 | AS24: =VLOOKUP(A24,'2022_PAPI_Indicators'!A19:AR199,43,FALSE) -> 0.54579777 | AT24: =VLOOKUP(A24,'2022_PAPI_Indicators'!A19:AS199,44,FALSE) -> 0.49491251 | AU24: =VLOOKUP(A24,'2022_PAPI_Indicators'!A19:AT199,45,FALSE) -> 0.58031583 | AV24: =VLOOKUP(A24,'2022_PAPI_Indicators'!A19:AU199,46,FALSE) -> 0.49719089 | AW24: =VLOOKUP(A24,'2022_PAPI_Indicators'!A19:AV199,47,FALSE) -> 0.29983196 | AX24: =VLOOKUP(A24,'2022_PAPI_Indicators'!A19:AW199,48,FALSE) -> 0.66221929 | AY24: =VLOOKUP(A24,'2022_PAPI_Indicators'!A19:AX199,49,FALSE) -> 0.382626 | AZ24: =VLOOKUP(A24,'2022_PAPI_Indicators'!A19:AY199,50,FALSE) -> 0.54988104 | BA24: =VLOOKUP(A24,'2022_PAPI_Indicators'!A19:AZ199,51,FALSE) -> 0.27926442 | BB24: =VLOOKUP(A24,'2022_PAPI_Indicators'!A19:BA199,52,FALSE) -> 0.35778266 | BC24: =VLOOKUP(A24,'2022_PAPI_Indicators'!A19:BB199,53,FALSE) -> 0.24776357 | BD24: =VLOOKUP(A24,'2022_PAPI_Indicators'!A19:BC199,54,FALSE) -> 0.25098917 | BE24: =VLOOKUP(A24,'2022_PAPI_Indicators'!A19:BD199,55,FALSE) -> 0.57911181 | BF24: =VLOOKUP(A24,'2022_PAPI_Indicators'!A19:BE199,56,FALSE) -> 0.54004639 | BG24: =VLOOKUP(A24,'2022_PAPI_Indicators'!A19:BF199,57,FALSE) -> 0.48097962 | BH24: =VLOOKUP(A24,'2022_PAPI_Indicators'!A19:BG199,58,FALSE) -> 0.69158596 | BI24: =VLOOKUP(A24,'2022_PAPI_Indicators'!A19:BH199,59,FALSE) -> 0.34392169 | BJ24: =VLOOKUP(A24,'2022_PAPI_Indicators'!A19:BI199,60,FALSE) -> 0.28005594 | BK24: =VLOOKUP(A24,'2022_PAPI_Indicators'!A19:BJ199,61,FALSE) -> 0.33681476 | BL24: =VLOOKUP(A24,'2022_PAPI_Indicators'!A19:BK199,62,FALSE) -> 0.7452035 | BM24: =VLOOKUP(A24,'2022_PAPI_Indicators'!A19:BL199,63,FALSE) -> 0.50622606 | BN24: =VLOOKUP(A24,'2022_PAPI_Indicators'!A19:BM199,64,FALSE) -> 0.60396725
A25: Paper Ballot was Used | B25: Tỷ lệ người trả lời cho biết hình thức bầu trưởng thôn/tổ trưởng tổ dân phố là bỏ phiếu kín (%) | C25: 0%-100% | D25: =VLOOKUP(A25,'2022_PAPI_Indicators'!A20:B200,2,) -> 0.6746344 | E25: =VLOOKUP(A25,'2022_PAPI_Indicators'!A20:C200,3,FALSE) -> 0.57918608 | F25: =VLOOKUP(A25,'2022_PAPI_Indicators'!A20:D200,4,FALSE) -> 0.72131401 | G25: =VLOOKUP(A25,'2022_PAPI_Indicators'!A20:E200,5,FALSE) -> 0.81807905 | H25: =VLOOKUP(A25,'2022_PAPI_Indicators'!A20:F200,6,FALSE) -> 0.62283158 | I25: =VLOOKUP(A25,'2022_PAPI_Indicators'!A20:G200,7,FALSE) -> 0.5860312 | J25: =VLOOKUP(A25,'2022_PAPI_Indicators'!A20:H200,8,FALSE) -> 0.672656 | K25: =VLOOKUP(A25,'2022_PAPI_Indicators'!A20:I200,9,FALSE) -> 0.80011892 | L25: =VLOOKUP(A25,'2022_PAPI_Indicators'!A20:J200,10,FALSE) -> 0.73918957 | M25: =VLOOKUP(A25,'2022_PAPI_Indicators'!A20:K200,11,FALSE) -> 0.6729086 | N25: =VLOOKUP(A25,'2022_PAPI_Indicators'!A20:L200,12,FALSE) -> 0.74945349 | O25: =VLOOKUP(A25,'2022_PAPI_Indicators'!A20:M200,13,FALSE) -> 0.54883182 | P25: =VLOOKUP(A25,'2022_PAPI_Indicators'!A20:N200,14,FALSE) -> 0.4419758 | Q25: =VLOOKUP(A25,'2022_PAPI_Indicators'!A20:O200,15,FALSE) -> 0.83793467 | R25: =VLOOKUP(A25,'2022_PAPI_Indicators'!A20:P200,16,FALSE) -> 0 | S25: =VLOOKUP(A25,'2022_PAPI_Indicators'!A20:R200,17,FALSE) -> 0.40173408 | T25: =VLOOKUP(A25,'2022_PAPI_Indicators'!A20:S200,18,FALSE) -> 0.91881138 | U25: =VLOOKUP(A25,'2022_PAPI_Indicators'!A20:T200,19,FALSE) -> 0.9491204 | V25: =VLOOKUP(A25,'2022_PAPI_Indicators'!A20:U200,20,FALSE) -> 0.96756566 | W25: =VLOOKUP(A25,'2022_PAPI_Indicators'!A20:V200,21,FALSE) -> 0.5099715 | X25: =VLOOKUP(A25,'2022_PAPI_Indicators'!A20:W200,22,FALSE) -> 0.94861865 | Y25: =VLOOKUP(A25,'2022_PAPI_Indicators'!A20:X200,23,FALSE) -> 0.95734447 | Z25: =VLOOKUP(A25,'2022_PAPI_Indicators'!A20:Y200,24,FALSE) -> 0.80971003 | AA25: =VLOOKUP(A25,'2022_PAPI_Indicators'!A20:Z200,25,FALSE) -> 0.81995893 | AB25: =VLOOKUP(A25,'2022_PAPI_Indicators'!A20:AA200,26,FALSE) -> 0.86800611 | AC25: =VLOOKUP(A25,'2022_PAPI_Indicators'!A20:AB200,27,FALSE) -> 0.79832345 | AD25: =VLOOKUP(A25,'2022_PAPI_Indicators'!A20:AC200,28,FALSE) -> 0.7465502 | AE25: =VLOOKUP(A25,'2022_PAPI_Indicators'!A20:AD200,29,FALSE) -> 0.84593004 | AF25: =VLOOKUP(A25,'2022_PAPI_Indicators'!A20:AE200,30,FALSE) -> 0.83036542 | AG25: =VLOOKUP(A25,'2022_PAPI_Indicators'!A20:AF200,31,FALSE) -> 0.90783304 | AH25: =VLOOKUP(A25,'2022_PAPI_Indicators'!A20:AG200,32,FALSE) -> 0.92520064 | AI25: =VLOOKUP(A25,'2022_PAPI_Indicators'!A20:AH200,33,FALSE) -> 0.25622627 | AJ25: =VLOOKUP(A25,'2022_PAPI_Indicators'!A20:AI200,34,FALSE) -> 0.96783733 | AK25: =VLOOKUP(A25,'2022_PAPI_Indicators'!A20:AJ200,35,FALSE) -> 0.77025419 | AL25: =VLOOKUP(A25,'2022_PAPI_Indicators'!A20:AK200,36,FALSE) -> 0.97273999 | AM25: =VLOOKUP(A25,'2022_PAPI_Indicators'!A20:AL200,37,FALSE) -> 0.97926122 | AN25: =VLOOKUP(A25,'2022_PAPI_Indicators'!A20:AM200,38,FALSE) -> 0.86606622 | AO25: =VLOOKUP(A25,'2022_PAPI_Indicators'!A20:AN200,39,FALSE) -> 0.95747495 | AP25: =VLOOKUP(A25,'2022_PAPI_Indicators'!A20:AO200,40,FALSE) -> 0.98245621 | AQ25: =VLOOKUP(A25,'2022_PAPI_Indicators'!A20:AP200,41,FALSE) -> 0.58144027 | AR25: =VLOOKUP(A25,'2022_PAPI_Indicators'!A20:AQ200,42,FALSE) -> 0.70861274 | AS25: =VLOOKUP(A25,'2022_PAPI_Indicators'!A20:AR200,43,FALSE) -> 0.59718275 | AT25: =VLOOKUP(A25,'2022_PAPI_Indicators'!A20:AS200,44,FALSE) -> 0.86218315 | AU25: =VLOOKUP(A25,'2022_PAPI_Indicators'!A20:AT200,45,FALSE) -> 0.80231428 | AV25: =VLOOKUP(A25,'2022_PAPI_Indicators'!A20:AU200,46,FALSE) -> 0.96956772 | AW25: =VLOOKUP(A25,'2022_PAPI_Indicators'!A20:AV200,47,FALSE) -> 0.85344285 | AX25: =VLOOKUP(A25,'2022_PAPI_Indicators'!A20:AW200,48,FALSE) -> 0.94970822 | AY25: =VLOOKUP(A25,'2022_PAPI_Indicators'!A20:AX200,49,FALSE) -> 0.82316869 | AZ25: =VLOOKUP(A25,'2022_PAPI_Indicators'!A20:AY200,50,FALSE) -> 0.93587774 | BA25: =VLOOKUP(A25,'2022_PAPI_Indicators'!A20:AZ200,51,FALSE) -> 0.6798318 | BB25: =VLOOKUP(A25,'2022_PAPI_Indicators'!A20:BA200,52,FALSE) -> 0.95442212 | BC25: =VLOOKUP(A25,'2022_PAPI_Indicators'!A20:BB200,53,FALSE) -> 0.99233586 | BD25: =VLOOKUP(A25,'2022_PAPI_Indicators'!A20:BC200,54,FALSE) -> 0.99504912 | BE25: =VLOOKUP(A25,'2022_PAPI_Indicators'!A20:BD200,55,FALSE) -> 0.99507743 | BF25: =VLOOKUP(A25,'2022_PAPI_Indicators'!A20:BE200,56,FALSE) -> 0.97743988 | BG25: =VLOOKUP(A25,'2022_PAPI_Indicators'!A20:BF200,57,FALSE) -> 0.93475121 | BH25: =VLOOKUP(A25,'2022_PAPI_Indicators'!A20:BG200,58,FALSE) -> 0.97916603 | BI25: =VLOOKUP(A25,'2022_PAPI_Indicators'!A20:BH200,59,FALSE) -> 1 | BJ25: =VLOOKUP(A25,'2022_PAPI_Indicators'!A20:BI200,60,FALSE) -> 0.99245059 | BK25: =VLOOKUP(A25,'2022_PAPI_Indicators'!A20:BJ200,61,FALSE) -> 1 | BL25: =VLOOKUP(A25,'2022_PAPI_Indicators'!A20:BK200,62,FALSE) -> 0.99728388 | BM25: =VLOOKUP(A25,'2022_PAPI_Indicators'!A20:BL200,63,FALSE) -> 0.964145 | BN25: =VLOOKUP(A25,'2022_PAPI_Indicators'!A20:BM200,64,FALSE) -> 0.9957183
A26: Votes Counted in Public | B26: Tỷ lệ người trả lời cho biết kết quả bầu cử trưởng thôn/tổ trưởng tổ dân phố được niêm yết công khai (%) | C26: 0%-100% | D26: =VLOOKUP(A26,'2022_PAPI_Indicators'!A21:B201,2,) -> 0.88301671 | E26: =VLOOKUP(A26,'2022_PAPI_Indicators'!A21:C201,3,FALSE) -> 0.88455725 | F26: =VLOOKUP(A26,'2022_PAPI_Indicators'!A21:D201,4,FALSE) -> 0.96597117 | G26: =VLOOKUP(A26,'2022_PAPI_Indicators'!A21:E201,5,FALSE) -> 0.94044095 | H26: =VLOOKUP(A26,'2022_PAPI_Indicators'!A21:F201,6,FALSE) -> 0.91618496 | I26: =VLOOKUP(A26,'2022_PAPI_Indicators'!A21:G201,7,FALSE) -> 0.87219602 | J26: =VLOOKUP(A26,'2022_PAPI_Indicators'!A21:H201,8,FALSE) -> 0.91367203 | K26: =VLOOKUP(A26,'2022_PAPI_Indicators'!A21:I201,9,FALSE) -> 0.75450999 | L26: =VLOOKUP(A26,'2022_PAPI_Indicators'!A21:J201,10,FALSE) -> 0.88436937 | M26: =VLOOKUP(A26,'2022_PAPI_Indicators'!A21:K201,11,FALSE) -> 0.97851712 | N26: =VLOOKUP(A26,'2022_PAPI_Indicators'!A21:L201,12,FALSE) -> 0.85002095 | O26: =VLOOKUP(A26,'2022_PAPI_Indicators'!A21:M201,13,FALSE) -> 0.91674477 | P26: =VLOOKUP(A26,'2022_PAPI_Indicators'!A21:N201,14,FALSE) -> 0.92970592 | Q26: =VLOOKUP(A26,'2022_PAPI_Indicators'!A21:O201,15,FALSE) -> 0.618541 | R26: =VLOOKUP(A26,'2022_PAPI_Indicators'!A21:P201,16,FALSE) -> 0 | S26: =VLOOKUP(A26,'2022_PAPI_Indicators'!A21:R201,17,FALSE) -> 0.96511483 | T26: =VLOOKUP(A26,'2022_PAPI_Indicators'!A21:S201,18,FALSE) -> 0.79115593 | U26: =VLOOKUP(A26,'2022_PAPI_Indicators'!A21:T201,19,FALSE) -> 0.71445876 | V26: =VLOOKUP(A26,'2022_PAPI_Indicators'!A21:U201,20,FALSE) -> 0.6276688 | W26: =VLOOKUP(A26,'2022_PAPI_Indicators'!A21:V201,21,FALSE) -> 0.89530855 | X26: =VLOOKUP(A26,'2022_PAPI_Indicators'!A21:W201,22,FALSE) -> 0.68269497 | Y26: =VLOOKUP(A26,'2022_PAPI_Indicators'!A21:X201,23,FALSE) -> 0.60960943 | Z26: =VLOOKUP(A26,'2022_PAPI_Indicators'!A21:Y201,24,FALSE) -> 0.79947078 | AA26: =VLOOKUP(A26,'2022_PAPI_Indicators'!A21:Z201,25,FALSE) -> 0.88112557 | AB26: =VLOOKUP(A26,'2022_PAPI_Indicators'!A21:AA201,26,FALSE) -> 0.78413731 | AC26: =VLOOKUP(A26,'2022_PAPI_Indicators'!A21:AB201,27,FALSE) -> 0.91033596 | AD26: =VLOOKUP(A26,'2022_PAPI_Indicators'!A21:AC201,28,FALSE) -> 0.8707006 | AE26: =VLOOKUP(A26,'2022_PAPI_Indicators'!A21:AD201,29,FALSE) -> 0.93096834 | AF26: =VLOOKUP(A26,'2022_PAPI_Indicators'!A21:AE201,30,FALSE) -> 0.90568888 | AG26: =VLOOKUP(A26,'2022_PAPI_Indicators'!A21:AF201,31,FALSE) -> 0.7295813 | AH26: =VLOOKUP(A26,'2022_PAPI_Indicators'!A21:AG201,32,FALSE) -> 0.82439804 | AI26: =VLOOKUP(A26,'2022_PAPI_Indicators'!A21:AH201,33,FALSE) -> 0.91048259 | AJ26: =VLOOKUP(A26,'2022_PAPI_Indicators'!A21:AI201,34,FALSE) -> 0.53469056 | AK26: =VLOOKUP(A26,'2022_PAPI_Indicators'!A21:AJ201,35,FALSE) -> 0.76316357 | AL26: =VLOOKUP(A26,'2022_PAPI_Indicators'!A21:AK201,36,FALSE) -> 0.52460116 | AM26: =VLOOKUP(A26,'2022_PAPI_Indicators'!A21:AL201,37,FALSE) -> 0.51487905 | AN26: =VLOOKUP(A26,'2022_PAPI_Indicators'!A21:AM201,38,FALSE) -> 0.51493686 | AO26: =VLOOKUP(A26,'2022_PAPI_Indicators'!A21:AN201,39,FALSE) -> 0.54427981 | AP26: =VLOOKUP(A26,'2022_PAPI_Indicators'!A21:AO201,40,FALSE) -> 0.66044223 | AQ26: =VLOOKUP(A26,'2022_PAPI_Indicators'!A21:AP201,41,FALSE) -> 0.77764827 | AR26: =VLOOKUP(A26,'2022_PAPI_Indicators'!A21:AQ201,42,FALSE) -> 0.7207312 | AS26: =VLOOKUP(A26,'2022_PAPI_Indicators'!A21:AR201,43,FALSE) -> 0.79084158 | AT26: =VLOOKUP(A26,'2022_PAPI_Indicators'!A21:AS201,44,FALSE) -> 0.71871048 | AU26: =VLOOKUP(A26,'2022_PAPI_Indicators'!A21:AT201,45,FALSE) -> 0.67179602 | AV26: =VLOOKUP(A26,'2022_PAPI_Indicators'!A21:AU201,46,FALSE) -> 0.64168841 | AW26: =VLOOKUP(A26,'2022_PAPI_Indicators'!A21:AV201,47,FALSE) -> 0.37718463 | AX26: =VLOOKUP(A26,'2022_PAPI_Indicators'!A21:AW201,48,FALSE) -> 0.59378296 | AY26: =VLOOKUP(A26,'2022_PAPI_Indicators'!A21:AX201,49,FALSE) -> 0.67173523 | AZ26: =VLOOKUP(A26,'2022_PAPI_Indicators'!A21:AY201,50,FALSE) -> 0.63638645 | BA26: =VLOOKUP(A26,'2022_PAPI_Indicators'!A21:AZ201,51,FALSE) -> 0.66516912 | BB26: =VLOOKUP(A26,'2022_PAPI_Indicators'!A21:BA201,52,FALSE) -> 0.56729549 | BC26: =VLOOKUP(A26,'2022_PAPI_Indicators'!A21:BB201,53,FALSE) -> 0.45886657 | BD26: =VLOOKUP(A26,'2022_PAPI_Indicators'!A21:BC201,54,FALSE) -> 0.44133595 | BE26: =VLOOKUP(A26,'2022_PAPI_Indicators'!A21:BD201,55,FALSE) -> 0.36521074 | BF26: =VLOOKUP(A26,'2022_PAPI_Indicators'!A21:BE201,56,FALSE) -> 0.42687389 | BG26: =VLOOKUP(A26,'2022_PAPI_Indicators'!A21:BF201,57,FALSE) -> 0.5149008 | BH26: =VLOOKUP(A26,'2022_PAPI_Indicators'!A21:BG201,58,FALSE) -> 0.39120546 | BI26: =VLOOKUP(A26,'2022_PAPI_Indicators'!A21:BH201,59,FALSE) -> 0.62212878 | BJ26: =VLOOKUP(A26,'2022_PAPI_Indicators'!A21:BI201,60,FALSE) -> 0.47402284 | BK26: =VLOOKUP(A26,'2022_PAPI_Indicators'!A21:BJ201,61,FALSE) -> 0.46183133 | BL26: =VLOOKUP(A26,'2022_PAPI_Indicators'!A21:BK201,62,FALSE) -> 0.41558281 | BM26: =VLOOKUP(A26,'2022_PAPI_Indicators'!A21:BL201,63,FALSE) -> 0.41746324 | BN26: =VLOOKUP(A26,'2022_PAPI_Indicators'!A21:BM201,64,FALSE) -> 0.70747936
A27: Candidate was Not Suggested | B27: Tỷ lệ người trả lời cho biết chính quyền không gợi ý bầu cho một ứng viên cụ thể (%) | C27: 0%-100% | D27: =VLOOKUP(A27,'2022_PAPI_Indicators'!A22:B202,2,) -> 0.12670377 | E27: =VLOOKUP(A27,'2022_PAPI_Indicators'!A22:C202,3,FALSE) -> 0 | F27: =VLOOKUP(A27,'2022_PAPI_Indicators'!A22:D202,4,FALSE) -> 0.46187398 | G27: =VLOOKUP(A27,'2022_PAPI_Indicators'!A22:E202,5,FALSE) -> 0.50825876 | H27: =VLOOKUP(A27,'2022_PAPI_Indicators'!A22:F202,6,FALSE) -> 0.061151262 | I27: =VLOOKUP(A27,'2022_PAPI_Indicators'!A22:G202,7,FALSE) -> 0.16582493 | J27: =VLOOKUP(A27,'2022_PAPI_Indicators'!A22:H202,8,FALSE) -> 0.35266232 | K27: =VLOOKUP(A27,'2022_PAPI_Indicators'!A22:I202,9,FALSE) -> 0.39369735 | L27: =VLOOKUP(A27,'2022_PAPI_Indicators'!A22:J202,10,FALSE) -> 0.27396309 | M27: =VLOOKUP(A27,'2022_PAPI_Indicators'!A22:K202,11,FALSE) -> 0.25693172 | N27: =VLOOKUP(A27,'2022_PAPI_Indicators'!A22:L202,12,FALSE) -> 0.18607876 | O27: =VLOOKUP(A27,'2022_PAPI_Indicators'!A22:M202,13,FALSE) -> 0.12974942 | P27: =VLOOKUP(A27,'2022_PAPI_Indicators'!A22:N202,14,FALSE) -> 0.026604023 | Q27: =VLOOKUP(A27,'2022_PAPI_Indicators'!A22:O202,15,FALSE) -> 0.019271122 | R27: =VLOOKUP(A27,'2022_PAPI_Indicators'!A22:P202,16,FALSE) -> 0 | S27: =VLOOKUP(A27,'2022_PAPI_Indicators'!A22:R202,17,FALSE) -> 0 | T27: =VLOOKUP(A27,'2022_PAPI_Indicators'!A22:S202,18,FALSE) -> 0.54113764 | U27: =VLOOKUP(A27,'2022_PAPI_Indicators'!A22:T202,19,FALSE) -> 0.56169266 | V27: =VLOOKUP(A27,'2022_PAPI_Indicators'!A22:U202,20,FALSE) -> 0.81570172 | W27: =VLOOKUP(A27,'2022_PAPI_Indicators'!A22:V202,21,FALSE) -> 0.049820721 | X27: =VLOOKUP(A27,'2022_PAPI_Indicators'!A22:W202,22,FALSE) -> 0.64865839 | Y27: =VLOOKUP(A27,'2022_PAPI_Indicators'!A22:X202,23,FALSE) -> 0.51124126 | Z27: =VLOOKUP(A27,'2022_PAPI_Indicators'!A22:Y202,24,FALSE) -> 0.25995517 | AA27: =VLOOKUP(A27,'2022_PAPI_Indicators'!A22:Z202,25,FALSE) -> 0.26049495 | AB27: =VLOOKUP(A27,'2022_PAPI_Indicators'!A22:AA202,26,FALSE) -> 0.16666667 | AC27: =VLOOKUP(A27,'2022_PAPI_Indicators'!A22:AB202,27,FALSE) -> 0.28919408 | AD27: =VLOOKUP(A27,'2022_PAPI_Indicators'!A22:AC202,28,FALSE) -> 0.27694264 | AE27: =VLOOKUP(A27,'2022_PAPI_Indicators'!A22:AD202,29,FALSE) -> 0.53087789 | AF27: =VLOOKUP(A27,'2022_PAPI_Indicators'!A22:AE202,30,FALSE) -> 0.53433532 | AG27: =VLOOKUP(A27,'2022_PAPI_Indicators'!A22:AF202,31,FALSE) -> 0.55669451 | AH27: =VLOOKUP(A27,'2022_PAPI_Indicators'!A22:AG202,32,FALSE) -> 0.61123472 | AI27: =VLOOKUP(A27,'2022_PAPI_Indicators'!A22:AH202,33,FALSE) -> 0.048518617 | AJ27: =VLOOKUP(A27,'2022_PAPI_Indicators'!A22:AI202,34,FALSE) -> 0.47954723 | AK27: =VLOOKUP(A27,'2022_PAPI_Indicators'!A22:AJ202,35,FALSE) -> 0.3186608 | AL27: =VLOOKUP(A27,'2022_PAPI_Indicators'!A22:AK202,36,FALSE) -> 0.77348864 | AM27: =VLOOKUP(A27,'2022_PAPI_Indicators'!A22:AL202,37,FALSE) -> 0.5 | AN27: =VLOOKUP(A27,'2022_PAPI_Indicators'!A22:AM202,38,FALSE) -> 0.25959718 | AO27: =VLOOKUP(A27,'2022_PAPI_Indicators'!A22:AN202,39,FALSE) -> 0.61161405 | AP27: =VLOOKUP(A27,'2022_PAPI_Indicators'!A22:AO202,40,FALSE) -> 0.66666669 | AQ27: =VLOOKUP(A27,'2022_PAPI_Indicators'!A22:AP202,41,FALSE) -> 0.2311895 | AR27: =VLOOKUP(A27,'2022_PAPI_Indicators'!A22:AQ202,42,FALSE) -> 0.154678 | AS27: =VLOOKUP(A27,'2022_PAPI_Indicators'!A22:AR202,43,FALSE) -> 0.1685925 | AT27: =VLOOKUP(A27,'2022_PAPI_Indicators'!A22:AS202,44,FALSE) -> 0.51309848 | AU27: =VLOOKUP(A27,'2022_PAPI_Indicators'!A22:AT202,45,FALSE) -> 0.32592839 | AV27: =VLOOKUP(A27,'2022_PAPI_Indicators'!A22:AU202,46,FALSE) -> 0.08224003 | AW27: =VLOOKUP(A27,'2022_PAPI_Indicators'!A22:AV202,47,FALSE) -> 0.18560776 | AX27: =VLOOKUP(A27,'2022_PAPI_Indicators'!A22:AW202,48,FALSE) -> 0.52309567 | AY27: =VLOOKUP(A27,'2022_PAPI_Indicators'!A22:AX202,49,FALSE) -> 0.36490279 | AZ27: =VLOOKUP(A27,'2022_PAPI_Indicators'!A22:AY202,50,FALSE) -> 0.63157892 | BA27: =VLOOKUP(A27,'2022_PAPI_Indicators'!A22:AZ202,51,FALSE) -> 0.13379012 | BB27: =VLOOKUP(A27,'2022_PAPI_Indicators'!A22:BA202,52,FALSE) -> 0.5 | BC27: =VLOOKUP(A27,'2022_PAPI_Indicators'!A22:BB202,53,FALSE) -> 0.9308815 | BD27: =VLOOKUP(A27,'2022_PAPI_Indicators'!A22:BC202,54,FALSE) -> 0.94923437 | BE27: =VLOOKUP(A27,'2022_PAPI_Indicators'!A22:BD202,55,FALSE) -> 0.92275327 | BF27: =VLOOKUP(A27,'2022_PAPI_Indicators'!A22:BE202,56,FALSE) -> 0.76578575 | BG27: =VLOOKUP(A27,'2022_PAPI_Indicators'!A22:BF202,57,FALSE) -> 0 | BH27: =VLOOKUP(A27,'2022_PAPI_Indicators'!A22:BG202,58,FALSE) -> 0.69999999 | BI27: =VLOOKUP(A27,'2022_PAPI_Indicators'!A22:BH202,59,FALSE) -> 1 | BJ27: =VLOOKUP(A27,'2022_PAPI_Indicators'!A22:BI202,60,FALSE) -> 0.93595582 | BK27: =VLOOKUP(A27,'2022_PAPI_Indicators'!A22:BJ202,61,FALSE) -> 0.9632507 | BL27: =VLOOKUP(A27,'2022_PAPI_Indicators'!A22:BK202,62,FALSE) -> 0.75 | BM27: =VLOOKUP(A27,'2022_PAPI_Indicators'!A22:BL202,63,FALSE) -> 0.95898789 | BN27: =VLOOKUP(A27,'2022_PAPI_Indicators'!A22:BM202,64,FALSE) -> 0
A28: Voted for Winner | B28: Tỷ lệ người trả lời cho biết họ đã bầu cho người đã trúng cử (%) | C28: 0%-100% | D28: =VLOOKUP(A28,'2022_PAPI_Indicators'!A23:B203,2,) -> 0.93147224 | E28: =VLOOKUP(A28,'2022_PAPI_Indicators'!A23:C203,3,FALSE) -> 0.90700805 | F28: =VLOOKUP(A28,'2022_PAPI_Indicators'!A23:D203,4,FALSE) -> 0.93666148 | G28: =VLOOKUP(A28,'2022_PAPI_Indicators'!A23:E203,5,FALSE) -> 0.95609456 | H28: =VLOOKUP(A28,'2022_PAPI_Indicators'!A23:F203,6,FALSE) -> 0.92485577 | I28: =VLOOKUP(A28,'2022_PAPI_Indicators'!A23:G203,7,FALSE) -> 0.86346549 | J28: =VLOOKUP(A28,'2022_PAPI_Indicators'!A23:H203,8,FALSE) -> 0.96581995 | K28: =VLOOKUP(A28,'2022_PAPI_Indicators'!A23:I203,9,FALSE) -> 0.89060926 | L28: =VLOOKUP(A28,'2022_PAPI_Indicators'!A23:J203,10,FALSE) -> 0.93778008 | M28: =VLOOKUP(A28,'2022_PAPI_Indicators'!A23:K203,11,FALSE) -> 0.95440114 | N28: =VLOOKUP(A28,'2022_PAPI_Indicators'!A23:L203,12,FALSE) -> 0.93309975 | O28: =VLOOKUP(A28,'2022_PAPI_Indicators'!A23:M203,13,FALSE) -> 0.95932996 | P28: =VLOOKUP(A28,'2022_PAPI_Indicators'!A23:N203,14,FALSE) -> 0.90152514 | Q28: =VLOOKUP(A28,'2022_PAPI_Indicators'!A23:O203,15,FALSE) -> 0.89455032 | R28: =VLOOKUP(A28,'2022_PAPI_Indicators'!A23:P203,16,FALSE) -> 0 | S28: =VLOOKUP(A28,'2022_PAPI_Indicators'!A23:R203,17,FALSE) -> 0.93022966 | T28: =VLOOKUP(A28,'2022_PAPI_Indicators'!A23:S203,18,FALSE) -> 0.92553288 | U28: =VLOOKUP(A28,'2022_PAPI_Indicators'!A23:T203,19,FALSE) -> 0.9697721 | V28: =VLOOKUP(A28,'2022_PAPI_Indicators'!A23:U203,20,FALSE) -> 0.89889157 | W28: =VLOOKUP(A28,'2022_PAPI_Indicators'!A23:V203,21,FALSE) -> 0.99936104 | X28: =VLOOKUP(A28,'2022_PAPI_Indicators'!A23:W203,22,FALSE) -> 0.94532233 | Y28: =VLOOKUP(A28,'2022_PAPI_Indicators'!A23:X203,23,FALSE) -> 0.95167798 | Z28: =VLOOKUP(A28,'2022_PAPI_Indicators'!A23:Y203,24,FALSE) -> 0.97169805 | AA28: =VLOOKUP(A28,'2022_PAPI_Indicators'!A23:Z203,25,FALSE) -> 0.93207175 | AB28: =VLOOKUP(A28,'2022_PAPI_Indicators'!A23:AA203,26,FALSE) -> 0.87921977 | AC28: =VLOOKUP(A28,'2022_PAPI_Indicators'!A23:AB203,27,FALSE) -> 0.97074026 | AD28: =VLOOKUP(A28,'2022_PAPI_Indicators'!A23:AC203,28,FALSE) -> 0.95771831 | AE28: =VLOOKUP(A28,'2022_PAPI_Indicators'!A23:AD203,29,FALSE) -> 0.93915409 | AF28: =VLOOKUP(A28,'2022_PAPI_Indicators'!A23:AE203,30,FALSE) -> 0.89879441 | AG28: =VLOOKUP(A28,'2022_PAPI_Indicators'!A23:AF203,31,FALSE) -> 0.87711072 | AH28: =VLOOKUP(A28,'2022_PAPI_Indicators'!A23:AG203,32,FALSE) -> 0.93279827 | AI28: =VLOOKUP(A28,'2022_PAPI_Indicators'!A23:AH203,33,FALSE) -> 0.92487067 | AJ28: =VLOOKUP(A28,'2022_PAPI_Indicators'!A23:AI203,34,FALSE) -> 0.90983164 | AK28: =VLOOKUP(A28,'2022_PAPI_Indicators'!A23:AJ203,35,FALSE) -> 0.94956064 | AL28: =VLOOKUP(A28,'2022_PAPI_Indicators'!A23:AK203,36,FALSE) -> 0.95079762 | AM28: =VLOOKUP(A28,'2022_PAPI_Indicators'!A23:AL203,37,FALSE) -> 0.92425466 | AN28: =VLOOKUP(A28,'2022_PAPI_Indicators'!A23:AM203,38,FALSE) -> 0.88047028 | AO28: =VLOOKUP(A28,'2022_PAPI_Indicators'!A23:AN203,39,FALSE) -> 0.89368731 | AP28: =VLOOKUP(A28,'2022_PAPI_Indicators'!A23:AO203,40,FALSE) -> 0.87323201 | AQ28: =VLOOKUP(A28,'2022_PAPI_Indicators'!A23:AP203,41,FALSE) -> 0.94492954 | AR28: =VLOOKUP(A28,'2022_PAPI_Indicators'!A23:AQ203,42,FALSE) -> 0.88087249 | AS28: =VLOOKUP(A28,'2022_PAPI_Indicators'!A23:AR203,43,FALSE) -> 0.93882596 | AT28: =VLOOKUP(A28,'2022_PAPI_Indicators'!A23:AS203,44,FALSE) -> 0.95119178 | AU28: =VLOOKUP(A28,'2022_PAPI_Indicators'!A23:AT203,45,FALSE) -> 0.87038118 | AV28: =VLOOKUP(A28,'2022_PAPI_Indicators'!A23:AU203,46,FALSE) -> 0.83606035 | AW28: =VLOOKUP(A28,'2022_PAPI_Indicators'!A23:AV203,47,FALSE) -> 0.88684464 | AX28: =VLOOKUP(A28,'2022_PAPI_Indicators'!A23:AW203,48,FALSE) -> 0.91419244 | AY28: =VLOOKUP(A28,'2022_PAPI_Indicators'!A23:AX203,49,FALSE) -> 0.87724638 | AZ28: =VLOOKUP(A28,'2022_PAPI_Indicators'!A23:AY203,50,FALSE) -> 0.89287543 | BA28: =VLOOKUP(A28,'2022_PAPI_Indicators'!A23:AZ203,51,FALSE) -> 0.79101944 | BB28: =VLOOKUP(A28,'2022_PAPI_Indicators'!A23:BA203,52,FALSE) -> 0.87748432 | BC28: =VLOOKUP(A28,'2022_PAPI_Indicators'!A23:BB203,53,FALSE) -> 0.93306148 | BD28: =VLOOKUP(A28,'2022_PAPI_Indicators'!A23:BC203,54,FALSE) -> 0.89752454 | BE28: =VLOOKUP(A28,'2022_PAPI_Indicators'!A23:BD203,55,FALSE) -> 0.90929031 | BF28: =VLOOKUP(A28,'2022_PAPI_Indicators'!A23:BE203,56,FALSE) -> 0.88111728 | BG28: =VLOOKUP(A28,'2022_PAPI_Indicators'!A23:BF203,57,FALSE) -> 0.86241299 | BH28: =VLOOKUP(A28,'2022_PAPI_Indicators'!A23:BG203,58,FALSE) -> 0.87384003 | BI28: =VLOOKUP(A28,'2022_PAPI_Indicators'!A23:BH203,59,FALSE) -> 0.90553218 | BJ28: =VLOOKUP(A28,'2022_PAPI_Indicators'!A23:BI203,60,FALSE) -> 0.86998093 | BK28: =VLOOKUP(A28,'2022_PAPI_Indicators'!A23:BJ203,61,FALSE) -> 0.89312983 | BL28: =VLOOKUP(A28,'2022_PAPI_Indicators'!A23:BK203,62,FALSE) -> 0.93423873 | BM28: =VLOOKUP(A28,'2022_PAPI_Indicators'!A23:BL203,63,FALSE) -> 0.90663648 | BN28: =VLOOKUP(A28,'2022_PAPI_Indicators'!A23:BM203,64,FALSE) -> 0.92365861
A29: Voluntary Contributions | B29: 1.4: Đóng góp tự nguyện | C29: 0.25-2.5 điểm/points | D29: 1.28 | E29: 0.9794063 | F29: 0.80511767 | G29: 1.0044848 | H29: 1.2247975 | I29: 1.0431187 | J29: 0.75831985 | K29: 1.1589204 | L29: 0.79783249 | M29: 0.97365665 | N29: 0.92516834 | O29: 1.099342 | P29: 1.2296796 | Q29: 0.94256157 | R29: 0 | S29: 1.2670701 | T29: 1.1092987 | U29: 1.2622646 | V29: 1.2866832 | W29: 1.0359441 | X29: 1.1795737 | Y29: 0.99524105 | Z29: 1.1924056 | AA29: 1.0389417 | AB29: 0.83281064 | AC29: 1.2961042 | AD29: 1.1660979 | AE29: 1.2461913 | AF29: 0.94477177 | AG29: 0.89244246 | AH29: 1.2708672 | AI29: 0.63921356 | AJ29: 0.65492928 | AK29: 1.0419068 | AL29: 0.96019667 | AM29: 0.87005264 | AN29: 0.71708709 | AO29: 1.2052447 | AP29: 1.5830747 | AQ29: 1.1932834 | AR29: 1.1337743 | AS29: 1.3773526 | AT29: 1.0929514 | AU29: 0.92108846 | AV29: 0.98472983 | AW29: 0.77349216 | AX29: 1.4828119 | AY29: 1.1236087 | AZ29: 0.60141563 | BA29: 1.1866392 | BB29: 1.3578897 | BC29: 1.0894063 | BD29: 1.1539643 | BE29: 0.86388516 | BF29: 1.0614096 | BG29: 0.98520589 | BH29: 1.1120242 | BI29: 0.85265452 | BJ29: 0.96793383 | BK29: 1.0104785 | BL29: 1.2469752 | BM29: 1.2533687 | BN29: 0.73371786
A30: Voluntary Contribution to Local Projects | B30: Tỷ lệ người trả lời cho biết đã đóng góp tự nguyện cho một công trình công cộng ở xã/phường nơi sinh sống (%) | C30: 0%-100% | D30: =VLOOKUP(A30,'2022_PAPI_Indicators'!A25:B205,2,) -> 0.58849573 | E30: =VLOOKUP(A30,'2022_PAPI_Indicators'!A25:C205,3,FALSE) -> 0.37862793 | F30: =VLOOKUP(A30,'2022_PAPI_Indicators'!A25:D205,4,FALSE) -> 0.28059015 | G30: =VLOOKUP(A30,'2022_PAPI_Indicators'!A25:E205,5,FALSE) -> 0.25244886 | H30: =VLOOKUP(A30,'2022_PAPI_Indicators'!A25:F205,6,FALSE) -> 0.42699707 | I30: =VLOOKUP(A30,'2022_PAPI_Indicators'!A25:G205,7,FALSE) -> 0.4897173 | J30: =VLOOKUP(A30,'2022_PAPI_Indicators'!A25:H205,8,FALSE) -> 0.23008305 | K30: =VLOOKUP(A30,'2022_PAPI_Indicators'!A25:I205,9,FALSE) -> 0.50510138 | L30: =VLOOKUP(A30,'2022_PAPI_Indicators'!A25:J205,10,FALSE) -> 0.24813795 | M30: =VLOOKUP(A30,'2022_PAPI_Indicators'!A25:K205,11,FALSE) -> 0.24803151 | N30: =VLOOKUP(A30,'2022_PAPI_Indicators'!A25:L205,12,FALSE) -> 0.23572145 | O30: =VLOOKUP(A30,'2022_PAPI_Indicators'!A25:M205,13,FALSE) -> 0.35144839 | P30: =VLOOKUP(A30,'2022_PAPI_Indicators'!A25:N205,14,FALSE) -> 0.52885789 | Q30: =VLOOKUP(A30,'2022_PAPI_Indicators'!A25:O205,15,FALSE) -> 0.48245627 | R30: =VLOOKUP(A30,'2022_PAPI_Indicators'!A25:P205,16,FALSE) -> 0 | S30: =VLOOKUP(A30,'2022_PAPI_Indicators'!A25:R205,17,FALSE) -> 0.59767425 | T30: =VLOOKUP(A30,'2022_PAPI_Indicators'!A25:S205,18,FALSE) -> 0.46414596 | U30: =VLOOKUP(A30,'2022_PAPI_Indicators'!A25:T205,19,FALSE) -> 0.49026459 | V30: =VLOOKUP(A30,'2022_PAPI_Indicators'!A25:U205,20,FALSE) -> 0.52997768 | W30: =VLOOKUP(A30,'2022_PAPI_Indicators'!A25:V205,21,FALSE) -> 0.4855431 | X30: =VLOOKUP(A30,'2022_PAPI_Indicators'!A25:W205,22,FALSE) -> 0.55848104 | Y30: =VLOOKUP(A30,'2022_PAPI_Indicators'!A25:X205,23,FALSE) -> 0.39286092 | Z30: =VLOOKUP(A30,'2022_PAPI_Indicators'!A25:Y205,24,FALSE) -> 0.43077546 | AA30: =VLOOKUP(A30,'2022_PAPI_Indicators'!A25:Z205,25,FALSE) -> 0.5041604 | AB30: =VLOOKUP(A30,'2022_PAPI_Indicators'!A25:AA205,26,FALSE) -> 0.24758792 | AC30: =VLOOKUP(A30,'2022_PAPI_Indicators'!A25:AB205,27,FALSE) -> 0.49301156 | AD30: =VLOOKUP(A30,'2022_PAPI_Indicators'!A25:AC205,28,FALSE) -> 0.46432588 | AE30: =VLOOKUP(A30,'2022_PAPI_Indicators'!A25:AD205,29,FALSE) -> 0.4263387 | AF30: =VLOOKUP(A30,'2022_PAPI_Indicators'!A25:AE205,30,FALSE) -> 0.28972811 | AG30: =VLOOKUP(A30,'2022_PAPI_Indicators'!A25:AF205,31,FALSE) -> 0.24958563 | AH30: =VLOOKUP(A30,'2022_PAPI_Indicators'!A25:AG205,32,FALSE) -> 0.53107417 | AI30: =VLOOKUP(A30,'2022_PAPI_Indicators'!A25:AH205,33,FALSE) -> 0.16008238 | AJ30: =VLOOKUP(A30,'2022_PAPI_Indicators'!A25:AI205,34,FALSE) -> 0.14777339 | AK30: =VLOOKUP(A30,'2022_PAPI_Indicators'!A25:AJ205,35,FALSE) -> 0.40762788 | AL30: =VLOOKUP(A30,'2022_PAPI_Indicators'!A25:AK205,36,FALSE) -> 0.51456606 | AM30: =VLOOKUP(A30,'2022_PAPI_Indicators'!A25:AL205,37,FALSE) -> 0.30456799 | AN30: =VLOOKUP(A30,'2022_PAPI_Indicators'!A25:AM205,38,FALSE) -> 0.27796301 | AO30: =VLOOKUP(A30,'2022_PAPI_Indicators'!A25:AN205,39,FALSE) -> 0.49637195 | AP30: =VLOOKUP(A30,'2022_PAPI_Indicators'!A25:AO205,40,FALSE) -> 0.64836919 | AQ30: =VLOOKUP(A30,'2022_PAPI_Indicators'!A25:AP205,41,FALSE) -> 0.3593815 | AR30: =VLOOKUP(A30,'2022_PAPI_Indicators'!A25:AQ205,42,FALSE) -> 0.32956818 | AS30: =VLOOKUP(A30,'2022_PAPI_Indicators'!A25:AR205,43,FALSE) -> 0.49604151 | AT30: =VLOOKUP(A30,'2022_PAPI_Indicators'!A25:AS205,44,FALSE) -> 0.37751427 | AU30: =VLOOKUP(A30,'2022_PAPI_Indicators'!A25:AT205,45,FALSE) -> 0.46276337 | AV30: =VLOOKUP(A30,'2022_PAPI_Indicators'!A25:AU205,46,FALSE) -> 0.38247052 | AW30: =VLOOKUP(A30,'2022_PAPI_Indicators'!A25:AV205,47,FALSE) -> 0.256868 | AX30: =VLOOKUP(A30,'2022_PAPI_Indicators'!A25:AW205,48,FALSE) -> 0.69298691 | AY30: =VLOOKUP(A30,'2022_PAPI_Indicators'!A25:AX205,49,FALSE) -> 0.3967784 | AZ30: =VLOOKUP(A30,'2022_PAPI_Indicators'!A25:AY205,50,FALSE) -> 0.18852231 | BA30: =VLOOKUP(A30,'2022_PAPI_Indicators'!A25:AZ205,51,FALSE) -> 0.55273849 | BB30: =VLOOKUP(A30,'2022_PAPI_Indicators'!A25:BA205,52,FALSE) -> 0.4807229 | BC30: =VLOOKUP(A30,'2022_PAPI_Indicators'!A25:BB205,53,FALSE) -> 0.37194228 | BD30: =VLOOKUP(A30,'2022_PAPI_Indicators'!A25:BC205,54,FALSE) -> 0.38879552 | BE30: =VLOOKUP(A30,'2022_PAPI_Indicators'!A25:BD205,55,FALSE) -> 0.40772918 | BF30: =VLOOKUP(A30,'2022_PAPI_Indicators'!A25:BE205,56,FALSE) -> 0.54365891 | BG30: =VLOOKUP(A30,'2022_PAPI_Indicators'!A25:BF205,57,FALSE) -> 0.50549227 | BH30: =VLOOKUP(A30,'2022_PAPI_Indicators'!A25:BG205,58,FALSE) -> 0.49457875 | BI30: =VLOOKUP(A30,'2022_PAPI_Indicators'!A25:BH205,59,FALSE) -> 0.26196903 | BJ30: =VLOOKUP(A30,'2022_PAPI_Indicators'!A25:BI205,60,FALSE) -> 0.30276304 | BK30: =VLOOKUP(A30,'2022_PAPI_Indicators'!A25:BJ205,61,FALSE) -> 0.37727734 | BL30: =VLOOKUP(A30,'2022_PAPI_Indicators'!A25:BK205,62,FALSE) -> 0.61708081 | BM30: =VLOOKUP(A30,'2022_PAPI_Indicators'!A25:BL205,63,FALSE) -> 0.50372857 | BN30: =VLOOKUP(A30,'2022_PAPI_Indicators'!A25:BM205,64,FALSE) -> 0.2534388
A31: Community Monitoring Board Monitors Contribution | B31: Tỷ lệ người trả lời cho biết Ban Thanh tra nhân dân hoặc Ban giám sát đầu tư cộng đồng giám sát việc xây mới/tu sửa công trình (%) | C31: 0%-100% | D31: =VLOOKUP(A31,'2022_PAPI_Indicators'!A26:B206,2,) -> 0.4685263 | E31: =VLOOKUP(A31,'2022_PAPI_Indicators'!A26:C206,3,FALSE) -> 0.31188783 | F31: =VLOOKUP(A31,'2022_PAPI_Indicators'!A26:D206,4,FALSE) -> 0.21522862 | G31: =VLOOKUP(A31,'2022_PAPI_Indicators'!A26:E206,5,FALSE) -> 0.46817294 | H31: =VLOOKUP(A31,'2022_PAPI_Indicators'!A26:F206,6,FALSE) -> 0.4582186 | I31: =VLOOKUP(A31,'2022_PAPI_Indicators'!A26:G206,7,FALSE) -> 0.21782506 | J31: =VLOOKUP(A31,'2022_PAPI_Indicators'!A26:H206,8,FALSE) -> 0.23278667 | K31: =VLOOKUP(A31,'2022_PAPI_Indicators'!A26:I206,9,FALSE) -> 0.38873747 | L31: =VLOOKUP(A31,'2022_PAPI_Indicators'!A26:J206,10,FALSE) -> 0.17535622 | M31: =VLOOKUP(A31,'2022_PAPI_Indicators'!A26:K206,11,FALSE) -> 0.36527205 | N31: =VLOOKUP(A31,'2022_PAPI_Indicators'!A26:L206,12,FALSE) -> 0.33767778 | O31: =VLOOKUP(A31,'2022_PAPI_Indicators'!A26:M206,13,FALSE) -> 0.46926624 | P31: =VLOOKUP(A31,'2022_PAPI_Indicators'!A26:N206,14,FALSE) -> 0.40834218 | Q31: =VLOOKUP(A31,'2022_PAPI_Indicators'!A26:O206,15,FALSE) -> 0.27990392 | R31: =VLOOKUP(A31,'2022_PAPI_Indicators'!A26:P206,16,FALSE) -> 0 | S31: =VLOOKUP(A31,'2022_PAPI_Indicators'!A26:R206,17,FALSE) -> 0.39023256 | T31: =VLOOKUP(A31,'2022_PAPI_Indicators'!A26:S206,18,FALSE) -> 0.39243791 | U31: =VLOOKUP(A31,'2022_PAPI_Indicators'!A26:T206,19,FALSE) -> 0.29825804 | V31: =VLOOKUP(A31,'2022_PAPI_Indicators'!A26:U206,20,FALSE) -> 0.45003724 | W31: =VLOOKUP(A31,'2022_PAPI_Indicators'!A26:V206,21,FALSE) -> 0.30567089 | X31: =VLOOKUP(A31,'2022_PAPI_Indicators'!A26:W206,22,FALSE) -> 0.36230701 | Y31: =VLOOKUP(A31,'2022_PAPI_Indicators'!A26:X206,23,FALSE) -> 0.335706 | Z31: =VLOOKUP(A31,'2022_PAPI_Indicators'!A26:Y206,24,FALSE) -> 0.41196373 | AA31: =VLOOKUP(A31,'2022_PAPI_Indicators'!A26:Z206,25,FALSE) -> 0.37473157 | AB31: =VLOOKUP(A31,'2022_PAPI_Indicators'!A26:AA206,26,FALSE) -> 0.27595538 | AC31: =VLOOKUP(A31,'2022_PAPI_Indicators'!A26:AB206,27,FALSE) -> 0.39253688 | AD31: =VLOOKUP(A31,'2022_PAPI_Indicators'!A26:AC206,28,FALSE) -> 0.36247313 | AE31: =VLOOKUP(A31,'2022_PAPI_Indicators'!A26:AD206,29,FALSE) -> 0.40712529 | AF31: =VLOOKUP(A31,'2022_PAPI_Indicators'!A26:AE206,30,FALSE) -> 0.35725537 | AG31: =VLOOKUP(A31,'2022_PAPI_Indicators'!A26:AF206,31,FALSE) -> 0.31913811 | AH31: =VLOOKUP(A31,'2022_PAPI_Indicators'!A26:AG206,32,FALSE) -> 0.470844 | AI31: =VLOOKUP(A31,'2022_PAPI_Indicators'!A26:AH206,33,FALSE) -> 0.24414429 | AJ31: =VLOOKUP(A31,'2022_PAPI_Indicators'!A26:AI206,34,FALSE) -> 0.23299605 | AK31: =VLOOKUP(A31,'2022_PAPI_Indicators'!A26:AJ206,35,FALSE) -> 0.43170211 | AL31: =VLOOKUP(A31,'2022_PAPI_Indicators'!A26:AK206,36,FALSE) -> 0.25728303 | AM31: =VLOOKUP(A31,'2022_PAPI_Indicators'!A26:AL206,37,FALSE) -> 0.34278646 | AN31: =VLOOKUP(A31,'2022_PAPI_Indicators'!A26:AM206,38,FALSE) -> 0.22370401 | AO31: =VLOOKUP(A31,'2022_PAPI_Indicators'!A26:AN206,39,FALSE) -> 0.41066352 | AP31: =VLOOKUP(A31,'2022_PAPI_Indicators'!A26:AO206,40,FALSE) -> 0.43993741 | AQ31: =VLOOKUP(A31,'2022_PAPI_Indicators'!A26:AP206,41,FALSE) -> 0.51824754 | AR31: =VLOOKUP(A31,'2022_PAPI_Indicators'!A26:AQ206,42,FALSE) -> 0.43588021 | AS31: =VLOOKUP(A31,'2022_PAPI_Indicators'!A26:AR206,43,FALSE) -> 0.51961058 | AT31: =VLOOKUP(A31,'2022_PAPI_Indicators'!A26:AS206,44,FALSE) -> 0.38454685 | AU31: =VLOOKUP(A31,'2022_PAPI_Indicators'!A26:AT206,45,FALSE) -> 0.32032236 | AV31: =VLOOKUP(A31,'2022_PAPI_Indicators'!A26:AU206,46,FALSE) -> 0.25782627 | AW31: =VLOOKUP(A31,'2022_PAPI_Indicators'!A26:AV206,47,FALSE) -> 0.17562801 | AX31: =VLOOKUP(A31,'2022_PAPI_Indicators'!A26:AW206,48,FALSE) -> 0.57753503 | AY31: =VLOOKUP(A31,'2022_PAPI_Indicators'!A26:AX206,49,FALSE) -> 0.38071594 | AZ31: =VLOOKUP(A31,'2022_PAPI_Indicators'!A26:AY206,50,FALSE) -> 0.12568155 | BA31: =VLOOKUP(A31,'2022_PAPI_Indicators'!A26:AZ206,51,FALSE) -> 0.41569787 | BB31: =VLOOKUP(A31,'2022_PAPI_Indicators'!A26:BA206,52,FALSE) -> 0.56453538 | BC31: =VLOOKUP(A31,'2022_PAPI_Indicators'!A26:BB206,53,FALSE) -> 0.42061532 | BD31: =VLOOKUP(A31,'2022_PAPI_Indicators'!A26:BC206,54,FALSE) -> 0.51465106 | BE31: =VLOOKUP(A31,'2022_PAPI_Indicators'!A26:BD206,55,FALSE) -> 0.2524375 | BF31: =VLOOKUP(A31,'2022_PAPI_Indicators'!A26:BE206,56,FALSE) -> 0.30236185 | BG31: =VLOOKUP(A31,'2022_PAPI_Indicators'!A26:BF206,57,FALSE) -> 0.17280309 | BH31: =VLOOKUP(A31,'2022_PAPI_Indicators'!A26:BG206,58,FALSE) -> 0.27255687 | BI31: =VLOOKUP(A31,'2022_PAPI_Indicators'!A26:BH206,59,FALSE) -> 0.38663161 | BJ31: =VLOOKUP(A31,'2022_PAPI_Indicators'!A26:BI206,60,FALSE) -> 0.34709623 | BK31: =VLOOKUP(A31,'2022_PAPI_Indicators'!A26:BJ206,61,FALSE) -> 0.35454965 | BL31: =VLOOKUP(A31,'2022_PAPI_Indicators'!A26:BK206,62,FALSE) -> 0.5139755 | BM31: =VLOOKUP(A31,'2022_PAPI_Indicators'!A26:BL206,63,FALSE) -> 0.42451099 | BN31: =VLOOKUP(A31,'2022_PAPI_Indicators'!A26:BM206,64,FALSE) -> 0.20735903
A32: Voluntary Contribution Recorded | B32: Tỷ lệ người trả lời cho biết đóng góp của họ được ghi chép vào sổ sách của xã/phường (%) | C32: 0%-100% | D32: =VLOOKUP(A32,'2022_PAPI_Indicators'!A27:B207,2,) -> 0.76412314 | E32: =VLOOKUP(A32,'2022_PAPI_Indicators'!A27:C207,3,FALSE) -> 0.63385075 | F32: =VLOOKUP(A32,'2022_PAPI_Indicators'!A27:D207,4,FALSE) -> 0.53014964 | G32: =VLOOKUP(A32,'2022_PAPI_Indicators'!A27:E207,5,FALSE) -> 0.6107949 | H32: =VLOOKUP(A32,'2022_PAPI_Indicators'!A27:F207,6,FALSE) -> 0.76767683 | I32: =VLOOKUP(A32,'2022_PAPI_Indicators'!A27:G207,7,FALSE) -> 0.62871248 | J32: =VLOOKUP(A32,'2022_PAPI_Indicators'!A27:H207,8,FALSE) -> 0.56542927 | K32: =VLOOKUP(A32,'2022_PAPI_Indicators'!A27:I207,9,FALSE) -> 0.71240807 | L32: =VLOOKUP(A32,'2022_PAPI_Indicators'!A27:J207,10,FALSE) -> 0.53791559 | M32: =VLOOKUP(A32,'2022_PAPI_Indicators'!A27:K207,11,FALSE) -> 0.63790751 | N32: =VLOOKUP(A32,'2022_PAPI_Indicators'!A27:L207,12,FALSE) -> 0.66040593 | O32: =VLOOKUP(A32,'2022_PAPI_Indicators'!A27:M207,13,FALSE) -> 0.59760273 | P32: =VLOOKUP(A32,'2022_PAPI_Indicators'!A27:N207,14,FALSE) -> 0.73430002 | Q32: =VLOOKUP(A32,'2022_PAPI_Indicators'!A27:O207,15,FALSE) -> 0.48963293 | R32: =VLOOKUP(A32,'2022_PAPI_Indicators'!A27:P207,16,FALSE) -> 0 | S32: =VLOOKUP(A32,'2022_PAPI_Indicators'!A27:R207,17,FALSE) -> 0.79255831 | T32: =VLOOKUP(A32,'2022_PAPI_Indicators'!A27:S207,18,FALSE) -> 0.64537257 | U32: =VLOOKUP(A32,'2022_PAPI_Indicators'!A27:T207,19,FALSE) -> 0.63471735 | V32: =VLOOKUP(A32,'2022_PAPI_Indicators'!A27:U207,20,FALSE) -> 0.73501116 | W32: =VLOOKUP(A32,'2022_PAPI_Indicators'!A27:V207,21,FALSE) -> 0.69057506 | X32: =VLOOKUP(A32,'2022_PAPI_Indicators'!A27:W207,22,FALSE) -> 0.66504192 | Y32: =VLOOKUP(A32,'2022_PAPI_Indicators'!A27:X207,23,FALSE) -> 0.4571338 | Z32: =VLOOKUP(A32,'2022_PAPI_Indicators'!A27:Y207,24,FALSE) -> 0.66111785 | AA32: =VLOOKUP(A32,'2022_PAPI_Indicators'!A27:Z207,25,FALSE) -> 0.64317155 | AB32: =VLOOKUP(A32,'2022_PAPI_Indicators'!A27:AA207,26,FALSE) -> 0.47221157 | AC32: =VLOOKUP(A32,'2022_PAPI_Indicators'!A27:AB207,27,FALSE) -> 0.80495107 | AD32: =VLOOKUP(A32,'2022_PAPI_Indicators'!A27:AC207,28,FALSE) -> 0.89814723 | AE32: =VLOOKUP(A32,'2022_PAPI_Indicators'!A27:AD207,29,FALSE) -> 0.74163103 | AF32: =VLOOKUP(A32,'2022_PAPI_Indicators'!A27:AE207,30,FALSE) -> 0.57221389 | AG32: =VLOOKUP(A32,'2022_PAPI_Indicators'!A27:AF207,31,FALSE) -> 0.57085305 | AH32: =VLOOKUP(A32,'2022_PAPI_Indicators'!A27:AG207,32,FALSE) -> 0.79207164 | AI32: =VLOOKUP(A32,'2022_PAPI_Indicators'!A27:AH207,33,FALSE) -> 0.31251222 | AJ32: =VLOOKUP(A32,'2022_PAPI_Indicators'!A27:AI207,34,FALSE) -> 0.44577828 | AK32: =VLOOKUP(A32,'2022_PAPI_Indicators'!A27:AJ207,35,FALSE) -> 0.80119056 | AL32: =VLOOKUP(A32,'2022_PAPI_Indicators'!A27:AK207,36,FALSE) -> 0.58322155 | AM32: =VLOOKUP(A32,'2022_PAPI_Indicators'!A27:AL207,37,FALSE) -> 0.5092501 | AN32: =VLOOKUP(A32,'2022_PAPI_Indicators'!A27:AM207,38,FALSE) -> 0.42654333 | AO32: =VLOOKUP(A32,'2022_PAPI_Indicators'!A27:AN207,39,FALSE) -> 0.75991178 | AP32: =VLOOKUP(A32,'2022_PAPI_Indicators'!A27:AO207,40,FALSE) -> 0.77486116 | AQ32: =VLOOKUP(A32,'2022_PAPI_Indicators'!A27:AP207,41,FALSE) -> 0.7725774 | AR32: =VLOOKUP(A32,'2022_PAPI_Indicators'!A27:AQ207,42,FALSE) -> 0.77641213 | AS32: =VLOOKUP(A32,'2022_PAPI_Indicators'!A27:AR207,43,FALSE) -> 0.76376379 | AT32: =VLOOKUP(A32,'2022_PAPI_Indicators'!A27:AS207,44,FALSE) -> 0.6271866 | AU32: =VLOOKUP(A32,'2022_PAPI_Indicators'!A27:AT207,45,FALSE) -> 0.69739783 | AV32: =VLOOKUP(A32,'2022_PAPI_Indicators'!A27:AU207,46,FALSE) -> 0.55924922 | AW32: =VLOOKUP(A32,'2022_PAPI_Indicators'!A27:AV207,47,FALSE) -> 0.46933311 | AX32: =VLOOKUP(A32,'2022_PAPI_Indicators'!A27:AW207,48,FALSE) -> 0.77631193 | AY32: =VLOOKUP(A32,'2022_PAPI_Indicators'!A27:AX207,49,FALSE) -> 0.67240214 | AZ32: =VLOOKUP(A32,'2022_PAPI_Indicators'!A27:AY207,50,FALSE) -> 0.31965619 | BA32: =VLOOKUP(A32,'2022_PAPI_Indicators'!A27:AZ207,51,FALSE) -> 0.78977662 | BB32: =VLOOKUP(A32,'2022_PAPI_Indicators'!A27:BA207,52,FALSE) -> 0.62695467 | BC32: =VLOOKUP(A32,'2022_PAPI_Indicators'!A27:BB207,53,FALSE) -> 0.67282689 | BD32: =VLOOKUP(A32,'2022_PAPI_Indicators'!A27:BC207,54,FALSE) -> 0.53620756 | BE32: =VLOOKUP(A32,'2022_PAPI_Indicators'!A27:BD207,55,FALSE) -> 0.41260418 | BF32: =VLOOKUP(A32,'2022_PAPI_Indicators'!A27:BE207,56,FALSE) -> 0.77787828 | BG32: =VLOOKUP(A32,'2022_PAPI_Indicators'!A27:BF207,57,FALSE) -> 0.67005694 | BH32: =VLOOKUP(A32,'2022_PAPI_Indicators'!A27:BG207,58,FALSE) -> 0.59205437 | BI32: =VLOOKUP(A32,'2022_PAPI_Indicators'!A27:BH207,59,FALSE) -> 0.34507743 | BJ32: =VLOOKUP(A32,'2022_PAPI_Indicators'!A27:BI207,60,FALSE) -> 0.63937545 | BK32: =VLOOKUP(A32,'2022_PAPI_Indicators'!A27:BJ207,61,FALSE) -> 0.49318296 | BL32: =VLOOKUP(A32,'2022_PAPI_Indicators'!A27:BK207,62,FALSE) -> 0.60527998 | BM32: =VLOOKUP(A32,'2022_PAPI_Indicators'!A27:BL207,63,FALSE) -> 0.66216373 | BN32: =VLOOKUP(A32,'2022_PAPI_Indicators'!A27:BM207,64,FALSE) -> 0.4715727
A33: Participated in Decision-making to Start a Project | B33: Tỷ lệ người trả lời cho biết đã tham gia vào việc quyết định xây mới/tu sửa công trình công cộng ở xã/phường (%) | C33: 0%-100% | D33: =VLOOKUP(A33,'2022_PAPI_Indicators'!A28:B208,2,) -> 0.6268748 | E33: =VLOOKUP(A33,'2022_PAPI_Indicators'!A28:C208,3,FALSE) -> 0.40552831 | F33: =VLOOKUP(A33,'2022_PAPI_Indicators'!A28:D208,4,FALSE) -> 0.46566916 | G33: =VLOOKUP(A33,'2022_PAPI_Indicators'!A28:E208,5,FALSE) -> 0.44892946 | H33: =VLOOKUP(A33,'2022_PAPI_Indicators'!A28:F208,6,FALSE) -> 0.62258971 | I33: =VLOOKUP(A33,'2022_PAPI_Indicators'!A28:G208,7,FALSE) -> 0.41431925 | J33: =VLOOKUP(A33,'2022_PAPI_Indicators'!A28:H208,8,FALSE) -> 0.35490295 | K33: =VLOOKUP(A33,'2022_PAPI_Indicators'!A28:I208,9,FALSE) -> 0.57713437 | L33: =VLOOKUP(A33,'2022_PAPI_Indicators'!A28:J208,10,FALSE) -> 0.5074482 | M33: =VLOOKUP(A33,'2022_PAPI_Indicators'!A28:K208,11,FALSE) -> 0.43012512 | N33: =VLOOKUP(A33,'2022_PAPI_Indicators'!A28:L208,12,FALSE) -> 0.58758098 | O33: =VLOOKUP(A33,'2022_PAPI_Indicators'!A28:M208,13,FALSE) -> 0.53696275 | P33: =VLOOKUP(A33,'2022_PAPI_Indicators'!A28:N208,14,FALSE) -> 0.57640529 | Q33: =VLOOKUP(A33,'2022_PAPI_Indicators'!A28:O208,15,FALSE) -> 0.24481647 | R33: =VLOOKUP(A33,'2022_PAPI_Indicators'!A28:P208,16,FALSE) -> 0 | S33: =VLOOKUP(A33,'2022_PAPI_Indicators'!A28:R208,17,FALSE) -> 0.53925544 | T33: =VLOOKUP(A33,'2022_PAPI_Indicators'!A28:S208,18,FALSE) -> 0.49413073 | U33: =VLOOKUP(A33,'2022_PAPI_Indicators'!A28:T208,19,FALSE) -> 0.43514967 | V33: =VLOOKUP(A33,'2022_PAPI_Indicators'!A28:U208,20,FALSE) -> 0.59832215 | W33: =VLOOKUP(A33,'2022_PAPI_Indicators'!A28:V208,21,FALSE) -> 0.46163473 | X33: =VLOOKUP(A33,'2022_PAPI_Indicators'!A28:W208,22,FALSE) -> 0.59892321 | Y33: =VLOOKUP(A33,'2022_PAPI_Indicators'!A28:X208,23,FALSE) -> 0.38930193 | Z33: =VLOOKUP(A33,'2022_PAPI_Indicators'!A28:Y208,24,FALSE) -> 0.49059412 | AA33: =VLOOKUP(A33,'2022_PAPI_Indicators'!A28:Z208,25,FALSE) -> 0.48102319 | AB33: =VLOOKUP(A33,'2022_PAPI_Indicators'!A28:AA208,26,FALSE) -> 0.31840983 | AC33: =VLOOKUP(A33,'2022_PAPI_Indicators'!A28:AB208,27,FALSE) -> 0.72024977 | AD33: =VLOOKUP(A33,'2022_PAPI_Indicators'!A28:AC208,28,FALSE) -> 0.71051282 | AE33: =VLOOKUP(A33,'2022_PAPI_Indicators'!A28:AD208,29,FALSE) -> 0.61208808 | AF33: =VLOOKUP(A33,'2022_PAPI_Indicators'!A28:AE208,30,FALSE) -> 0.47746259 | AG33: =VLOOKUP(A33,'2022_PAPI_Indicators'!A28:AF208,31,FALSE) -> 0.41897237 | AH33: =VLOOKUP(A33,'2022_PAPI_Indicators'!A28:AG208,32,FALSE) -> 0.55115092 | AI33: =VLOOKUP(A33,'2022_PAPI_Indicators'!A28:AH208,33,FALSE) -> 0.14545682 | AJ33: =VLOOKUP(A33,'2022_PAPI_Indicators'!A28:AI208,34,FALSE) -> 0.18519405 | AK33: =VLOOKUP(A33,'2022_PAPI_Indicators'!A28:AJ208,35,FALSE) -> 0.41763693 | AL33: =VLOOKUP(A33,'2022_PAPI_Indicators'!A28:AK208,36,FALSE) -> 0.49168086 | AM33: =VLOOKUP(A33,'2022_PAPI_Indicators'!A28:AL208,37,FALSE) -> 0.27990103 | AN33: =VLOOKUP(A33,'2022_PAPI_Indicators'!A28:AM208,38,FALSE) -> 0.31469133 | AO33: =VLOOKUP(A33,'2022_PAPI_Indicators'!A28:AN208,39,FALSE) -> 0.74455792 | AP33: =VLOOKUP(A33,'2022_PAPI_Indicators'!A28:AO208,40,FALSE) -> 0.69530696 | AQ33: =VLOOKUP(A33,'2022_PAPI_Indicators'!A28:AP208,41,FALSE) -> 0.60154629 | AR33: =VLOOKUP(A33,'2022_PAPI_Indicators'!A28:AQ208,42,FALSE) -> 0.49734199 | AS33: =VLOOKUP(A33,'2022_PAPI_Indicators'!A28:AR208,43,FALSE) -> 0.70852679 | AT33: =VLOOKUP(A33,'2022_PAPI_Indicators'!A28:AS208,44,FALSE) -> 0.48962596 | AU33: =VLOOKUP(A33,'2022_PAPI_Indicators'!A28:AT208,45,FALSE) -> 0.51121467 | AV33: =VLOOKUP(A33,'2022_PAPI_Indicators'!A28:AU208,46,FALSE) -> 0.36494103 | AW33: =VLOOKUP(A33,'2022_PAPI_Indicators'!A28:AV208,47,FALSE) -> 0.30784488 | AX33: =VLOOKUP(A33,'2022_PAPI_Indicators'!A28:AW208,48,FALSE) -> 0.547149 | AY33: =VLOOKUP(A33,'2022_PAPI_Indicators'!A28:AX208,49,FALSE) -> 0.50173163 | AZ33: =VLOOKUP(A33,'2022_PAPI_Indicators'!A28:AY208,50,FALSE) -> 0.24863692 | BA33: =VLOOKUP(A33,'2022_PAPI_Indicators'!A28:AZ208,51,FALSE) -> 0.62933725 | BB33: =VLOOKUP(A33,'2022_PAPI_Indicators'!A28:BA208,52,FALSE) -> 0.51442808 | BC33: =VLOOKUP(A33,'2022_PAPI_Indicators'!A28:BB208,53,FALSE) -> 0.56767309 | BD33: =VLOOKUP(A33,'2022_PAPI_Indicators'!A28:BC208,54,FALSE) -> 0.46379247 | BE33: =VLOOKUP(A33,'2022_PAPI_Indicators'!A28:BD208,55,FALSE) -> 0.33495834 | BF33: =VLOOKUP(A33,'2022_PAPI_Indicators'!A28:BE208,56,FALSE) -> 0.48407519 | BG33: =VLOOKUP(A33,'2022_PAPI_Indicators'!A28:BF208,57,FALSE) -> 0.44670463 | BH33: =VLOOKUP(A33,'2022_PAPI_Indicators'!A28:BG208,58,FALSE) -> 0.29421812 | BI33: =VLOOKUP(A33,'2022_PAPI_Indicators'!A28:BH208,59,FALSE) -> 0.38030967 | BJ33: =VLOOKUP(A33,'2022_PAPI_Indicators'!A28:BI208,60,FALSE) -> 0.50111169 | BK33: =VLOOKUP(A33,'2022_PAPI_Indicators'!A28:BJ208,61,FALSE) -> 0.36818373 | BL33: =VLOOKUP(A33,'2022_PAPI_Indicators'!A28:BK208,62,FALSE) -> 0.42267102 | BM33: =VLOOKUP(A33,'2022_PAPI_Indicators'!A28:BL208,63,FALSE) -> 0.35275057 | BN33: =VLOOKUP(A33,'2022_PAPI_Indicators'!A28:BM208,64,FALSE) -> 0.32255849
A34: Provided Input to Project Design | B34: Tỷ lệ người trả lời cho biết có tham gia đóng góp ý kiến trong quá trình thiết kế để xây mới/tu sửa công trình (%) | C34: 0%-100% | D34: =VLOOKUP(A34,'2022_PAPI_Indicators'!A29:B209,2,) -> 0.37770262 | E34: =VLOOKUP(A34,'2022_PAPI_Indicators'!A29:C209,3,FALSE) -> 0.26003006 | F34: =VLOOKUP(A34,'2022_PAPI_Indicators'!A29:D209,4,FALSE) -> 0.28059015 | G34: =VLOOKUP(A34,'2022_PAPI_Indicators'!A29:E209,5,FALSE) -> 0.28899994 | H34: =VLOOKUP(A34,'2022_PAPI_Indicators'!A29:F209,6,FALSE) -> 0.41230506 | I34: =VLOOKUP(A34,'2022_PAPI_Indicators'!A29:G209,7,FALSE) -> 0.33358848 | J34: =VLOOKUP(A34,'2022_PAPI_Indicators'!A29:H209,8,FALSE) -> 0.28271464 | K34: =VLOOKUP(A34,'2022_PAPI_Indicators'!A29:I209,9,FALSE) -> 0.33780229 | L34: =VLOOKUP(A34,'2022_PAPI_Indicators'!A29:J209,10,FALSE) -> 0.27984673 | M34: =VLOOKUP(A34,'2022_PAPI_Indicators'!A29:K209,11,FALSE) -> 0.33615127 | N34: =VLOOKUP(A34,'2022_PAPI_Indicators'!A29:L209,12,FALSE) -> 0.30279765 | O34: =VLOOKUP(A34,'2022_PAPI_Indicators'!A29:M209,13,FALSE) -> 0.32771015 | P34: =VLOOKUP(A34,'2022_PAPI_Indicators'!A29:N209,14,FALSE) -> 0.42503867 | Q34: =VLOOKUP(A34,'2022_PAPI_Indicators'!A29:O209,15,FALSE) -> 0.13317321 | R34: =VLOOKUP(A34,'2022_PAPI_Indicators'!A29:P209,16,FALSE) -> 0 | S34: =VLOOKUP(A34,'2022_PAPI_Indicators'!A29:R209,17,FALSE) -> 0.38018653 | T34: =VLOOKUP(A34,'2022_PAPI_Indicators'!A29:S209,18,FALSE) -> 0.28683224 | U34: =VLOOKUP(A34,'2022_PAPI_Indicators'!A29:T209,19,FALSE) -> 0.42380795 | V34: =VLOOKUP(A34,'2022_PAPI_Indicators'!A29:U209,20,FALSE) -> 0.53836685 | W34: =VLOOKUP(A34,'2022_PAPI_Indicators'!A29:V209,21,FALSE) -> 0.32957926 | X34: =VLOOKUP(A34,'2022_PAPI_Indicators'!A29:W209,22,FALSE) -> 0.42624354 | Y34: =VLOOKUP(A34,'2022_PAPI_Indicators'!A29:X209,23,FALSE) -> 0.24641462 | Z34: =VLOOKUP(A34,'2022_PAPI_Indicators'!A29:Y209,24,FALSE) -> 0.43077546 | AA34: =VLOOKUP(A34,'2022_PAPI_Indicators'!A29:Z209,25,FALSE) -> 0.26843998 | AB34: =VLOOKUP(A34,'2022_PAPI_Indicators'!A29:AA209,26,FALSE) -> 0.16248553 | AC34: =VLOOKUP(A34,'2022_PAPI_Indicators'!A29:AB209,27,FALSE) -> 0.52455819 | AD34: =VLOOKUP(A34,'2022_PAPI_Indicators'!A29:AC209,28,FALSE) -> 0.39133996 | AE34: =VLOOKUP(A34,'2022_PAPI_Indicators'!A29:AD209,29,FALSE) -> 0.44600761 | AF34: =VLOOKUP(A34,'2022_PAPI_Indicators'!A29:AE209,30,FALSE) -> 0.28849271 | AG34: =VLOOKUP(A34,'2022_PAPI_Indicators'!A29:AF209,31,FALSE) -> 0.32552597 | AH34: =VLOOKUP(A34,'2022_PAPI_Indicators'!A29:AG209,32,FALSE) -> 0.42161128 | AI34: =VLOOKUP(A34,'2022_PAPI_Indicators'!A29:AH209,33,FALSE) -> 0.16008238 | AJ34: =VLOOKUP(A34,'2022_PAPI_Indicators'!A29:AI209,34,FALSE) -> 0.11281084 | AK34: =VLOOKUP(A34,'2022_PAPI_Indicators'!A29:AJ209,35,FALSE) -> 0.32729289 | AL34: =VLOOKUP(A34,'2022_PAPI_Indicators'!A29:AK209,36,FALSE) -> 0.19417357 | AM34: =VLOOKUP(A34,'2022_PAPI_Indicators'!A29:AL209,37,FALSE) -> 0.17015605 | AN34: =VLOOKUP(A34,'2022_PAPI_Indicators'!A29:AM209,38,FALSE) -> 0.110185 | AO34: =VLOOKUP(A34,'2022_PAPI_Indicators'!A29:AN209,39,FALSE) -> 0.40340742 | AP34: =VLOOKUP(A34,'2022_PAPI_Indicators'!A29:AO209,40,FALSE) -> 0.64836919 | AQ34: =VLOOKUP(A34,'2022_PAPI_Indicators'!A29:AP209,41,FALSE) -> 0.34463933 | AR34: =VLOOKUP(A34,'2022_PAPI_Indicators'!A29:AQ209,42,FALSE) -> 0.37441841 | AS34: =VLOOKUP(A34,'2022_PAPI_Indicators'!A29:AR209,43,FALSE) -> 0.55109662 | AT34: =VLOOKUP(A34,'2022_PAPI_Indicators'!A29:AS209,44,FALSE) -> 0.35157102 | AU34: =VLOOKUP(A34,'2022_PAPI_Indicators'!A29:AT209,45,FALSE) -> 0.16016118 | AV34: =VLOOKUP(A34,'2022_PAPI_Indicators'!A29:AU209,46,FALSE) -> 0.26067218 | AW34: =VLOOKUP(A34,'2022_PAPI_Indicators'!A29:AV209,47,FALSE) -> 0.21624801 | AX34: =VLOOKUP(A34,'2022_PAPI_Indicators'!A29:AW209,48,FALSE) -> 0.53587711 | AY34: =VLOOKUP(A34,'2022_PAPI_Indicators'!A29:AX209,49,FALSE) -> 0.38525489 | AZ34: =VLOOKUP(A34,'2022_PAPI_Indicators'!A29:AY209,50,FALSE) -> 0.14299357 | BA34: =VLOOKUP(A34,'2022_PAPI_Indicators'!A29:AZ209,51,FALSE) -> 0.26488459 | BB34: =VLOOKUP(A34,'2022_PAPI_Indicators'!A29:BA209,52,FALSE) -> 0.4807229 | BC34: =VLOOKUP(A34,'2022_PAPI_Indicators'!A29:BB209,53,FALSE) -> 0.4021346 | BD34: =VLOOKUP(A34,'2022_PAPI_Indicators'!A29:BC209,54,FALSE) -> 0.31379861 | BE34: =VLOOKUP(A34,'2022_PAPI_Indicators'!A29:BD209,55,FALSE) -> 0.16991666 | BF34: =VLOOKUP(A34,'2022_PAPI_Indicators'!A29:BE209,56,FALSE) -> 0.298823 | BG34: =VLOOKUP(A34,'2022_PAPI_Indicators'!A29:BF209,57,FALSE) -> 0.29780307 | BH34: =VLOOKUP(A34,'2022_PAPI_Indicators'!A29:BG209,58,FALSE) -> 0.3194856 | BI34: =VLOOKUP(A34,'2022_PAPI_Indicators'!A29:BH209,59,FALSE) -> 0.17253871 | BJ34: =VLOOKUP(A34,'2022_PAPI_Indicators'!A29:BI209,60,FALSE) -> 0.35617077 | BK34: =VLOOKUP(A34,'2022_PAPI_Indicators'!A29:BJ209,61,FALSE) -> 0.13636622 | BL34: =VLOOKUP(A34,'2022_PAPI_Indicators'!A29:BK209,62,FALSE) -> 0.24006204 | BM34: =VLOOKUP(A34,'2022_PAPI_Indicators'!A29:BL209,63,FALSE) -> 0.38863078 | BN34: =VLOOKUP(A34,'2022_PAPI_Indicators'!A29:BM209,64,FALSE) -> 0.23039892
A35: Dimension 2: Transparency of Local Decision-making | B35: Chỉ số nội dung 2: Công khai, minh bạch trong hoạch định chính sách | C35: 1-10 điểm/points | D35: =VLOOKUP(A35,'2022_PAPI_Indicators'!A30:B210,2,) -> 5.7769713 | E35: =VLOOKUP(A35,'2022_PAPI_Indicators'!A30:C210,3,FALSE) -> 5.3071561 | F35: =VLOOKUP(A35,'2022_PAPI_Indicators'!A30:D210,4,FALSE) -> 4.8963985 | G35: =VLOOKUP(A35,'2022_PAPI_Indicators'!A30:E210,5,FALSE) -> 5.4914384 | H35: =VLOOKUP(A35,'2022_PAPI_Indicators'!A30:F210,6,FALSE) -> 5.5072861 | I35: =VLOOKUP(A35,'2022_PAPI_Indicators'!A30:G210,7,FALSE) -> 5.0399146 | J35: =VLOOKUP(A35,'2022_PAPI_Indicators'!A30:H210,8,FALSE) -> 5.1839385 | K35: =VLOOKUP(A35,'2022_PAPI_Indicators'!A30:I210,9,FALSE) -> 5.3419909 | L35: =VLOOKUP(A35,'2022_PAPI_Indicators'!A30:J210,10,FALSE) -> 5.0647259 | M35: =VLOOKUP(A35,'2022_PAPI_Indicators'!A30:K210,11,FALSE) -> 5.3534017 | N35: =VLOOKUP(A35,'2022_PAPI_Indicators'!A30:L210,12,FALSE) -> 5.1149569 | O35: =VLOOKUP(A35,'2022_PAPI_Indicators'!A30:M210,13,FALSE) -> 5.4902997 | P35: =VLOOKUP(A35,'2022_PAPI_Indicators'!A30:N210,14,FALSE) -> 5.3385687 | Q35: =VLOOKUP(A35,'2022_PAPI_Indicators'!A30:O210,15,FALSE) -> 6.3744926 | R35: =VLOOKUP(A35,'2022_PAPI_Indicators'!A30:P210,16,FALSE) -> 0 | S35: =VLOOKUP(A35,'2022_PAPI_Indicators'!A30:R210,17,FALSE) -> 5.7251115 | T35: =VLOOKUP(A35,'2022_PAPI_Indicators'!A30:S210,18,FALSE) -> 5.5963526 | U35: =VLOOKUP(A35,'2022_PAPI_Indicators'!A30:T210,19,FALSE) -> 0 | V35: =VLOOKUP(A35,'2022_PAPI_Indicators'!A30:U210,20,FALSE) -> 5.1472168 | W35: =VLOOKUP(A35,'2022_PAPI_Indicators'!A30:V210,21,FALSE) -> 5.7387886 | X35: =VLOOKUP(A35,'2022_PAPI_Indicators'!A30:W210,22,FALSE) -> 5.8100276 | Y35: =VLOOKUP(A35,'2022_PAPI_Indicators'!A30:X210,23,FALSE) -> 5.4620914 | Z35: =VLOOKUP(A35,'2022_PAPI_Indicators'!A30:Y210,24,FALSE) -> 5.2896872 | AA35: =VLOOKUP(A35,'2022_PAPI_Indicators'!A30:Z210,25,FALSE) -> 5.3519111 | AB35: =VLOOKUP(A35,'2022_PAPI_Indicators'!A30:AA210,26,FALSE) -> 5.5233769 | AC35: =VLOOKUP(A35,'2022_PAPI_Indicators'!A30:AB210,27,FALSE) -> 5.9741015 | AD35: =VLOOKUP(A35,'2022_PAPI_Indicators'!A30:AC210,28,FALSE) -> 5.4372683 | AE35: =VLOOKUP(A35,'2022_PAPI_Indicators'!A30:AD210,29,FALSE) -> 5.5813656 | AF35: =VLOOKUP(A35,'2022_PAPI_Indicators'!A30:AE210,30,FALSE) -> 5.7066135 | AG35: =VLOOKUP(A35,'2022_PAPI_Indicators'!A30:AF210,31,FALSE) -> 5.2588515 | AH35: =VLOOKUP(A35,'2022_PAPI_Indicators'!A30:AG210,32,FALSE) -> 5.8476505 | AI35: =VLOOKUP(A35,'2022_PAPI_Indicators'!A30:AH210,33,FALSE) -> 4.9122033 | AJ35: =VLOOKUP(A35,'2022_PAPI_Indicators'!A30:AI210,34,FALSE) -> 5.196342 | AK35: =VLOOKUP(A35,'2022_PAPI_Indicators'!A30:AJ210,35,FALSE) -> 5.3759542 | AL35: =VLOOKUP(A35,'2022_PAPI_Indicators'!A30:AK210,36,FALSE) -> 5.0405498 | AM35: =VLOOKUP(A35,'2022_PAPI_Indicators'!A30:AL210,37,FALSE) -> 4.9806123 | AN35: =VLOOKUP(A35,'2022_PAPI_Indicators'!A30:AM210,38,FALSE) -> 5.4958148 | AO35: =VLOOKUP(A35,'2022_PAPI_Indicators'!A30:AN210,39,FALSE) -> 5.8627214 | AP35: =VLOOKUP(A35,'2022_PAPI_Indicators'!A30:AO210,40,FALSE) -> 5.9622197 | AQ35: =VLOOKUP(A35,'2022_PAPI_Indicators'!A30:AP210,41,FALSE) -> 4.6563315 | AR35: =VLOOKUP(A35,'2022_PAPI_Indicators'!A30:AQ210,42,FALSE) -> 5.0327177 | AS35: =VLOOKUP(A35,'2022_PAPI_Indicators'!A30:AR210,43,FALSE) -> 4.8388987 | AT35: =VLOOKUP(A35,'2022_PAPI_Indicators'!A30:AS210,44,FALSE) -> 4.8707852 | AU35: =VLOOKUP(A35,'2022_PAPI_Indicators'!A30:AT210,45,FALSE) -> 4.934135 | AV35: =VLOOKUP(A35,'2022_PAPI_Indicators'!A30:AU210,46,FALSE) -> 5.1443405 | AW35: =VLOOKUP(A35,'2022_PAPI_Indicators'!A30:AV210,47,FALSE) -> 4.5563498 | AX35: =VLOOKUP(A35,'2022_PAPI_Indicators'!A30:AW210,48,FALSE) -> 6.2098551 | AY35: =VLOOKUP(A35,'2022_PAPI_Indicators'!A30:AX210,49,FALSE) -> 4.9619207 | AZ35: =VLOOKUP(A35,'2022_PAPI_Indicators'!A30:AY210,50,FALSE) -> 5.1835022 | BA35: =VLOOKUP(A35,'2022_PAPI_Indicators'!A30:AZ210,51,FALSE) -> 4.8661146 | BB35: =VLOOKUP(A35,'2022_PAPI_Indicators'!A30:BA210,52,FALSE) -> 4.7437758 | BC35: =VLOOKUP(A35,'2022_PAPI_Indicators'!A30:BB210,53,FALSE) -> 4.4102159 | BD35: =VLOOKUP(A35,'2022_PAPI_Indicators'!A30:BC210,54,FALSE) -> 4.7946405 | BE35: =VLOOKUP(A35,'2022_PAPI_Indicators'!A30:BD210,55,FALSE) -> 4.8381114 | BF35: =VLOOKUP(A35,'2022_PAPI_Indicators'!A30:BE210,56,FALSE) -> 5.1310143 | BG35: =VLOOKUP(A35,'2022_PAPI_Indicators'!A30:BF210,57,FALSE) -> 4.6019926 | BH35: =VLOOKUP(A35,'2022_PAPI_Indicators'!A30:BG210,58,FALSE) -> 4.5968947 | BI35: =VLOOKUP(A35,'2022_PAPI_Indicators'!A30:BH210,59,FALSE) -> 4.7571344 | BJ35: =VLOOKUP(A35,'2022_PAPI_Indicators'!A30:BI210,60,FALSE) -> 4.7551465 | BK35: =VLOOKUP(A35,'2022_PAPI_Indicators'!A30:BJ210,61,FALSE) -> 5.1033745 | BL35: =VLOOKUP(A35,'2022_PAPI_Indicators'!A30:BK210,62,FALSE) -> 5.0884023 | BM35: =VLOOKUP(A35,'2022_PAPI_Indicators'!A30:BL210,63,FALSE) -> 5.7437673 | BN35: =VLOOKUP(A35,'2022_PAPI_Indicators'!A30:BM210,64,FALSE) -> 5.1472244
A36: Access to Information | B36: 2.1: Tiếp cận thông tin | C36: 0.25-2.5 điểm/points | D36: =VLOOKUP(A36,'2022_PAPI_Indicators'!A31:B211,2,) -> 0.8727957 | E36: =VLOOKUP(A36,'2022_PAPI_Indicators'!A31:C211,3,FALSE) -> 0.92699921 | F36: =VLOOKUP(A36,'2022_PAPI_Indicators'!A31:D211,4,FALSE) -> 0.7303142 | G36: =VLOOKUP(A36,'2022_PAPI_Indicators'!A31:E211,5,FALSE) -> 0.93221569 | H36: =VLOOKUP(A36,'2022_PAPI_Indicators'!A31:F211,6,FALSE) -> 0.81806922 | I36: =VLOOKUP(A36,'2022_PAPI_Indicators'!A31:G211,7,FALSE) -> 0.80895936 | J36: =VLOOKUP(A36,'2022_PAPI_Indicators'!A31:H211,8,FALSE) -> 0.78549027 | K36: =VLOOKUP(A36,'2022_PAPI_Indicators'!A31:I211,9,FALSE) -> 0.88567579 | L36: =VLOOKUP(A36,'2022_PAPI_Indicators'!A31:J211,10,FALSE) -> 0.77180469 | M36: =VLOOKUP(A36,'2022_PAPI_Indicators'!A31:K211,11,FALSE) -> 0.79502147 | N36: =VLOOKUP(A36,'2022_PAPI_Indicators'!A31:L211,12,FALSE) -> 0.80157667 | O36: =VLOOKUP(A36,'2022_PAPI_Indicators'!A31:M211,13,FALSE) -> 0.89948022 | P36: =VLOOKUP(A36,'2022_PAPI_Indicators'!A31:N211,14,FALSE) -> 0.83443063 | Q36: =VLOOKUP(A36,'2022_PAPI_Indicators'!A31:O211,15,FALSE) -> 0.9456175 | R36: =VLOOKUP(A36,'2022_PAPI_Indicators'!A31:P211,16,FALSE) -> 0 | S36: =VLOOKUP(A36,'2022_PAPI_Indicators'!A31:R211,17,FALSE) -> 0.80643404 | T36: =VLOOKUP(A36,'2022_PAPI_Indicators'!A31:S211,18,FALSE) -> 0.85454607 | U36: =VLOOKUP(A36,'2022_PAPI_Indicators'!A31:T211,19,FALSE) -> 0 | V36: =VLOOKUP(A36,'2022_PAPI_Indicators'!A31:U211,20,FALSE) -> 0.75779164 | W36: =VLOOKUP(A36,'2022_PAPI_Indicators'!A31:V211,21,FALSE) -> 0.74202716 | X36: =VLOOKUP(A36,'2022_PAPI_Indicators'!A31:W211,22,FALSE) -> 0.89758492 | Y36: =VLOOKUP(A36,'2022_PAPI_Indicators'!A31:X211,23,FALSE) -> 0.76763839 | Z36: =VLOOKUP(A36,'2022_PAPI_Indicators'!A31:Y211,24,FALSE) -> 0.79289174 | AA36: =VLOOKUP(A36,'2022_PAPI_Indicators'!A31:Z211,25,FALSE) -> 0.7740137 | AB36: =VLOOKUP(A36,'2022_PAPI_Indicators'!A31:AA211,26,FALSE) -> 0.77235258 | AC36: =VLOOKUP(A36,'2022_PAPI_Indicators'!A31:AB211,27,FALSE) -> 0.84339952 | AD36: =VLOOKUP(A36,'2022_PAPI_Indicators'!A31:AC211,28,FALSE) -> 0.75194424 | AE36: =VLOOKUP(A36,'2022_PAPI_Indicators'!A31:AD211,29,FALSE) -> 0.81647879 | AF36: =VLOOKUP(A36,'2022_PAPI_Indicators'!A31:AE211,30,FALSE) -> 0.83684385 | AG36: =VLOOKUP(A36,'2022_PAPI_Indicators'!A31:AF211,31,FALSE) -> 0.8095172 | AH36: =VLOOKUP(A36,'2022_PAPI_Indicators'!A31:AG211,32,FALSE) -> 0.97045398 | AI36: =VLOOKUP(A36,'2022_PAPI_Indicators'!A31:AH211,33,FALSE) -> 0.74681395 | AJ36: =VLOOKUP(A36,'2022_PAPI_Indicators'!A31:AI211,34,FALSE) -> 0.73497999 | AK36: =VLOOKUP(A36,'2022_PAPI_Indicators'!A31:AJ211,35,FALSE) -> 0.92795581 | AL36: =VLOOKUP(A36,'2022_PAPI_Indicators'!A31:AK211,36,FALSE) -> 0.74205607 | AM36: =VLOOKUP(A36,'2022_PAPI_Indicators'!A31:AL211,37,FALSE) -> 0.75996941 | AN36: =VLOOKUP(A36,'2022_PAPI_Indicators'!A31:AM211,38,FALSE) -> 0.92139661 | AO36: =VLOOKUP(A36,'2022_PAPI_Indicators'!A31:AN211,39,FALSE) -> 0.93892568 | AP36: =VLOOKUP(A36,'2022_PAPI_Indicators'!A31:AO211,40,FALSE) -> 0.84043932 | AQ36: =VLOOKUP(A36,'2022_PAPI_Indicators'!A31:AP211,41,FALSE) -> 0.77401328 | AR36: =VLOOKUP(A36,'2022_PAPI_Indicators'!A31:AQ211,42,FALSE) -> 0.81031471 | AS36: =VLOOKUP(A36,'2022_PAPI_Indicators'!A31:AR211,43,FALSE) -> 0.73959118 | AT36: =VLOOKUP(A36,'2022_PAPI_Indicators'!A31:AS211,44,FALSE) -> 0.81485021 | AU36: =VLOOKUP(A36,'2022_PAPI_Indicators'!A31:AT211,45,FALSE) -> 0.81678826 | AV36: =VLOOKUP(A36,'2022_PAPI_Indicators'!A31:AU211,46,FALSE) -> 0.80851066 | AW36: =VLOOKUP(A36,'2022_PAPI_Indicators'!A31:AV211,47,FALSE) -> 0.74069053 | AX36: =VLOOKUP(A36,'2022_PAPI_Indicators'!A31:AW211,48,FALSE) -> 0.86316592 | AY36: =VLOOKUP(A36,'2022_PAPI_Indicators'!A31:AX211,49,FALSE) -> 0.83008653 | AZ36: =VLOOKUP(A36,'2022_PAPI_Indicators'!A31:AY211,50,FALSE) -> 0.78049427 | BA36: =VLOOKUP(A36,'2022_PAPI_Indicators'!A31:AZ211,51,FALSE) -> 0.75671881 | BB36: =VLOOKUP(A36,'2022_PAPI_Indicators'!A31:BA211,52,FALSE) -> 0.71475905 | BC36: =VLOOKUP(A36,'2022_PAPI_Indicators'!A31:BB211,53,FALSE) -> 0.71881592 | BD36: =VLOOKUP(A36,'2022_PAPI_Indicators'!A31:BC211,54,FALSE) -> 0.71139133 | BE36: =VLOOKUP(A36,'2022_PAPI_Indicators'!A31:BD211,55,FALSE) -> 0.73499596 | BF36: =VLOOKUP(A36,'2022_PAPI_Indicators'!A31:BE211,56,FALSE) -> 0.80467385 | BG36: =VLOOKUP(A36,'2022_PAPI_Indicators'!A31:BF211,57,FALSE) -> 0.73715341 | BH36: =VLOOKUP(A36,'2022_PAPI_Indicators'!A31:BG211,58,FALSE) -> 0.74938226 | BI36: =VLOOKUP(A36,'2022_PAPI_Indicators'!A31:BH211,59,FALSE) -> 0.69352293 | BJ36: =VLOOKUP(A36,'2022_PAPI_Indicators'!A31:BI211,60,FALSE) -> 0.71482581 | BK36: =VLOOKUP(A36,'2022_PAPI_Indicators'!A31:BJ211,61,FALSE) -> 0.81039137 | BL36: =VLOOKUP(A36,'2022_PAPI_Indicators'!A31:BK211,62,FALSE) -> 0.74846238 | BM36: =VLOOKUP(A36,'2022_PAPI_Indicators'!A31:BL211,63,FALSE) -> 0.87070471 | BN36: =VLOOKUP(A36,'2022_PAPI_Indicators'!A31:BM211,64,FALSE) -> 0.81820679
A37: Searched for Information about State Policy and Legislation | B37: Tỷ lệ người trả lời cho biết đã tìm kiếm thông tin về chính sách, pháp luật từ chính quyền địa phương (%) | C37: 0%-100% | D37: =VLOOKUP(A37,'2022_PAPI_Indicators'!A32:B212,2,) -> 0.18685693 | E37: =VLOOKUP(A37,'2022_PAPI_Indicators'!A32:C212,3,FALSE) -> 0.21266308 | F37: =VLOOKUP(A37,'2022_PAPI_Indicators'!A32:D212,4,FALSE) -> 0.099980935 | G37: =VLOOKUP(A37,'2022_PAPI_Indicators'!A32:E212,5,FALSE) -> 0.22988372 | H37: =VLOOKUP(A37,'2022_PAPI_Indicators'!A32:F212,6,FALSE) -> 0.14356427 | I37: =VLOOKUP(A37,'2022_PAPI_Indicators'!A32:G212,7,FALSE) -> 0.14699303 | J37: =VLOOKUP(A37,'2022_PAPI_Indicators'!A32:H212,8,FALSE) -> 0.11560866 | K37: =VLOOKUP(A37,'2022_PAPI_Indicators'!A32:I212,9,FALSE) -> 0.196935 | L37: =VLOOKUP(A37,'2022_PAPI_Indicators'!A32:J212,10,FALSE) -> 0.1230789 | M37: =VLOOKUP(A37,'2022_PAPI_Indicators'!A32:K212,11,FALSE) -> 0.14568156 | N37: =VLOOKUP(A37,'2022_PAPI_Indicators'!A32:L212,12,FALSE) -> 0.12812024 | O37: =VLOOKUP(A37,'2022_PAPI_Indicators'!A32:M212,13,FALSE) -> 0.20133968 | P37: =VLOOKUP(A37,'2022_PAPI_Indicators'!A32:N212,14,FALSE) -> 0.15120083 | Q37: =VLOOKUP(A37,'2022_PAPI_Indicators'!A32:O212,15,FALSE) -> 0.23693381 | R37: =VLOOKUP(A37,'2022_PAPI_Indicators'!A32:P212,16,FALSE) -> 0 | S37: =VLOOKUP(A37,'2022_PAPI_Indicators'!A32:R212,17,FALSE) -> 0.12399163 | T37: =VLOOKUP(A37,'2022_PAPI_Indicators'!A32:S212,18,FALSE) -> 0.1706982 | U37: =VLOOKUP(A37,'2022_PAPI_Indicators'!A32:T212,19,FALSE) -> 0 | V37: =VLOOKUP(A37,'2022_PAPI_Indicators'!A32:U212,20,FALSE) -> 0.094303794 | W37: =VLOOKUP(A37,'2022_PAPI_Indicators'!A32:V212,21,FALSE) -> 0.09076786 | X37: =VLOOKUP(A37,'2022_PAPI_Indicators'!A32:W212,22,FALSE) -> 0.19587079 | Y37: =VLOOKUP(A37,'2022_PAPI_Indicators'!A32:X212,23,FALSE) -> 0.1050548 | Z37: =VLOOKUP(A37,'2022_PAPI_Indicators'!A32:Y212,24,FALSE) -> 0.11647344 | AA37: =VLOOKUP(A37,'2022_PAPI_Indicators'!A32:Z212,25,FALSE) -> 0.13055287 | AB37: =VLOOKUP(A37,'2022_PAPI_Indicators'!A32:AA212,26,FALSE) -> 0.11304022 | AC37: =VLOOKUP(A37,'2022_PAPI_Indicators'!A32:AB212,27,FALSE) -> 0.16111396 | AD37: =VLOOKUP(A37,'2022_PAPI_Indicators'!A32:AC212,28,FALSE) -> 0.12607318 | AE37: =VLOOKUP(A37,'2022_PAPI_Indicators'!A32:AD212,29,FALSE) -> 0.17161968 | AF37: =VLOOKUP(A37,'2022_PAPI_Indicators'!A32:AE212,30,FALSE) -> 0.14943612 | AG37: =VLOOKUP(A37,'2022_PAPI_Indicators'!A32:AF212,31,FALSE) -> 0.14446042 | AH37: =VLOOKUP(A37,'2022_PAPI_Indicators'!A32:AG212,32,FALSE) -> 0.24640331 | AI37: =VLOOKUP(A37,'2022_PAPI_Indicators'!A32:AH212,33,FALSE) -> 0.10541163 | AJ37: =VLOOKUP(A37,'2022_PAPI_Indicators'!A32:AI212,34,FALSE) -> 0.091046609 | AK37: =VLOOKUP(A37,'2022_PAPI_Indicators'!A32:AJ212,35,FALSE) -> 0.22053804 | AL37: =VLOOKUP(A37,'2022_PAPI_Indicators'!A32:AK212,36,FALSE) -> 0.088396497 | AM37: =VLOOKUP(A37,'2022_PAPI_Indicators'!A32:AL212,37,FALSE) -> 0.10845756 | AN37: =VLOOKUP(A37,'2022_PAPI_Indicators'!A32:AM212,38,FALSE) -> 0.20481172 | AO37: =VLOOKUP(A37,'2022_PAPI_Indicators'!A32:AN212,39,FALSE) -> 0.2164191 | AP37: =VLOOKUP(A37,'2022_PAPI_Indicators'!A32:AO212,40,FALSE) -> 0.15806229 | AQ37: =VLOOKUP(A37,'2022_PAPI_Indicators'!A32:AP212,41,FALSE) -> 0.1101682 | AR37: =VLOOKUP(A37,'2022_PAPI_Indicators'!A32:AQ212,42,FALSE) -> 0.15050685 | AS37: =VLOOKUP(A37,'2022_PAPI_Indicators'!A32:AR212,43,FALSE) -> 0.081703536 | AT37: =VLOOKUP(A37,'2022_PAPI_Indicators'!A32:AS212,44,FALSE) -> 0.14734019 | AU37: =VLOOKUP(A37,'2022_PAPI_Indicators'!A32:AT212,45,FALSE) -> 0.15669702 | AV37: =VLOOKUP(A37,'2022_PAPI_Indicators'!A32:AU212,46,FALSE) -> 0.14214103 | AW37: =VLOOKUP(A37,'2022_PAPI_Indicators'!A32:AV212,47,FALSE) -> 0.11481352 | AX37: =VLOOKUP(A37,'2022_PAPI_Indicators'!A32:AW212,48,FALSE) -> 0.17667399 | AY37: =VLOOKUP(A37,'2022_PAPI_Indicators'!A32:AX212,49,FALSE) -> 0.15430444 | AZ37: =VLOOKUP(A37,'2022_PAPI_Indicators'!A32:AY212,50,FALSE) -> 0.13885729 | BA37: =VLOOKUP(A37,'2022_PAPI_Indicators'!A32:AZ212,51,FALSE) -> 0.10191295 | BB37: =VLOOKUP(A37,'2022_PAPI_Indicators'!A32:BA212,52,FALSE) -> 0.07086549 | BC37: =VLOOKUP(A37,'2022_PAPI_Indicators'!A32:BB212,53,FALSE) -> 0.06586194 | BD37: =VLOOKUP(A37,'2022_PAPI_Indicators'!A32:BC212,54,FALSE) -> 0.063934289 | BE37: =VLOOKUP(A37,'2022_PAPI_Indicators'!A32:BD212,55,FALSE) -> 0.083275594 | BF37: =VLOOKUP(A37,'2022_PAPI_Indicators'!A32:BE212,56,FALSE) -> 0.14501378 | BG37: =VLOOKUP(A37,'2022_PAPI_Indicators'!A32:BF212,57,FALSE) -> 0.082369231 | BH37: =VLOOKUP(A37,'2022_PAPI_Indicators'!A32:BG212,58,FALSE) -> 0.091090105 | BI37: =VLOOKUP(A37,'2022_PAPI_Indicators'!A32:BH212,59,FALSE) -> 0.070023552 | BJ37: =VLOOKUP(A37,'2022_PAPI_Indicators'!A32:BI212,60,FALSE) -> 0.082003623 | BK37: =VLOOKUP(A37,'2022_PAPI_Indicators'!A32:BJ212,61,FALSE) -> 0.12540288 | BL37: =VLOOKUP(A37,'2022_PAPI_Indicators'!A32:BK212,62,FALSE) -> 0.08890076 | BM37: =VLOOKUP(A37,'2022_PAPI_Indicators'!A32:BL212,63,FALSE) -> 0.17045824 | BN37: =VLOOKUP(A37,'2022_PAPI_Indicators'!A32:BM212,64,FALSE) -> 0.15146697
A38: Received Information Needed about State Policy and Legislation | B38: Tỷ lệ người trả lời cho biết đã nhận được thông tin chính sách, pháp luật từ chính quyền địa phương (%) | C38: 0%-100% | D38: =VLOOKUP(A38,'2022_PAPI_Indicators'!A33:B213,2,) -> 0.17232534 | E38: =VLOOKUP(A38,'2022_PAPI_Indicators'!A33:C213,3,FALSE) -> 0.18845092 | F38: =VLOOKUP(A38,'2022_PAPI_Indicators'!A33:D213,4,FALSE) -> 0.07433036 | G38: =VLOOKUP(A38,'2022_PAPI_Indicators'!A33:E213,5,FALSE) -> 0.19396999 | H38: =VLOOKUP(A38,'2022_PAPI_Indicators'!A33:F213,6,FALSE) -> 0.12101202 | I38: =VLOOKUP(A38,'2022_PAPI_Indicators'!A33:G213,7,FALSE) -> 0.13334857 | J38: =VLOOKUP(A38,'2022_PAPI_Indicators'!A33:H213,8,FALSE) -> 0.10739484 | K38: =VLOOKUP(A38,'2022_PAPI_Indicators'!A33:I213,9,FALSE) -> 0.16315666 | L38: =VLOOKUP(A38,'2022_PAPI_Indicators'!A33:J213,10,FALSE) -> 0.11353364 | M38: =VLOOKUP(A38,'2022_PAPI_Indicators'!A33:K213,11,FALSE) -> 0.09290953 | N38: =VLOOKUP(A38,'2022_PAPI_Indicators'!A33:L213,12,FALSE) -> 0.11089572 | O38: =VLOOKUP(A38,'2022_PAPI_Indicators'!A33:M213,13,FALSE) -> 0.18621024 | P38: =VLOOKUP(A38,'2022_PAPI_Indicators'!A33:N213,14,FALSE) -> 0.14173034 | Q38: =VLOOKUP(A38,'2022_PAPI_Indicators'!A33:O213,15,FALSE) -> 0.20941758 | R38: =VLOOKUP(A38,'2022_PAPI_Indicators'!A33:P213,16,FALSE) -> 0 | S38: =VLOOKUP(A38,'2022_PAPI_Indicators'!A33:R213,17,FALSE) -> 0.11432346 | T38: =VLOOKUP(A38,'2022_PAPI_Indicators'!A33:S213,18,FALSE) -> 0.14243025 | U38: =VLOOKUP(A38,'2022_PAPI_Indicators'!A33:T213,19,FALSE) -> 0 | V38: =VLOOKUP(A38,'2022_PAPI_Indicators'!A33:U213,20,FALSE) -> 0.085234426 | W38: =VLOOKUP(A38,'2022_PAPI_Indicators'!A33:V213,21,FALSE) -> 0.069065347 | X38: =VLOOKUP(A38,'2022_PAPI_Indicators'!A33:W213,22,FALSE) -> 0.17129181 | Y38: =VLOOKUP(A38,'2022_PAPI_Indicators'!A33:X213,23,FALSE) -> 0.088753656 | Z38: =VLOOKUP(A38,'2022_PAPI_Indicators'!A33:Y213,24,FALSE) -> 0.10815391 | AA38: =VLOOKUP(A38,'2022_PAPI_Indicators'!A33:Z213,25,FALSE) -> 0.092045657 | AB38: =VLOOKUP(A38,'2022_PAPI_Indicators'!A33:AA213,26,FALSE) -> 0.0767105 | AC38: =VLOOKUP(A38,'2022_PAPI_Indicators'!A33:AB213,27,FALSE) -> 0.14892372 | AD38: =VLOOKUP(A38,'2022_PAPI_Indicators'!A33:AC213,28,FALSE) -> 0.10434368 | AE38: =VLOOKUP(A38,'2022_PAPI_Indicators'!A33:AD213,29,FALSE) -> 0.1179179 | AF38: =VLOOKUP(A38,'2022_PAPI_Indicators'!A33:AE213,30,FALSE) -> 0.11783369 | AG38: =VLOOKUP(A38,'2022_PAPI_Indicators'!A33:AF213,31,FALSE) -> 0.11065347 | AH38: =VLOOKUP(A38,'2022_PAPI_Indicators'!A33:AG213,32,FALSE) -> 0.22787856 | AI38: =VLOOKUP(A38,'2022_PAPI_Indicators'!A33:AH213,33,FALSE) -> 0.079419449 | AJ38: =VLOOKUP(A38,'2022_PAPI_Indicators'!A33:AI213,34,FALSE) -> 0.069526397 | AK38: =VLOOKUP(A38,'2022_PAPI_Indicators'!A33:AJ213,35,FALSE) -> 0.18428476 | AL38: =VLOOKUP(A38,'2022_PAPI_Indicators'!A33:AK213,36,FALSE) -> 0.088396497 | AM38: =VLOOKUP(A38,'2022_PAPI_Indicators'!A33:AL213,37,FALSE) -> 0.10141118 | AN38: =VLOOKUP(A38,'2022_PAPI_Indicators'!A33:AM213,38,FALSE) -> 0.17651805 | AO38: =VLOOKUP(A38,'2022_PAPI_Indicators'!A33:AN213,39,FALSE) -> 0.19782279 | AP38: =VLOOKUP(A38,'2022_PAPI_Indicators'!A33:AO213,40,FALSE) -> 0.1370026 | AQ38: =VLOOKUP(A38,'2022_PAPI_Indicators'!A33:AP213,41,FALSE) -> 0.085423037 | AR38: =VLOOKUP(A38,'2022_PAPI_Indicators'!A33:AQ213,42,FALSE) -> 0.12069264 | AS38: =VLOOKUP(A38,'2022_PAPI_Indicators'!A33:AR213,43,FALSE) -> 0.062108271 | AT38: =VLOOKUP(A38,'2022_PAPI_Indicators'!A33:AS213,44,FALSE) -> 0.13083805 | AU38: =VLOOKUP(A38,'2022_PAPI_Indicators'!A33:AT213,45,FALSE) -> 0.11142133 | AV38: =VLOOKUP(A38,'2022_PAPI_Indicators'!A33:AU213,46,FALSE) -> 0.11770994 | AW38: =VLOOKUP(A38,'2022_PAPI_Indicators'!A33:AV213,47,FALSE) -> 0.10025752 | AX38: =VLOOKUP(A38,'2022_PAPI_Indicators'!A33:AW213,48,FALSE) -> 0.16907838 | AY38: =VLOOKUP(A38,'2022_PAPI_Indicators'!A33:AX213,49,FALSE) -> 0.12747775 | AZ38: =VLOOKUP(A38,'2022_PAPI_Indicators'!A33:AY213,50,FALSE) -> 0.095843822 | BA38: =VLOOKUP(A38,'2022_PAPI_Indicators'!A33:AZ213,51,FALSE) -> 0.092130899 | BB38: =VLOOKUP(A38,'2022_PAPI_Indicators'!A33:BA213,52,FALSE) -> 0.04938269 | BC38: =VLOOKUP(A38,'2022_PAPI_Indicators'!A33:BB213,53,FALSE) -> 0.044357192 | BD38: =VLOOKUP(A38,'2022_PAPI_Indicators'!A33:BC213,54,FALSE) -> 0.047555048 | BE38: =VLOOKUP(A38,'2022_PAPI_Indicators'!A33:BD213,55,FALSE) -> 0.067549504 | BF38: =VLOOKUP(A38,'2022_PAPI_Indicators'!A33:BE213,56,FALSE) -> 0.12331528 | BG38: =VLOOKUP(A38,'2022_PAPI_Indicators'!A33:BF213,57,FALSE) -> 0.066744231 | BH38: =VLOOKUP(A38,'2022_PAPI_Indicators'!A33:BG213,58,FALSE) -> 0.076238103 | BI38: =VLOOKUP(A38,'2022_PAPI_Indicators'!A33:BH213,59,FALSE) -> 0.042194903 | BJ38: =VLOOKUP(A38,'2022_PAPI_Indicators'!A33:BI213,60,FALSE) -> 0.068795539 | BK38: =VLOOKUP(A38,'2022_PAPI_Indicators'!A33:BJ213,61,FALSE) -> 0.11816827 | BL38: =VLOOKUP(A38,'2022_PAPI_Indicators'!A33:BK213,62,FALSE) -> 0.066269629 | BM38: =VLOOKUP(A38,'2022_PAPI_Indicators'!A33:BL213,63,FALSE) -> 0.14816999 | BN38: =VLOOKUP(A38,'2022_PAPI_Indicators'!A33:BM213,64,FALSE) -> 0.13757472
A39: Information Received Useful | B39: Tỷ lệ người trả lời cho biết thông tin chính sách, pháp luật nhận được là hữu ích (%) | C39: 0%-100% | D39: =VLOOKUP(A39,'2022_PAPI_Indicators'!A34:B214,2,) -> 0.16953154 | E39: =VLOOKUP(A39,'2022_PAPI_Indicators'!A34:C214,3,FALSE) -> 0.21108915 | F39: =VLOOKUP(A39,'2022_PAPI_Indicators'!A34:D214,4,FALSE) -> 0.07052321 | G39: =VLOOKUP(A39,'2022_PAPI_Indicators'!A34:E214,5,FALSE) -> 0.22270097 | H39: =VLOOKUP(A39,'2022_PAPI_Indicators'!A34:F214,6,FALSE) -> 0.12211218 | I39: =VLOOKUP(A39,'2022_PAPI_Indicators'!A34:G214,7,FALSE) -> 0.1401708 | J39: =VLOOKUP(A39,'2022_PAPI_Indicators'!A34:H214,8,FALSE) -> 0.09837839 | K39: =VLOOKUP(A39,'2022_PAPI_Indicators'!A34:I214,9,FALSE) -> 0.18601471 | L39: =VLOOKUP(A39,'2022_PAPI_Indicators'!A34:J214,10,FALSE) -> 0.11353364 | M39: =VLOOKUP(A39,'2022_PAPI_Indicators'!A34:K214,11,FALSE) -> 0.13741936 | N39: =VLOOKUP(A39,'2022_PAPI_Indicators'!A34:L214,12,FALSE) -> 0.11902419 | O39: =VLOOKUP(A39,'2022_PAPI_Indicators'!A34:M214,13,FALSE) -> 0.19521666 | P39: =VLOOKUP(A39,'2022_PAPI_Indicators'!A34:N214,14,FALSE) -> 0.143941 | Q39: =VLOOKUP(A39,'2022_PAPI_Indicators'!A34:O214,15,FALSE) -> 0.22234471 | R39: =VLOOKUP(A39,'2022_PAPI_Indicators'!A34:P214,16,FALSE) -> 0 | S39: =VLOOKUP(A39,'2022_PAPI_Indicators'!A34:R214,17,FALSE) -> 0.12275451 | T39: =VLOOKUP(A39,'2022_PAPI_Indicators'!A34:S214,18,FALSE) -> 0.15656422 | U39: =VLOOKUP(A39,'2022_PAPI_Indicators'!A34:T214,19,FALSE) -> 0 | V39: =VLOOKUP(A39,'2022_PAPI_Indicators'!A34:U214,20,FALSE) -> 0.094303794 | W39: =VLOOKUP(A39,'2022_PAPI_Indicators'!A34:V214,21,FALSE) -> 0.076299518 | X39: =VLOOKUP(A39,'2022_PAPI_Indicators'!A34:W214,22,FALSE) -> 0.1794848 | Y39: =VLOOKUP(A39,'2022_PAPI_Indicators'!A34:X214,23,FALSE) -> 0.089656301 | Z39: =VLOOKUP(A39,'2022_PAPI_Indicators'!A34:Y214,24,FALSE) -> 0.10969736 | AA39: =VLOOKUP(A39,'2022_PAPI_Indicators'!A34:Z214,25,FALSE) -> 0.10544951 | AB39: =VLOOKUP(A39,'2022_PAPI_Indicators'!A34:AA214,26,FALSE) -> 0.10468116 | AC39: =VLOOKUP(A39,'2022_PAPI_Indicators'!A34:AB214,27,FALSE) -> 0.15188992 | AD39: =VLOOKUP(A39,'2022_PAPI_Indicators'!A34:AC214,28,FALSE) -> 0.10501546 | AE39: =VLOOKUP(A39,'2022_PAPI_Indicators'!A34:AD214,29,FALSE) -> 0.12671611 | AF39: =VLOOKUP(A39,'2022_PAPI_Indicators'!A34:AE214,30,FALSE) -> 0.14821097 | AG39: =VLOOKUP(A39,'2022_PAPI_Indicators'!A34:AF214,31,FALSE) -> 0.12627847 | AH39: =VLOOKUP(A39,'2022_PAPI_Indicators'!A34:AG214,32,FALSE) -> 0.22032431 | AI39: =VLOOKUP(A39,'2022_PAPI_Indicators'!A34:AH214,33,FALSE) -> 0.085990287 | AJ39: =VLOOKUP(A39,'2022_PAPI_Indicators'!A34:AI214,34,FALSE) -> 0.069526397 | AK39: =VLOOKUP(A39,'2022_PAPI_Indicators'!A34:AJ214,35,FALSE) -> 0.20392057 | AL39: =VLOOKUP(A39,'2022_PAPI_Indicators'!A34:AK214,36,FALSE) -> 0.088396497 | AM39: =VLOOKUP(A39,'2022_PAPI_Indicators'!A34:AL214,37,FALSE) -> 0.099878944 | AN39: =VLOOKUP(A39,'2022_PAPI_Indicators'!A34:AM214,38,FALSE) -> 0.19833682 | AO39: =VLOOKUP(A39,'2022_PAPI_Indicators'!A34:AN214,39,FALSE) -> 0.21022034 | AP39: =VLOOKUP(A39,'2022_PAPI_Indicators'!A34:AO214,40,FALSE) -> 0.14243729 | AQ39: =VLOOKUP(A39,'2022_PAPI_Indicators'!A34:AP214,41,FALSE) -> 0.097795621 | AR39: =VLOOKUP(A39,'2022_PAPI_Indicators'!A34:AQ214,42,FALSE) -> 0.11503382 | AS39: =VLOOKUP(A39,'2022_PAPI_Indicators'!A34:AR214,43,FALSE) -> 0.081703536 | AT39: =VLOOKUP(A39,'2022_PAPI_Indicators'!A34:AS214,44,FALSE) -> 0.14172991 | AU39: =VLOOKUP(A39,'2022_PAPI_Indicators'!A34:AT214,45,FALSE) -> 0.14987333 | AV39: =VLOOKUP(A39,'2022_PAPI_Indicators'!A34:AU214,46,FALSE) -> 0.13310823 | AW39: =VLOOKUP(A39,'2022_PAPI_Indicators'!A34:AV214,47,FALSE) -> 0.10025752 | AX39: =VLOOKUP(A39,'2022_PAPI_Indicators'!A34:AW214,48,FALSE) -> 0.17031312 | AY39: =VLOOKUP(A39,'2022_PAPI_Indicators'!A34:AX214,49,FALSE) -> 0.13657373 | AZ39: =VLOOKUP(A39,'2022_PAPI_Indicators'!A34:AY214,50,FALSE) -> 0.10409222 | BA39: =VLOOKUP(A39,'2022_PAPI_Indicators'!A34:AZ214,51,FALSE) -> 0.086279154 | BB39: =VLOOKUP(A39,'2022_PAPI_Indicators'!A34:BA214,52,FALSE) -> 0.063152172 | BC39: =VLOOKUP(A39,'2022_PAPI_Indicators'!A34:BB214,53,FALSE) -> 0.06586194 | BD39: =VLOOKUP(A39,'2022_PAPI_Indicators'!A34:BC214,54,FALSE) -> 0.063142955 | BE39: =VLOOKUP(A39,'2022_PAPI_Indicators'!A34:BD214,55,FALSE) -> 0.067549504 | BF39: =VLOOKUP(A39,'2022_PAPI_Indicators'!A34:BE214,56,FALSE) -> 0.1370668 | BG39: =VLOOKUP(A39,'2022_PAPI_Indicators'!A34:BF214,57,FALSE) -> 0.082369231 | BH39: =VLOOKUP(A39,'2022_PAPI_Indicators'!A34:BG214,58,FALSE) -> 0.082178906 | BI39: =VLOOKUP(A39,'2022_PAPI_Indicators'!A34:BH214,59,FALSE) -> 0.063066393 | BJ39: =VLOOKUP(A39,'2022_PAPI_Indicators'!A34:BI214,60,FALSE) -> 0.077512808 | BK39: =VLOOKUP(A39,'2022_PAPI_Indicators'!A34:BJ214,61,FALSE) -> 0.12540288 | BL39: =VLOOKUP(A39,'2022_PAPI_Indicators'!A34:BK214,62,FALSE) -> 0.087031297 | BM39: =VLOOKUP(A39,'2022_PAPI_Indicators'!A34:BL214,63,FALSE) -> 0.16062208 | BN39: =VLOOKUP(A39,'2022_PAPI_Indicators'!A34:BM214,64,FALSE) -> 0.14127241
A40: Information Received Reliable | B40: Tỷ lệ người trả lời cho biết thông tin về chính sách, pháp luật từ cơ quan chính quyền là đáng tin cậy (%) | C40: 0%-100% | D40: =VLOOKUP(A40,'2022_PAPI_Indicators'!A35:B215,2,) -> 0.17435466 | E40: =VLOOKUP(A40,'2022_PAPI_Indicators'!A35:C215,3,FALSE) -> 0.21108915 | F40: =VLOOKUP(A40,'2022_PAPI_Indicators'!A35:D215,4,FALSE) -> 0.07670188 | G40: =VLOOKUP(A40,'2022_PAPI_Indicators'!A35:E215,5,FALSE) -> 0.21551822 | H40: =VLOOKUP(A40,'2022_PAPI_Indicators'!A35:F215,6,FALSE) -> 0.12816273 | I40: =VLOOKUP(A40,'2022_PAPI_Indicators'!A35:G215,7,FALSE) -> 0.13334857 | J40: =VLOOKUP(A40,'2022_PAPI_Indicators'!A35:H215,8,FALSE) -> 0.099181026 | K40: =VLOOKUP(A40,'2022_PAPI_Indicators'!A35:I215,9,FALSE) -> 0.17509443 | L40: =VLOOKUP(A40,'2022_PAPI_Indicators'!A35:J215,10,FALSE) -> 0.10606769 | M40: =VLOOKUP(A40,'2022_PAPI_Indicators'!A35:K215,11,FALSE) -> 0.13016984 | N40: =VLOOKUP(A40,'2022_PAPI_Indicators'!A35:L215,12,FALSE) -> 0.11283091 | O40: =VLOOKUP(A40,'2022_PAPI_Indicators'!A35:M215,13,FALSE) -> 0.18170704 | P40: =VLOOKUP(A40,'2022_PAPI_Indicators'!A35:N215,14,FALSE) -> 0.15009549 | Q40: =VLOOKUP(A40,'2022_PAPI_Indicators'!A35:O215,15,FALSE) -> 0.22400668 | R40: =VLOOKUP(A40,'2022_PAPI_Indicators'!A35:P215,16,FALSE) -> 0 | S40: =VLOOKUP(A40,'2022_PAPI_Indicators'!A35:R215,17,FALSE) -> 0.1215174 | T40: =VLOOKUP(A40,'2022_PAPI_Indicators'!A35:S215,18,FALSE) -> 0.14243025 | U40: =VLOOKUP(A40,'2022_PAPI_Indicators'!A35:T215,19,FALSE) -> 0 | V40: =VLOOKUP(A40,'2022_PAPI_Indicators'!A35:U215,20,FALSE) -> 0.080269054 | W40: =VLOOKUP(A40,'2022_PAPI_Indicators'!A35:V215,21,FALSE) -> 0.075939715 | X40: =VLOOKUP(A40,'2022_PAPI_Indicators'!A35:W215,22,FALSE) -> 0.18024579 | Y40: =VLOOKUP(A40,'2022_PAPI_Indicators'!A35:X215,23,FALSE) -> 0.096904226 | Z40: =VLOOKUP(A40,'2022_PAPI_Indicators'!A35:Y215,24,FALSE) -> 0.10661046 | AA40: =VLOOKUP(A40,'2022_PAPI_Indicators'!A35:Z215,25,FALSE) -> 0.10656008 | AB40: =VLOOKUP(A40,'2022_PAPI_Indicators'!A35:AA215,26,FALSE) -> 0.098508328 | AC40: =VLOOKUP(A40,'2022_PAPI_Indicators'!A35:AB215,27,FALSE) -> 0.14924918 | AD40: =VLOOKUP(A40,'2022_PAPI_Indicators'!A35:AC215,28,FALSE) -> 0.10797573 | AE40: =VLOOKUP(A40,'2022_PAPI_Indicators'!A35:AD215,29,FALSE) -> 0.1335429 | AF40: =VLOOKUP(A40,'2022_PAPI_Indicators'!A35:AE215,30,FALSE) -> 0.14943612 | AG40: =VLOOKUP(A40,'2022_PAPI_Indicators'!A35:AF215,31,FALSE) -> 0.11065347 | AH40: =VLOOKUP(A40,'2022_PAPI_Indicators'!A35:AG215,32,FALSE) -> 0.2354328 | AI40: =VLOOKUP(A40,'2022_PAPI_Indicators'!A35:AH215,33,FALSE) -> 0.075183362 | AJ40: =VLOOKUP(A40,'2022_PAPI_Indicators'!A35:AI215,34,FALSE) -> 0.063180611 | AK40: =VLOOKUP(A40,'2022_PAPI_Indicators'!A35:AJ215,35,FALSE) -> 0.1973753 | AL40: =VLOOKUP(A40,'2022_PAPI_Indicators'!A35:AK215,36,FALSE) -> 0.088396497 | AM40: =VLOOKUP(A40,'2022_PAPI_Indicators'!A35:AL215,37,FALSE) -> 0.0943648 | AN40: =VLOOKUP(A40,'2022_PAPI_Indicators'!A35:AM215,38,FALSE) -> 0.19214305 | AO40: =VLOOKUP(A40,'2022_PAPI_Indicators'!A35:AN215,39,FALSE) -> 0.20402156 | AP40: =VLOOKUP(A40,'2022_PAPI_Indicators'!A35:AO215,40,FALSE) -> 0.1354174 | AQ40: =VLOOKUP(A40,'2022_PAPI_Indicators'!A35:AP215,41,FALSE) -> 0.10398191 | AR40: =VLOOKUP(A40,'2022_PAPI_Indicators'!A35:AQ215,42,FALSE) -> 0.10793921 | AS40: =VLOOKUP(A40,'2022_PAPI_Indicators'!A35:AR215,43,FALSE) -> 0.080061167 | AT40: =VLOOKUP(A40,'2022_PAPI_Indicators'!A35:AS215,44,FALSE) -> 0.14620318 | AU40: =VLOOKUP(A40,'2022_PAPI_Indicators'!A35:AT215,45,FALSE) -> 0.14987333 | AV40: =VLOOKUP(A40,'2022_PAPI_Indicators'!A35:AU215,46,FALSE) -> 0.12407544 | AW40: =VLOOKUP(A40,'2022_PAPI_Indicators'!A35:AV215,47,FALSE) -> 0.085701503 | AX40: =VLOOKUP(A40,'2022_PAPI_Indicators'!A35:AW215,48,FALSE) -> 0.17031312 | AY40: =VLOOKUP(A40,'2022_PAPI_Indicators'!A35:AX215,49,FALSE) -> 0.13902727 | AZ40: =VLOOKUP(A40,'2022_PAPI_Indicators'!A35:AY215,50,FALSE) -> 0.11181778 | BA40: =VLOOKUP(A40,'2022_PAPI_Indicators'!A35:AZ215,51,FALSE) -> 0.087405831 | BB40: =VLOOKUP(A40,'2022_PAPI_Indicators'!A35:BA215,52,FALSE) -> 0.055957153 | BC40: =VLOOKUP(A40,'2022_PAPI_Indicators'!A35:BB215,53,FALSE) -> 0.06586194 | BD40: =VLOOKUP(A40,'2022_PAPI_Indicators'!A35:BC215,54,FALSE) -> 0.055744667 | BE40: =VLOOKUP(A40,'2022_PAPI_Indicators'!A35:BD215,55,FALSE) -> 0.067549504 | BF40: =VLOOKUP(A40,'2022_PAPI_Indicators'!A35:BE215,56,FALSE) -> 0.13813803 | BG40: =VLOOKUP(A40,'2022_PAPI_Indicators'!A35:BF215,57,FALSE) -> 0.067593075 | BH40: =VLOOKUP(A40,'2022_PAPI_Indicators'!A35:BG215,58,FALSE) -> 0.079208501 | BI40: =VLOOKUP(A40,'2022_PAPI_Indicators'!A35:BH215,59,FALSE) -> 0.068965107 | BJ40: =VLOOKUP(A40,'2022_PAPI_Indicators'!A35:BI215,60,FALSE) -> 0.071178474 | BK40: =VLOOKUP(A40,'2022_PAPI_Indicators'!A35:BJ215,61,FALSE) -> 0.12540288 | BL40: =VLOOKUP(A40,'2022_PAPI_Indicators'!A35:BK215,62,FALSE) -> 0.087031297 | BM40: =VLOOKUP(A40,'2022_PAPI_Indicators'!A35:BL215,63,FALSE) -> 0.16206613 | BN40: =VLOOKUP(A40,'2022_PAPI_Indicators'!A35:BM215,64,FALSE) -> 0.13595051
A41: Did Not Pay a Bribe for the Information | B41: Tỷ lệ người trả lời cho biết KHÔNG phải trả chi phí không chính thức mới lấy được thông tin từ chính quyền địa phương (%) | C41: 0%-100% | D41: =VLOOKUP(A41,'2022_PAPI_Indicators'!A36:B216,2,) -> 0.95275384 | E41: =VLOOKUP(A41,'2022_PAPI_Indicators'!A36:C216,3,FALSE) -> 0.96321088 | F41: =VLOOKUP(A41,'2022_PAPI_Indicators'!A36:D216,4,FALSE) -> 0.92634165 | G41: =VLOOKUP(A41,'2022_PAPI_Indicators'!A36:E216,5,FALSE) -> 0.9635213 | H41: =VLOOKUP(A41,'2022_PAPI_Indicators'!A36:F216,6,FALSE) -> 1 | I41: =VLOOKUP(A41,'2022_PAPI_Indicators'!A36:G216,7,FALSE) -> 0.94374031 | J41: =VLOOKUP(A41,'2022_PAPI_Indicators'!A36:H216,8,FALSE) -> 1 | K41: =VLOOKUP(A41,'2022_PAPI_Indicators'!A36:I216,9,FALSE) -> 0.94701678 | L41: =VLOOKUP(A41,'2022_PAPI_Indicators'!A36:J216,10,FALSE) -> 0.93370879 | M41: =VLOOKUP(A41,'2022_PAPI_Indicators'!A36:K216,11,FALSE) -> 0.98609746 | N41: =VLOOKUP(A41,'2022_PAPI_Indicators'!A36:L216,12,FALSE) -> 1 | O41: =VLOOKUP(A41,'2022_PAPI_Indicators'!A36:M216,13,FALSE) -> 0.9558742 | P41: =VLOOKUP(A41,'2022_PAPI_Indicators'!A36:N216,14,FALSE) -> 0.99268967 | Q41: =VLOOKUP(A41,'2022_PAPI_Indicators'!A36:O216,15,FALSE) -> 0.96474367 | R41: =VLOOKUP(A41,'2022_PAPI_Indicators'!A36:P216,16,FALSE) -> 0 | S41: =VLOOKUP(A41,'2022_PAPI_Indicators'!A36:R216,17,FALSE) -> 1 | T41: =VLOOKUP(A41,'2022_PAPI_Indicators'!A36:S216,18,FALSE) -> 1 | U41: =VLOOKUP(A41,'2022_PAPI_Indicators'!A36:T216,19,FALSE) -> 0 | V41: =VLOOKUP(A41,'2022_PAPI_Indicators'!A36:U216,20,FALSE) -> 1 | W41: =VLOOKUP(A41,'2022_PAPI_Indicators'!A36:V216,21,FALSE) -> 1 | X41: =VLOOKUP(A41,'2022_PAPI_Indicators'!A36:W216,22,FALSE) -> 1 | Y41: =VLOOKUP(A41,'2022_PAPI_Indicators'!A36:X216,23,FALSE) -> 1 | Z41: =VLOOKUP(A41,'2022_PAPI_Indicators'!A36:Y216,24,FALSE) -> 1 | AA41: =VLOOKUP(A41,'2022_PAPI_Indicators'!A36:Z216,25,FALSE) -> 0.9444117 | AB41: =VLOOKUP(A41,'2022_PAPI_Indicators'!A36:AA216,26,FALSE) -> 1 | AC41: =VLOOKUP(A41,'2022_PAPI_Indicators'!A36:AB216,27,FALSE) -> 0.96317887 | AD41: =VLOOKUP(A41,'2022_PAPI_Indicators'!A36:AC216,28,FALSE) -> 0.9007495 | AE41: =VLOOKUP(A41,'2022_PAPI_Indicators'!A36:AD216,29,FALSE) -> 0.95256329 | AF41: =VLOOKUP(A41,'2022_PAPI_Indicators'!A36:AE216,30,FALSE) -> 1 | AG41: =VLOOKUP(A41,'2022_PAPI_Indicators'!A36:AF216,31,FALSE) -> 1 | AH41: =VLOOKUP(A41,'2022_PAPI_Indicators'!A36:AG216,32,FALSE) -> 1 | AI41: =VLOOKUP(A41,'2022_PAPI_Indicators'!A36:AH216,33,FALSE) -> 0.99600774 | AJ41: =VLOOKUP(A41,'2022_PAPI_Indicators'!A36:AI216,34,FALSE) -> 1 | AK41: =VLOOKUP(A41,'2022_PAPI_Indicators'!A36:AJ216,35,FALSE) -> 1 | AL41: =VLOOKUP(A41,'2022_PAPI_Indicators'!A36:AK216,36,FALSE) -> 0.98122549 | AM41: =VLOOKUP(A41,'2022_PAPI_Indicators'!A36:AL216,37,FALSE) -> 0.935031 | AN41: =VLOOKUP(A41,'2022_PAPI_Indicators'!A36:AM216,38,FALSE) -> 1 | AO41: =VLOOKUP(A41,'2022_PAPI_Indicators'!A36:AN216,39,FALSE) -> 1 | AP41: =VLOOKUP(A41,'2022_PAPI_Indicators'!A36:AO216,40,FALSE) -> 1 | AQ41: =VLOOKUP(A41,'2022_PAPI_Indicators'!A36:AP216,41,FALSE) -> 1 | AR41: =VLOOKUP(A41,'2022_PAPI_Indicators'!A36:AQ216,42,FALSE) -> 1 | AS41: =VLOOKUP(A41,'2022_PAPI_Indicators'!A36:AR216,43,FALSE) -> 1 | AT41: =VLOOKUP(A41,'2022_PAPI_Indicators'!A36:AS216,44,FALSE) -> 0.92736185 | AU41: =VLOOKUP(A41,'2022_PAPI_Indicators'!A36:AT216,45,FALSE) -> 0.91290587 | AV41: =VLOOKUP(A41,'2022_PAPI_Indicators'!A36:AU216,46,FALSE) -> 0.94896197 | AW41: =VLOOKUP(A41,'2022_PAPI_Indicators'!A36:AV216,47,FALSE) -> 0.92841804 | AX41: =VLOOKUP(A41,'2022_PAPI_Indicators'!A36:AW216,48,FALSE) -> 0.96838313 | AY41: =VLOOKUP(A41,'2022_PAPI_Indicators'!A36:AX216,49,FALSE) -> 0.99620086 | AZ41: =VLOOKUP(A41,'2022_PAPI_Indicators'!A36:AY216,50,FALSE) -> 0.94503808 | BA41: =VLOOKUP(A41,'2022_PAPI_Indicators'!A36:AZ216,51,FALSE) -> 0.97123069 | BB41: =VLOOKUP(A41,'2022_PAPI_Indicators'!A36:BA216,52,FALSE) -> 1 | BC41: =VLOOKUP(A41,'2022_PAPI_Indicators'!A36:BB216,53,FALSE) -> 1 | BD41: =VLOOKUP(A41,'2022_PAPI_Indicators'!A36:BC216,54,FALSE) -> 1 | BE41: =VLOOKUP(A41,'2022_PAPI_Indicators'!A36:BD216,55,FALSE) -> 1 | BF41: =VLOOKUP(A41,'2022_PAPI_Indicators'!A36:BE216,56,FALSE) -> 0.94519836 | BG41: =VLOOKUP(A41,'2022_PAPI_Indicators'!A36:BF216,57,FALSE) -> 1 | BH41: =VLOOKUP(A41,'2022_PAPI_Indicators'!A36:BG216,58,FALSE) -> 1 | BI41: =VLOOKUP(A41,'2022_PAPI_Indicators'!A36:BH216,59,FALSE) -> 0.98113602 | BJ41: =VLOOKUP(A41,'2022_PAPI_Indicators'!A36:BI216,60,FALSE) -> 0.92866462 | BK41: =VLOOKUP(A41,'2022_PAPI_Indicators'!A36:BJ216,61,FALSE) -> 1 | BL41: =VLOOKUP(A41,'2022_PAPI_Indicators'!A36:BK216,62,FALSE) -> 1 | BM41: =VLOOKUP(A41,'2022_PAPI_Indicators'!A36:BL216,63,FALSE) -> 1 | BN41: =VLOOKUP(A41,'2022_PAPI_Indicators'!A36:BM216,64,FALSE) -> 0.97855353
... A65: Contacted Commune People's Committee | B65: Tỷ lệ người trả lời cho biết họ đã liên hệ cán bộ UBND xã/phường để giải quyết khúc mắc (%) | C65: 0%-100% | D65: =VLOOKUP(A65,'2022_PAPI_Indicators'!A60:B240,2,) -> 0.12513061 | E65: =VLOOKUP(A65,'2022_PAPI_Indicators'!A60:C240,3,FALSE) -> 0.10856292 | F65: =VLOOKUP(A65,'2022_PAPI_Indicators'!A60:D240,4,FALSE) -> 0.11779301 | G65: =VLOOKUP(A65,'2022_PAPI_Indicators'!A60:E240,5,FALSE) -> 0.1958193 | H65: =VLOOKUP(A65,'2022_PAPI_Indicators'!A60:F240,6,FALSE) -> 0.13861386 | I65: =VLOOKUP(A65,'2022_PAPI_Indicators'!A60:G240,7,FALSE) -> 0.15154026 | J65: =VLOOKUP(A65,'2022_PAPI_Indicators'!A60:H240,8,FALSE) -> 0.12170132 | K65: =VLOOKUP(A65,'2022_PAPI_Indicators'!A60:I240,9,FALSE) -> 0.16163746 | L65: =VLOOKUP(A65,'2022_PAPI_Indicators'!A60:J240,10,FALSE) -> 0.10537458 | M65: =VLOOKUP(A65,'2022_PAPI_Indicators'!A60:K240,11,FALSE) -> 0.14280438 | N65: =VLOOKUP(A65,'2022_PAPI_Indicators'!A60:L240,12,FALSE) -> 0.14379728 | O65: =VLOOKUP(A65,'2022_PAPI_Indicators'!A60:M240,13,FALSE) -> 0.12466373 | P65: =VLOOKUP(A65,'2022_PAPI_Indicators'!A60:N240,14,FALSE) -> 0.11637436 | Q65: =VLOOKUP(A65,'2022_PAPI_Indicators'!A60:O240,15,FALSE) -> 0.16860563 | R65: =VLOOKUP(A65,'2022_PAPI_Indicators'!A60:P240,16,FALSE) -> 0.12658566 | S65: =VLOOKUP(A65,'2022_PAPI_Indicators'!A60:R240,17,FALSE) -> 0.10541362 | T65: =VLOOKUP(A65,'2022_PAPI_Indicators'!A60:S240,18,FALSE) -> 0.1261238 | U65: =VLOOKUP(A65,'2022_PAPI_Indicators'!A60:T240,19,FALSE) -> 0 | V65: =VLOOKUP(A65,'2022_PAPI_Indicators'!A60:U240,20,FALSE) -> 0.075303681 | W65: =VLOOKUP(A65,'2022_PAPI_Indicators'!A60:V240,21,FALSE) -> 0.15483668 | X65: =VLOOKUP(A65,'2022_PAPI_Indicators'!A60:W240,22,FALSE) -> 0.13582778 | Y65: =VLOOKUP(A65,'2022_PAPI_Indicators'!A60:X240,23,FALSE) -> 0.10234687 | Z65: =VLOOKUP(A65,'2022_PAPI_Indicators'!A60:Y240,24,FALSE) -> 0.16960862 | AA65: =VLOOKUP(A65,'2022_PAPI_Indicators'!A60:Z240,25,FALSE) -> 0.11365779 | AB65: =VLOOKUP(A65,'2022_PAPI_Indicators'!A60:AA240,26,FALSE) -> 0.13554528 | AC65: =VLOOKUP(A65,'2022_PAPI_Indicators'!A60:AB240,27,FALSE) -> 0.14439599 | AD65: =VLOOKUP(A65,'2022_PAPI_Indicators'!A60:AC240,28,FALSE) -> 0.13333334 | AE65: =VLOOKUP(A65,'2022_PAPI_Indicators'!A60:AD240,29,FALSE) -> 0.15625 | AF65: =VLOOKUP(A65,'2022_PAPI_Indicators'!A60:AE240,30,FALSE) -> 0.13642511 | AG65: =VLOOKUP(A65,'2022_PAPI_Indicators'!A60:AF240,31,FALSE) -> 0.18112843 | AH65: =VLOOKUP(A65,'2022_PAPI_Indicators'!A60:AG240,32,FALSE) -> 0.19014119 | AI65: =VLOOKUP(A65,'2022_PAPI_Indicators'!A60:AH240,33,FALSE) -> 0.16876402 | AJ65: =VLOOKUP(A65,'2022_PAPI_Indicators'!A60:AI240,34,FALSE) -> 0.1607116 | AK65: =VLOOKUP(A65,'2022_PAPI_Indicators'!A60:AJ240,35,FALSE) -> 0.2109744 | AL65: =VLOOKUP(A65,'2022_PAPI_Indicators'!A60:AK240,36,FALSE) -> 0.15817066 | AM65: =VLOOKUP(A65,'2022_PAPI_Indicators'!A60:AL240,37,FALSE) -> 0.18831906 | AN65: =VLOOKUP(A65,'2022_PAPI_Indicators'!A60:AM240,38,FALSE) -> 0.23493724 | AO65: =VLOOKUP(A65,'2022_PAPI_Indicators'!A60:AN240,39,FALSE) -> 0.24509476 | AP65: =VLOOKUP(A65,'2022_PAPI_Indicators'!A60:AO240,40,FALSE) -> 0.24796282 | AQ65: =VLOOKUP(A65,'2022_PAPI_Indicators'!A60:AP240,41,FALSE) -> 0.11442845 | AR65: =VLOOKUP(A65,'2022_PAPI_Indicators'!A60:AQ240,42,FALSE) -> 0.17625006 | AS65: =VLOOKUP(A65,'2022_PAPI_Indicators'!A60:AR240,43,FALSE) -> 0.11115303 | AT65: =VLOOKUP(A65,'2022_PAPI_Indicators'!A60:AS240,44,FALSE) -> 0.20262785 | AU65: =VLOOKUP(A65,'2022_PAPI_Indicators'!A60:AT240,45,FALSE) -> 0.17953014 | AV65: =VLOOKUP(A65,'2022_PAPI_Indicators'!A60:AU240,46,FALSE) -> 0.18330017 | AW65: =VLOOKUP(A65,'2022_PAPI_Indicators'!A60:AV240,47,FALSE) -> 0.1920597 | AX65: =VLOOKUP(A65,'2022_PAPI_Indicators'!A60:AW240,48,FALSE) -> 0.22428319 | AY65: =VLOOKUP(A65,'2022_PAPI_Indicators'!A60:AX240,49,FALSE) -> 0.16482528 | AZ65: =VLOOKUP(A65,'2022_PAPI_Indicators'!A60:AY240,50,FALSE) -> 0.18299203 | BA65: =VLOOKUP(A65,'2022_PAPI_Indicators'!A60:AZ240,51,FALSE) -> 0.21614698 | BB65: =VLOOKUP(A65,'2022_PAPI_Indicators'!A60:BA240,52,FALSE) -> 0.11901589 | BC65: =VLOOKUP(A65,'2022_PAPI_Indicators'!A60:BB240,53,FALSE) -> 0.17126732 | BD65: =VLOOKUP(A65,'2022_PAPI_Indicators'!A60:BC240,54,FALSE) -> 0.18697172 | BE65: =VLOOKUP(A65,'2022_PAPI_Indicators'!A60:BD240,55,FALSE) -> 0.21498474 | BF65: =VLOOKUP(A65,'2022_PAPI_Indicators'!A60:BE240,56,FALSE) -> 0.26359579 | BG65: =VLOOKUP(A65,'2022_PAPI_Indicators'!A60:BF240,57,FALSE) -> 0.30418104 | BH65: =VLOOKUP(A65,'2022_PAPI_Indicators'!A60:BG240,58,FALSE) -> 0.1643451 | BI65: =VLOOKUP(A65,'2022_PAPI_Indicators'!A60:BH240,59,FALSE) -> 0.20240477 | BJ65: =VLOOKUP(A65,'2022_PAPI_Indicators'!A60:BI240,60,FALSE) -> 0.16568409 | BK65: =VLOOKUP(A65,'2022_PAPI_Indicators'!A60:BJ240,61,FALSE) -> 0.24276483 | BL65: =VLOOKUP(A65,'2022_PAPI_Indicators'!A60:BK240,62,FALSE) -> 0.2345507 | BM65: =VLOOKUP(A65,'2022_PAPI_Indicators'!A60:BL240,63,FALSE) -> 0.33198002 | BN65: =VLOOKUP(A65,'2022_PAPI_Indicators'!A60:BM240,64,FALSE) -> 0.25832203
A66: Contact with Commune People's Committee Successful | B66: Tỷ lệ người trả lời cho biết cuộc gặp với cán bộ UBND xã/phường để giải quyết khúc mắc có kết quả tốt (%) | C66: 0%-100% | D66: 0.89 | E66: 0.92996269 | F66: 0.93458962 | G66: 0.9124648 | H66: 0.92460245 | I66: 0.85338956 | J66: 0.9867112 | K66: 0.92713743 | L66: 0.91599339 | M66: 0.89846909 | N66: 0.94347274 | O66: 0.88092273 | P66: 0.93716037 | Q66: 1 | R66: 0.94 | S66: 0.78890646 | T66: 0.88146788 | V66: 0.78637516 | W66: 0.99765933 | X66: 0.88966316 | Y66: 0.92036325 | Z66: 0.91942704 | AA66: 0.93117833 | AB66: 0.8867169 | AC66: 0.86507761 | AD66: 0.75252664 | AE66: 0.95210284 | AF66: 0.89692754 | AG66: 0.88033205 | AH66: 0.90038812 | AI66: 0.99010533 | AJ66: 0.90557969 | AK66: 0.90692794 | AL66: 0.89168167 | AM66: 0.86855352 | AN66: 0.95985639 | AO66: 0.92412609 | AP66: 0.93698651 | AQ66: 0.94732106 | AR66: 0.73175442 | AS66: 0.91168481 | AT66: 0.91330498 | AU66: 0.98386127 | AV66: 0.82587451 | AW66: 0.95196128 | AX66: 0.91845596 | AY66: 0.88078332 | AZ66: 0.76999629 | BA66: 0.9339751 | BB66: 0.88779664 | BC66: 0.90866971 | BD66: 0.86561316 | BE66: 0.85908461 | BF66: 0.89566213 | BG66: 0.96963006 | BH66: 0.89090693 | BI66: 0.8152734 | BJ66: 0.86792827 | BK66: 1 | BL66: 0.96380293 | BM66: 0.96587294 | BN66: 0.85804886
A67: Contacted Mass Organization | B67: Tỷ lệ người trả lời cho biết họ đã liên hệ cán bộ đoàn thể để giải quyết khúc mắc (%) | C67: 0%-100% | D67: =VLOOKUP(A67,'2022_PAPI_Indicators'!A62:B242,2,) -> 0.054790724 | E67: =VLOOKUP(A67,'2022_PAPI_Indicators'!A62:C242,3,FALSE) -> 0.08469528 | F67: =VLOOKUP(A67,'2022_PAPI_Indicators'!A62:D242,4,FALSE) -> 0.077989228 | G67: =VLOOKUP(A67,'2022_PAPI_Indicators'!A62:E242,5,FALSE) -> 0.15185186 | H67: =VLOOKUP(A67,'2022_PAPI_Indicators'!A62:F242,6,FALSE) -> 0.080857947 | I67: =VLOOKUP(A67,'2022_PAPI_Indicators'!A62:G242,7,FALSE) -> 0.084001526 | J67: =VLOOKUP(A67,'2022_PAPI_Indicators'!A62:H242,8,FALSE) -> 0.06458392 | K67: =VLOOKUP(A67,'2022_PAPI_Indicators'!A62:I242,9,FALSE) -> 0.073917978 | L67: =VLOOKUP(A67,'2022_PAPI_Indicators'!A62:J242,10,FALSE) -> 0.10004175 | M67: =VLOOKUP(A67,'2022_PAPI_Indicators'!A62:K242,11,FALSE) -> 0.096269198 | N67: =VLOOKUP(A67,'2022_PAPI_Indicators'!A62:L242,12,FALSE) -> 0.076446675 | O67: =VLOOKUP(A67,'2022_PAPI_Indicators'!A62:M242,13,FALSE) -> 0.087035634 | P67: =VLOOKUP(A67,'2022_PAPI_Indicators'!A62:N242,14,FALSE) -> 0.12168401 | Q67: =VLOOKUP(A67,'2022_PAPI_Indicators'!A62:O242,15,FALSE) -> 0.072945498 | R67: =VLOOKUP(A67,'2022_PAPI_Indicators'!A62:P242,16,FALSE) -> 0.092957169 | S67: =VLOOKUP(A67,'2022_PAPI_Indicators'!A62:R242,17,FALSE) -> 0.072691105 | T67: =VLOOKUP(A67,'2022_PAPI_Indicators'!A62:S242,18,FALSE) -> 0.090514094 | U67: =VLOOKUP(A67,'2022_PAPI_Indicators'!A62:T242,19,FALSE) -> 0 | V67: =VLOOKUP(A67,'2022_PAPI_Indicators'!A62:U242,20,FALSE) -> 0.036112841 | W67: =VLOOKUP(A67,'2022_PAPI_Indicators'!A62:V242,21,FALSE) -> 0.1249643 | X67: =VLOOKUP(A67,'2022_PAPI_Indicators'!A62:W242,22,FALSE) -> 0.078003101 | Y67: =VLOOKUP(A67,'2022_PAPI_Indicators'!A62:X242,23,FALSE) -> 0.04804416 | Z67: =VLOOKUP(A67,'2022_PAPI_Indicators'!A62:Y242,24,FALSE) -> 0.05206294 | AA67: =VLOOKUP(A67,'2022_PAPI_Indicators'!A62:Z242,25,FALSE) -> 0.080933496 | AB67: =VLOOKUP(A67,'2022_PAPI_Indicators'!A62:AA242,26,FALSE) -> 0.066872463 | AC67: =VLOOKUP(A67,'2022_PAPI_Indicators'!A62:AB242,27,FALSE) -> 0.090499192 | AD67: =VLOOKUP(A67,'2022_PAPI_Indicators'!A62:AC242,28,FALSE) -> 0.054628268 | AE67: =VLOOKUP(A67,'2022_PAPI_Indicators'!A62:AD242,29,FALSE) -> 0.14810893 | AF67: =VLOOKUP(A67,'2022_PAPI_Indicators'!A62:AE242,30,FALSE) -> 0.15048678 | AG67: =VLOOKUP(A67,'2022_PAPI_Indicators'!A62:AF242,31,FALSE) -> 0.12926508 | AH67: =VLOOKUP(A67,'2022_PAPI_Indicators'!A62:AG242,32,FALSE) -> 0.14379887 | AI67: =VLOOKUP(A67,'2022_PAPI_Indicators'!A62:AH242,33,FALSE) -> 0.061681617 | AJ67: =VLOOKUP(A67,'2022_PAPI_Indicators'!A62:AI242,34,FALSE) -> 0.089184456 | AK67: =VLOOKUP(A67,'2022_PAPI_Indicators'!A62:AJ242,35,FALSE) -> 0.12890421 | AL67: =VLOOKUP(A67,'2022_PAPI_Indicators'!A62:AK242,36,FALSE) -> 0.058911081 | AM67: =VLOOKUP(A67,'2022_PAPI_Indicators'!A62:AL242,37,FALSE) -> 0.088073969 | AN67: =VLOOKUP(A67,'2022_PAPI_Indicators'!A62:AM242,38,FALSE) -> 0.10346235 | AO67: =VLOOKUP(A67,'2022_PAPI_Indicators'!A62:AN242,39,FALSE) -> 0.13985015 | AP67: =VLOOKUP(A67,'2022_PAPI_Indicators'!A62:AO242,40,FALSE) -> 0.19248271 | AQ67: =VLOOKUP(A67,'2022_PAPI_Indicators'!A62:AP242,41,FALSE) -> 0.10528091 | AR67: =VLOOKUP(A67,'2022_PAPI_Indicators'!A62:AQ242,42,FALSE) -> 0.073509216 | AS67: =VLOOKUP(A67,'2022_PAPI_Indicators'!A62:AR242,43,FALSE) -> 0.05882353 | AT67: =VLOOKUP(A67,'2022_PAPI_Indicators'!A62:AS242,44,FALSE) -> 0.12700135 | AU67: =VLOOKUP(A67,'2022_PAPI_Indicators'!A62:AT242,45,FALSE) -> 0.13333693 | AV67: =VLOOKUP(A67,'2022_PAPI_Indicators'!A62:AU242,46,FALSE) -> 0.12498214 | AW67: =VLOOKUP(A67,'2022_PAPI_Indicators'!A62:AV242,47,FALSE) -> 0.089830808 | AX67: =VLOOKUP(A67,'2022_PAPI_Indicators'!A62:AW242,48,FALSE) -> 0.13679656 | AY67: =VLOOKUP(A67,'2022_PAPI_Indicators'!A62:AX242,49,FALSE) -> 0.08979328 | AZ67: =VLOOKUP(A67,'2022_PAPI_Indicators'!A62:AY242,50,FALSE) -> 0.10281413 | BA67: =VLOOKUP(A67,'2022_PAPI_Indicators'!A62:AZ242,51,FALSE) -> 0.1038542 | BB67: =VLOOKUP(A67,'2022_PAPI_Indicators'!A62:BA242,52,FALSE) -> 0.057431474 | BC67: =VLOOKUP(A67,'2022_PAPI_Indicators'!A62:BB242,53,FALSE) -> 0.074094683 | BD67: =VLOOKUP(A67,'2022_PAPI_Indicators'!A62:BC242,54,FALSE) -> 0.11986995 | BE67: =VLOOKUP(A67,'2022_PAPI_Indicators'!A62:BD242,55,FALSE) -> 0.078106977 | BF67: =VLOOKUP(A67,'2022_PAPI_Indicators'!A62:BE242,56,FALSE) -> 0.18519709 | BG67: =VLOOKUP(A67,'2022_PAPI_Indicators'!A62:BF242,57,FALSE) -> 0.15814997 | BH67: =VLOOKUP(A67,'2022_PAPI_Indicators'!A62:BG242,58,FALSE) -> 0.065044232 | BI67: =VLOOKUP(A67,'2022_PAPI_Indicators'!A62:BH242,59,FALSE) -> 0.12869307 | BJ67: =VLOOKUP(A67,'2022_PAPI_Indicators'!A62:BI242,60,FALSE) -> 0.10305933 | BK67: =VLOOKUP(A67,'2022_PAPI_Indicators'!A62:BJ242,61,FALSE) -> 0.13435148 | BL67: =VLOOKUP(A67,'2022_PAPI_Indicators'!A62:BK242,62,FALSE) -> 0.13960057 | BM67: =VLOOKUP(A67,'2022_PAPI_Indicators'!A62:BL242,63,FALSE) -> 0.16034991 | BN67: =VLOOKUP(A67,'2022_PAPI_Indicators'!A62:BM242,64,FALSE) -> 0.11537525
A68: Contact with Mass Organization Successful | B68: Tỷ lệ người trả lời cho biết cuộc gặp với cán bộ đoàn thể để giải quyết khúc mắc có kết quả tốt (%) | C68: 0%-100% | D68: =VLOOKUP(A68,'2022_PAPI_Indicators'!A63:B243,2,) -> 0.95668703 | E68: =VLOOKUP(A68,'2022_PAPI_Indicators'!A63:C243,3,FALSE) -> 0.91022575 | F68: =VLOOKUP(A68,'2022_PAPI_Indicators'!A63:D243,4,FALSE) -> 1 | G68: =VLOOKUP(A68,'2022_PAPI_Indicators'!A63:E243,5,FALSE) -> 0.95200962 | H68: =VLOOKUP(A68,'2022_PAPI_Indicators'!A63:F243,6,FALSE) -> 1 | I68: =VLOOKUP(A68,'2022_PAPI_Indicators'!A63:G243,7,FALSE) -> 0.90959156 | J68: =VLOOKUP(A68,'2022_PAPI_Indicators'!A63:H243,8,FALSE) -> 1 | K68: =VLOOKUP(A68,'2022_PAPI_Indicators'!A63:I243,9,FALSE) -> 0.93103039 | L68: =VLOOKUP(A68,'2022_PAPI_Indicators'!A63:J243,10,FALSE) -> 0.92481035 | M68: =VLOOKUP(A68,'2022_PAPI_Indicators'!A63:K243,11,FALSE) -> 1 | N68: =VLOOKUP(A68,'2022_PAPI_Indicators'!A63:L243,12,FALSE) -> 1 | O68: =VLOOKUP(A68,'2022_PAPI_Indicators'!A63:M243,13,FALSE) -> 1 | P68: =VLOOKUP(A68,'2022_PAPI_Indicators'!A63:N243,14,FALSE) -> 0.99091637 | Q68: =VLOOKUP(A68,'2022_PAPI_Indicators'!A63:O243,15,FALSE) -> 1 | R68: =VLOOKUP(A68,'2022_PAPI_Indicators'!A63:P243,16,FALSE) -> 0.92022043 | S68: =VLOOKUP(A68,'2022_PAPI_Indicators'!A63:R243,17,FALSE) -> 0.88317484 | T68: =VLOOKUP(A68,'2022_PAPI_Indicators'!A63:S243,18,FALSE) -> 1 | U68: =VLOOKUP(A68,'2022_PAPI_Indicators'!A63:T243,19,FALSE) -> 0 | V68: =VLOOKUP(A68,'2022_PAPI_Indicators'!A63:U243,20,FALSE) -> 1 | W68: =VLOOKUP(A68,'2022_PAPI_Indicators'!A63:V243,21,FALSE) -> 0.9416883 | X68: =VLOOKUP(A68,'2022_PAPI_Indicators'!A63:W243,22,FALSE) -> 1 | Y68: =VLOOKUP(A68,'2022_PAPI_Indicators'!A63:X243,23,FALSE) -> 1 | Z68: =VLOOKUP(A68,'2022_PAPI_Indicators'!A63:Y243,24,FALSE) -> 1 | AA68: =VLOOKUP(A68,'2022_PAPI_Indicators'!A63:Z243,25,FALSE) -> 1 | AB68: =VLOOKUP(A68,'2022_PAPI_Indicators'!A63:AA243,26,FALSE) -> 0.78269255 | AC68: =VLOOKUP(A68,'2022_PAPI_Indicators'!A63:AB243,27,FALSE) -> 1 | AD68: =VLOOKUP(A68,'2022_PAPI_Indicators'!A63:AC243,28,FALSE) -> 0.94581079 | AE68: =VLOOKUP(A68,'2022_PAPI_Indicators'!A63:AD243,29,FALSE) -> 1 | AF68: =VLOOKUP(A68,'2022_PAPI_Indicators'!A63:AE243,30,FALSE) -> 0.85983813 | AG68: =VLOOKUP(A68,'2022_PAPI_Indicators'!A63:AF243,31,FALSE) -> 0.8882128 | AH68: =VLOOKUP(A68,'2022_PAPI_Indicators'!A63:AG243,32,FALSE) -> 1 | AI68: =VLOOKUP(A68,'2022_PAPI_Indicators'!A63:AH243,33,FALSE) -> 1 | AJ68: =VLOOKUP(A68,'2022_PAPI_Indicators'!A63:AI243,34,FALSE) -> 0.92188662 | AK68: =VLOOKUP(A68,'2022_PAPI_Indicators'!A63:AJ243,35,FALSE) -> 0.94922376 | AL68: =VLOOKUP(A68,'2022_PAPI_Indicators'!A63:AK243,36,FALSE) -> 1 | AM68: =VLOOKUP(A68,'2022_PAPI_Indicators'!A63:AL243,37,FALSE) -> 0.91930246 | AN68: =VLOOKUP(A68,'2022_PAPI_Indicators'!A63:AM243,38,FALSE) -> 0.96870893 | AO68: =VLOOKUP(A68,'2022_PAPI_Indicators'!A63:AN243,39,FALSE) -> 0.95567566 | AP68: =VLOOKUP(A68,'2022_PAPI_Indicators'!A63:AO243,40,FALSE) -> 0.95529413 | AQ68: =VLOOKUP(A68,'2022_PAPI_Indicators'!A63:AP243,41,FALSE) -> 0.87880975 | AR68: =VLOOKUP(A68,'2022_PAPI_Indicators'!A63:AQ243,42,FALSE) -> 0.68647987 | AS68: =VLOOKUP(A68,'2022_PAPI_Indicators'!A63:AR243,43,FALSE) -> 1 | AT68: =VLOOKUP(A68,'2022_PAPI_Indicators'!A63:AS243,44,FALSE) -> 0.87125307 | AU68: =VLOOKUP(A68,'2022_PAPI_Indicators'!A63:AT243,45,FALSE) -> 0.94882369 | AV68: =VLOOKUP(A68,'2022_PAPI_Indicators'!A63:AU243,46,FALSE) -> 0.93436497 | AW68: =VLOOKUP(A68,'2022_PAPI_Indicators'!A63:AV243,47,FALSE) -> 0.8249433 | AX68: =VLOOKUP(A68,'2022_PAPI_Indicators'!A63:AW243,48,FALSE) -> 0.96337587 | AY68: =VLOOKUP(A68,'2022_PAPI_Indicators'!A63:AX243,49,FALSE) -> 0.95335913 | AZ68: =VLOOKUP(A68,'2022_PAPI_Indicators'!A63:AY243,50,FALSE) -> 1 | BA68: =VLOOKUP(A68,'2022_PAPI_Indicators'!A63:AZ243,51,FALSE) -> 0.96819389 | BB68: =VLOOKUP(A68,'2022_PAPI_Indicators'!A63:BA243,52,FALSE) -> 1 | BC68: =VLOOKUP(A68,'2022_PAPI_Indicators'!A63:BB243,53,FALSE) -> 1 | BD68: =VLOOKUP(A68,'2022_PAPI_Indicators'!A63:BC243,54,FALSE) -> 0.93735379 | BE68: =VLOOKUP(A68,'2022_PAPI_Indicators'!A63:BD243,55,FALSE) -> 0.9036727 | BF68: =VLOOKUP(A68,'2022_PAPI_Indicators'!A63:BE243,56,FALSE) -> 0.96287328 | BG68: =VLOOKUP(A68,'2022_PAPI_Indicators'!A63:BF243,57,FALSE) -> 1 | BH68: =VLOOKUP(A68,'2022_PAPI_Indicators'!A63:BG243,58,FALSE) -> 1 | BI68: =VLOOKUP(A68,'2022_PAPI_Indicators'!A63:BH243,59,FALSE) -> 0.94556117 | BJ68: =VLOOKUP(A68,'2022_PAPI_Indicators'!A63:BI243,60,FALSE) -> 1 | BK68: =VLOOKUP(A68,'2022_PAPI_Indicators'!A63:BJ243,61,FALSE) -> 1 | BL68: =VLOOKUP(A68,'2022_PAPI_Indicators'!A63:BK243,62,FALSE) -> 0.9932555 | BM68: =VLOOKUP(A68,'2022_PAPI_Indicators'!A63:BL243,63,FALSE) -> 0.95666933 | BN68: =VLOOKUP(A68,'2022_PAPI_Indicators'!A63:BM243,64,FALSE) -> 1
A69: Contacted People's Council | B69: Tỷ lệ người trả lời cho biết họ đã liên hệ cán bộ HĐND xã/phường để giải quyết khúc mắc (%) | C69: 0%-100% | D69: =VLOOKUP(A69,'2022_PAPI_Indicators'!A64:B244,2,) -> 0.030997146 | E69: =VLOOKUP(A69,'2022_PAPI_Indicators'!A64:C244,3,FALSE) -> 0.031233605 | F69: =VLOOKUP(A69,'2022_PAPI_Indicators'!A64:D244,4,FALSE) -> 0.049661089 | G69: =VLOOKUP(A69,'2022_PAPI_Indicators'!A64:E244,5,FALSE) -> 0.052685432 | H69: =VLOOKUP(A69,'2022_PAPI_Indicators'!A64:F244,6,FALSE) -> 0.058305714 | I69: =VLOOKUP(A69,'2022_PAPI_Indicators'!A64:G244,7,FALSE) -> 0.075044505 | J69: =VLOOKUP(A69,'2022_PAPI_Indicators'!A64:H244,8,FALSE) -> 0.053483542 | K69: =VLOOKUP(A69,'2022_PAPI_Indicators'!A64:I244,9,FALSE) -> 0.096780233 | L69: =VLOOKUP(A69,'2022_PAPI_Indicators'!A64:J244,10,FALSE) -> 0.047568105 | M69: =VLOOKUP(A69,'2022_PAPI_Indicators'!A64:K244,11,FALSE) -> 0.036247637 | N69: =VLOOKUP(A69,'2022_PAPI_Indicators'!A64:L244,12,FALSE) -> 0.01625693 | O69: =VLOOKUP(A69,'2022_PAPI_Indicators'!A64:M244,13,FALSE) -> 0.027375475 | P69: =VLOOKUP(A69,'2022_PAPI_Indicators'!A64:N244,14,FALSE) -> 0.059184007 | Q69: =VLOOKUP(A69,'2022_PAPI_Indicators'!A64:O244,15,FALSE) -> 0.045244969 | R69: =VLOOKUP(A69,'2022_PAPI_Indicators'!A64:P244,16,FALSE) -> 0.038666084 | S69: =VLOOKUP(A69,'2022_PAPI_Indicators'!A64:R244,17,FALSE) -> 0.055306058 | T69: =VLOOKUP(A69,'2022_PAPI_Indicators'!A64:S244,18,FALSE) -> 0.054363411 | U69: =VLOOKUP(A69,'2022_PAPI_Indicators'!A64:T244,19,FALSE) -> 0 | V69: =VLOOKUP(A69,'2022_PAPI_Indicators'!A64:U244,20,FALSE) -> 0.0080433683 | W69: =VLOOKUP(A69,'2022_PAPI_Indicators'!A64:V244,21,FALSE) -> 0.058233157 | X69: =VLOOKUP(A69,'2022_PAPI_Indicators'!A64:W244,22,FALSE) -> 0.046149138 | Y69: =VLOOKUP(A69,'2022_PAPI_Indicators'!A64:X244,23,FALSE) -> 0.029894361 | Z69: =VLOOKUP(A69,'2022_PAPI_Indicators'!A64:Y244,24,FALSE) -> 0.02341515 | AA69: =VLOOKUP(A69,'2022_PAPI_Indicators'!A64:Z244,25,FALSE) -> 0.045764428 | AB69: =VLOOKUP(A69,'2022_PAPI_Indicators'!A64:AA244,26,FALSE) -> 0.025077173 | AC69: =VLOOKUP(A69,'2022_PAPI_Indicators'!A64:AB244,27,FALSE) -> 0.057008676 | AD69: =VLOOKUP(A69,'2022_PAPI_Indicators'!A64:AC244,28,FALSE) -> 0.036530808 | AE69: =VLOOKUP(A69,'2022_PAPI_Indicators'!A64:AD244,29,FALSE) -> 0.06118571 | AF69: =VLOOKUP(A69,'2022_PAPI_Indicators'!A64:AE244,30,FALSE) -> 0.046791069 | AG69: =VLOOKUP(A69,'2022_PAPI_Indicators'!A64:AF244,31,FALSE) -> 0.061713804 | AH69: =VLOOKUP(A69,'2022_PAPI_Indicators'!A64:AG244,32,FALSE) -> 0.056385469 | AI69: =VLOOKUP(A69,'2022_PAPI_Indicators'!A64:AH244,33,FALSE) -> 0.014309055 | AJ69: =VLOOKUP(A69,'2022_PAPI_Indicators'!A64:AI244,34,FALSE) -> 0.044281866 | AK69: =VLOOKUP(A69,'2022_PAPI_Indicators'!A64:AJ244,35,FALSE) -> 0.0558891 | AL69: =VLOOKUP(A69,'2022_PAPI_Indicators'!A64:AK244,36,FALSE) -> 0.013696254 | AM69: =VLOOKUP(A69,'2022_PAPI_Indicators'!A64:AL244,37,FALSE) -> 0.061098609 | AN69: =VLOOKUP(A69,'2022_PAPI_Indicators'!A64:AM244,38,FALSE) -> 0.065737449 | AO69: =VLOOKUP(A69,'2022_PAPI_Indicators'!A64:AN244,39,FALSE) -> 0.081743069 | AP69: =VLOOKUP(A69,'2022_PAPI_Indicators'!A64:AO244,40,FALSE) -> 0.099411771 | AQ69: =VLOOKUP(A69,'2022_PAPI_Indicators'!A64:AP244,41,FALSE) -> 0.046387888 | AR69: =VLOOKUP(A69,'2022_PAPI_Indicators'!A64:AQ244,42,FALSE) -> 0.025774036 | AS69: =VLOOKUP(A69,'2022_PAPI_Indicators'!A64:AR244,43,FALSE) -> 0.031054135 | AT69: =VLOOKUP(A69,'2022_PAPI_Indicators'!A64:AS244,44,FALSE) -> 0.063912317 | AU69: =VLOOKUP(A69,'2022_PAPI_Indicators'!A64:AT244,45,FALSE) -> 0.029338337 | AV69: =VLOOKUP(A69,'2022_PAPI_Indicators'!A64:AU244,46,FALSE) -> 0.048862167 | AW69: =VLOOKUP(A69,'2022_PAPI_Indicators'!A64:AV244,47,FALSE) -> 0.044608604 | AX69: =VLOOKUP(A69,'2022_PAPI_Indicators'!A64:AW244,48,FALSE) -> 0.06360016 | AY69: =VLOOKUP(A69,'2022_PAPI_Indicators'!A64:AX244,49,FALSE) -> 0.033224501 | AZ69: =VLOOKUP(A69,'2022_PAPI_Indicators'!A64:AY244,50,FALSE) -> 0.051261868 | BA69: =VLOOKUP(A69,'2022_PAPI_Indicators'!A64:AZ244,51,FALSE) -> 0.051127587 | BB69: =VLOOKUP(A69,'2022_PAPI_Indicators'!A64:BA244,52,FALSE) -> 0.031989079 | BC69: =VLOOKUP(A69,'2022_PAPI_Indicators'!A64:BB244,53,FALSE) -> 0.046202976 | BD69: =VLOOKUP(A69,'2022_PAPI_Indicators'!A64:BC244,54,FALSE) -> 0.031175813 | BE69: =VLOOKUP(A69,'2022_PAPI_Indicators'!A64:BD244,55,FALSE) -> 0.053697638 | BF69: =VLOOKUP(A69,'2022_PAPI_Indicators'!A64:BE244,56,FALSE) -> 0.065095522 | BG69: =VLOOKUP(A69,'2022_PAPI_Indicators'!A64:BF244,57,FALSE) -> 0.075578459 | BH69: =VLOOKUP(A69,'2022_PAPI_Indicators'!A64:BG244,58,FALSE) -> 0.042574652 | BI69: =VLOOKUP(A69,'2022_PAPI_Indicators'!A64:BH244,59,FALSE) -> 0.044167135 | BJ69: =VLOOKUP(A69,'2022_PAPI_Indicators'!A64:BI244,60,FALSE) -> 0.023069771 | BK69: =VLOOKUP(A69,'2022_PAPI_Indicators'!A64:BJ244,61,FALSE) -> 0.040193517 | BL69: =VLOOKUP(A69,'2022_PAPI_Indicators'!A64:BK244,62,FALSE) -> 0.060661253 | BM69: =VLOOKUP(A69,'2022_PAPI_Indicators'!A64:BL244,63,FALSE) -> 0.08364898 | BN69: =VLOOKUP(A69,'2022_PAPI_Indicators'!A64:BM244,64,FALSE) -> 0.043300971
A70: Contact with Peope's Council Sucessful | B70: Tỷ lệ người trả lời cho biết cuộc gặp với cán bộ HĐND xã/phường để giải quyết khúc mắc có kết quả tốt (%) | C70: 0%-100% | D70: =VLOOKUP(A70,'2022_PAPI_Indicators'!A65:B245,2,) -> 0.88548851 | E70: =VLOOKUP(A70,'2022_PAPI_Indicators'!A65:C245,3,FALSE) -> 0.75427109 | F70: =VLOOKUP(A70,'2022_PAPI_Indicators'!A65:D245,4,FALSE) -> 0.84948933 | G70: =VLOOKUP(A70,'2022_PAPI_Indicators'!A65:E245,5,FALSE) -> 1 | H70: =VLOOKUP(A70,'2022_PAPI_Indicators'!A65:F245,6,FALSE) -> 0.98113137 | I70: =VLOOKUP(A70,'2022_PAPI_Indicators'!A65:G245,7,FALSE) -> 0.69999999 | J70: =VLOOKUP(A70,'2022_PAPI_Indicators'!A65:H245,8,FALSE) -> 0.86143064 | K70: =VLOOKUP(A70,'2022_PAPI_Indicators'!A65:I245,9,FALSE) -> 0.73957872 | L70: =VLOOKUP(A70,'2022_PAPI_Indicators'!A65:J245,10,FALSE) -> 1 | M70: =VLOOKUP(A70,'2022_PAPI_Indicators'!A65:K245,11,FALSE) -> 1 | N70: =VLOOKUP(A70,'2022_PAPI_Indicators'!A65:L245,12,FALSE) -> 1 | O70: =VLOOKUP(A70,'2022_PAPI_Indicators'!A65:M245,13,FALSE) -> 0.83550209 | P70: =VLOOKUP(A70,'2022_PAPI_Indicators'!A65:N245,14,FALSE) -> 1 | Q70: =VLOOKUP(A70,'2022_PAPI_Indicators'!A65:O245,15,FALSE) -> 1 | R70: =VLOOKUP(A70,'2022_PAPI_Indicators'!A65:P245,16,FALSE) -> 0.80820185 | S70: =VLOOKUP(A70,'2022_PAPI_Indicators'!A65:R245,17,FALSE) -> 0.7174812 | T70: =VLOOKUP(A70,'2022_PAPI_Indicators'!A65:S245,18,FALSE) -> 0.87000471 | U70: =VLOOKUP(A70,'2022_PAPI_Indicators'!A65:T245,19,FALSE) -> 0 | V70: =VLOOKUP(A70,'2022_PAPI_Indicators'!A65:U245,20,FALSE) -> 1 | W70: =VLOOKUP(A70,'2022_PAPI_Indicators'!A65:V245,21,FALSE) -> 1 | X70: =VLOOKUP(A70,'2022_PAPI_Indicators'!A65:W245,22,FALSE) -> 1 | Y70: =VLOOKUP(A70,'2022_PAPI_Indicators'!A65:X245,23,FALSE) -> 1 | Z70: =VLOOKUP(A70,'2022_PAPI_Indicators'!A65:Y245,24,FALSE) -> 1 | AA70: =VLOOKUP(A70,'2022_PAPI_Indicators'!A65:Z245,25,FALSE) -> 1 | AB70: =VLOOKUP(A70,'2022_PAPI_Indicators'!A65:AA245,26,FALSE) -> 1 | AC70: =VLOOKUP(A70,'2022_PAPI_Indicators'!A65:AB245,27,FALSE) -> 0.89593869 | AD70: =VLOOKUP(A70,'2022_PAPI_Indicators'!A65:AC245,28,FALSE) -> 0.75689602 | AE70: =VLOOKUP(A70,'2022_PAPI_Indicators'!A65:AD245,29,FALSE) -> 0.87768507 | AF70: =VLOOKUP(A70,'2022_PAPI_Indicators'!A65:AE245,30,FALSE) -> 0.82462025 | AG70: =VLOOKUP(A70,'2022_PAPI_Indicators'!A65:AF245,31,FALSE) -> 0.97867185 | AH70: =VLOOKUP(A70,'2022_PAPI_Indicators'!A65:AG245,32,FALSE) -> 1 | AI70: =VLOOKUP(A70,'2022_PAPI_Indicators'!A65:AH245,33,FALSE) -> 0.83683366 | AJ70: =VLOOKUP(A70,'2022_PAPI_Indicators'!A65:AI245,34,FALSE) -> 1 | AK70: =VLOOKUP(A70,'2022_PAPI_Indicators'!A65:AJ245,35,FALSE) -> 1 | AL70: =VLOOKUP(A70,'2022_PAPI_Indicators'!A65:AK245,36,FALSE) -> 1 | AM70: =VLOOKUP(A70,'2022_PAPI_Indicators'!A65:AL245,37,FALSE) -> 0.84667635 | AN70: =VLOOKUP(A70,'2022_PAPI_Indicators'!A65:AM245,38,FALSE) -> 1 | AO70: =VLOOKUP(A70,'2022_PAPI_Indicators'!A65:AN245,39,FALSE) -> 0.89416367 | AP70: =VLOOKUP(A70,'2022_PAPI_Indicators'!A65:AO245,40,FALSE) -> 0.98405415 | AQ70: =VLOOKUP(A70,'2022_PAPI_Indicators'!A65:AP245,41,FALSE) -> 0.85714287 | AR70: =VLOOKUP(A70,'2022_PAPI_Indicators'!A65:AQ245,42,FALSE) -> 0.66666669 | AS70: =VLOOKUP(A70,'2022_PAPI_Indicators'!A65:AR245,43,FALSE) -> 0.94711262 | AT70: =VLOOKUP(A70,'2022_PAPI_Indicators'!A65:AS245,44,FALSE) -> 0.83183753 | AU70: =VLOOKUP(A70,'2022_PAPI_Indicators'!A65:AT245,45,FALSE) -> 1 | AV70: =VLOOKUP(A70,'2022_PAPI_Indicators'!A65:AU245,46,FALSE) -> 0.80427372 | AW70: =VLOOKUP(A70,'2022_PAPI_Indicators'!A65:AV245,47,FALSE) -> 0.83684748 | AX70: =VLOOKUP(A70,'2022_PAPI_Indicators'!A65:AW245,48,FALSE) -> 1 | AY70: =VLOOKUP(A70,'2022_PAPI_Indicators'!A65:AX245,49,FALSE) -> 0.97737491 | AZ70: =VLOOKUP(A70,'2022_PAPI_Indicators'!A65:AY245,50,FALSE) -> 0.92601281 | BA70: =VLOOKUP(A70,'2022_PAPI_Indicators'!A65:AZ245,51,FALSE) -> 0.86749375 | BB70: =VLOOKUP(A70,'2022_PAPI_Indicators'!A65:BA245,52,FALSE) -> 0.81068039 | BC70: =VLOOKUP(A70,'2022_PAPI_Indicators'!A65:BB245,53,FALSE) -> 1 | BD70: =VLOOKUP(A70,'2022_PAPI_Indicators'!A65:BC245,54,FALSE) -> 0.65557313 | BE70: =VLOOKUP(A70,'2022_PAPI_Indicators'!A65:BD245,55,FALSE) -> 0.72418129 | BF70: =VLOOKUP(A70,'2022_PAPI_Indicators'!A65:BE245,56,FALSE) -> 0.86350006 | BG70: =VLOOKUP(A70,'2022_PAPI_Indicators'!A65:BF245,57,FALSE) -> 1 | BH70: =VLOOKUP(A70,'2022_PAPI_Indicators'!A65:BG245,58,FALSE) -> 0.77907687 | BI70: =VLOOKUP(A70,'2022_PAPI_Indicators'!A65:BH245,59,FALSE) -> 0.97586763 | BJ70: =VLOOKUP(A70,'2022_PAPI_Indicators'!A65:BI245,60,FALSE) -> 1 | BK70: =VLOOKUP(A70,'2022_PAPI_Indicators'!A65:BJ245,61,FALSE) -> 0.78049606 | BL70: =VLOOKUP(A70,'2022_PAPI_Indicators'!A65:BK245,62,FALSE) -> 0.98459101 | BM70: =VLOOKUP(A70,'2022_PAPI_Indicators'!A65:BL245,63,FALSE) -> 1 | BN70: =VLOOKUP(A70,'2022_PAPI_Indicators'!A65:BM245,64,FALSE) -> 1
A71: Governments Responsive to Citizen Appeals | B71: 3.2: Giải đáp khiếu nại, tố cáo, khúc mắc của người dân | C71: 0.33-3.33 điểm/points | D71: =VLOOKUP(A71,'2022_PAPI_Indicators'!A66:B246,2,) -> 0.46011353 | E71: =VLOOKUP(A71,'2022_PAPI_Indicators'!A66:C246,3,FALSE) -> 0.44412714 | F71: =VLOOKUP(A71,'2022_PAPI_Indicators'!A66:D246,4,FALSE) -> 0.4457795 | G71: =VLOOKUP(A71,'2022_PAPI_Indicators'!A66:E246,5,FALSE) -> 0.49313554 | H71: =VLOOKUP(A71,'2022_PAPI_Indicators'!A66:F246,6,FALSE) -> 0.53686279 | I71: =VLOOKUP(A71,'2022_PAPI_Indicators'!A66:G246,7,FALSE) -> 0.47874582 | J71: =VLOOKUP(A71,'2022_PAPI_Indicators'!A66:H246,8,FALSE) -> 0.48313457 | K71: =VLOOKUP(A71,'2022_PAPI_Indicators'!A66:I246,9,FALSE) -> 0.51467711 | L71: =VLOOKUP(A71,'2022_PAPI_Indicators'!A66:J246,10,FALSE) -> 0.59180713 | M71: =VLOOKUP(A71,'2022_PAPI_Indicators'!A66:K246,11,FALSE) -> 0.47778746 | N71: =VLOOKUP(A71,'2022_PAPI_Indicators'!A66:L246,12,FALSE) -> 0.50330263 | O71: =VLOOKUP(A71,'2022_PAPI_Indicators'!A66:M246,13,FALSE) -> 0.5275802 | P71: =VLOOKUP(A71,'2022_PAPI_Indicators'!A66:N246,14,FALSE) -> 0.49974263 | Q71: =VLOOKUP(A71,'2022_PAPI_Indicators'!A66:O246,15,FALSE) -> 0.46540508 | R71: =VLOOKUP(A71,'2022_PAPI_Indicators'!A66:P246,16,FALSE) -> 0.52693224 | S71: =VLOOKUP(A71,'2022_PAPI_Indicators'!A66:R246,17,FALSE) -> 0.49914122 | T71: =VLOOKUP(A71,'2022_PAPI_Indicators'!A66:S246,18,FALSE) -> 0.44856972 | U71: =VLOOKUP(A71,'2022_PAPI_Indicators'!A66:T246,19,FALSE) -> 0 | V71: =VLOOKUP(A71,'2022_PAPI_Indicators'!A66:U246,20,FALSE) -> 0.44507074 | W71: =VLOOKUP(A71,'2022_PAPI_Indicators'!A66:V246,21,FALSE) -> 0.46964151 | X71: =VLOOKUP(A71,'2022_PAPI_Indicators'!A66:W246,22,FALSE) -> 0.47990677 | Y71: =VLOOKUP(A71,'2022_PAPI_Indicators'!A66:X246,23,FALSE) -> 0.45006052 | Z71: =VLOOKUP(A71,'2022_PAPI_Indicators'!A66:Y246,24,FALSE) -> 0.47249603 | AA71: =VLOOKUP(A71,'2022_PAPI_Indicators'!A66:Z246,25,FALSE) -> 0.49825123 | AB71: =VLOOKUP(A71,'2022_PAPI_Indicators'!A66:AA246,26,FALSE) -> 0.45222223 | AC71: =VLOOKUP(A71,'2022_PAPI_Indicators'!A66:AB246,27,FALSE) -> 0.5938707 | AD71: =VLOOKUP(A71,'2022_PAPI_Indicators'!A66:AC246,28,FALSE) -> 0.54424965 | AE71: =VLOOKUP(A71,'2022_PAPI_Indicators'!A66:AD246,29,FALSE) -> 0.56890267 | AF71: =VLOOKUP(A71,'2022_PAPI_Indicators'!A66:AE246,30,FALSE) -> 0.65695608 | AG71: =VLOOKUP(A71,'2022_PAPI_Indicators'!A66:AF246,31,FALSE) -> 0.56814754 | AH71: =VLOOKUP(A71,'2022_PAPI_Indicators'!A66:AG246,32,FALSE) -> 0.53285402 | AI71: =VLOOKUP(A71,'2022_PAPI_Indicators'!A66:AH246,33,FALSE) -> 0.40773672 | AJ71: =VLOOKUP(A71,'2022_PAPI_Indicators'!A66:AI246,34,FALSE) -> 0.4843331 | AK71: =VLOOKUP(A71,'2022_PAPI_Indicators'!A66:AJ246,35,FALSE) -> 0.47543061 | AL71: =VLOOKUP(A71,'2022_PAPI_Indicators'!A66:AK246,36,FALSE) -> 0.44286284 | AM71: =VLOOKUP(A71,'2022_PAPI_Indicators'!A66:AL246,37,FALSE) -> 0.47263181 | AN71: =VLOOKUP(A71,'2022_PAPI_Indicators'!A66:AM246,38,FALSE) -> 0.42960647 | AO71: =VLOOKUP(A71,'2022_PAPI_Indicators'!A66:AN246,39,FALSE) -> 0.48570821 | AP71: =VLOOKUP(A71,'2022_PAPI_Indicators'!A66:AO246,40,FALSE) -> 0.49544874 | AQ71: =VLOOKUP(A71,'2022_PAPI_Indicators'!A66:AP246,41,FALSE) -> 0.48664829 | AR71: =VLOOKUP(A71,'2022_PAPI_Indicators'!A66:AQ246,42,FALSE) -> 0.47925252 | AS71: =VLOOKUP(A71,'2022_PAPI_Indicators'!A66:AR246,43,FALSE) -> 0.43617055 | AT71: =VLOOKUP(A71,'2022_PAPI_Indicators'!A66:AS246,44,FALSE) -> 0.52367514 | AU71: =VLOOKUP(A71,'2022_PAPI_Indicators'!A66:AT246,45,FALSE) -> 0.46023467 | AV71: =VLOOKUP(A71,'2022_PAPI_Indicators'!A66:AU246,46,FALSE) -> 0.45670316 | AW71: =VLOOKUP(A71,'2022_PAPI_Indicators'!A66:AV246,47,FALSE) -> 0.40278682 | AX71: =VLOOKUP(A71,'2022_PAPI_Indicators'!A66:AW246,48,FALSE) -> 0.46766376 | AY71: =VLOOKUP(A71,'2022_PAPI_Indicators'!A66:AX246,49,FALSE) -> 0.43277785 | AZ71: =VLOOKUP(A71,'2022_PAPI_Indicators'!A66:AY246,50,FALSE) -> 0.47352466 | BA71: =VLOOKUP(A71,'2022_PAPI_Indicators'!A66:AZ246,51,FALSE) -> 0.40277576 | BB71: =VLOOKUP(A71,'2022_PAPI_Indicators'!A66:BA246,52,FALSE) -> 0.44470605 | BC71: =VLOOKUP(A71,'2022_PAPI_Indicators'!A66:BB246,53,FALSE) -> 0.42040145 | BD71: =VLOOKUP(A71,'2022_PAPI_Indicators'!A66:BC246,54,FALSE) -> 0.45045468 | BE71: =VLOOKUP(A71,'2022_PAPI_Indicators'!A66:BD246,55,FALSE) -> 0.47353089 | BF71: =VLOOKUP(A71,'2022_PAPI_Indicators'!A66:BE246,56,FALSE) -> 0.49717849 | BG71: =VLOOKUP(A71,'2022_PAPI_Indicators'!A66:BF246,57,FALSE) -> 0.44475511 | BH71: =VLOOKUP(A71,'2022_PAPI_Indicators'!A66:BG246,58,FALSE) -> 0.38513565 | BI71: =VLOOKUP(A71,'2022_PAPI_Indicators'!A66:BH246,59,FALSE) -> 0.43443531 | BJ71: =VLOOKUP(A71,'2022_PAPI_Indicators'!A66:BI246,60,FALSE) -> 0.41216269 | BK71: =VLOOKUP(A71,'2022_PAPI_Indicators'!A66:BJ246,61,FALSE) -> 0.44817984 | BL71: =VLOOKUP(A71,'2022_PAPI_Indicators'!A66:BK246,62,FALSE) -> 0.41566196 | BM71: =VLOOKUP(A71,'2022_PAPI_Indicators'!A66:BL246,63,FALSE) -> 0.51612604 | BN71: =VLOOKUP(A71,'2022_PAPI_Indicators'!A66:BM246,64,FALSE) -> 0.53107828
A72: Actions Taken by Citizens | B72: Tỷ lệ người trả lời cho biết họ đã gửi khuyến nghị, tố giác, tố cáo, khiếu nại tới chính quyền địa phương (%) | C72: 0%-100% | D72: =VLOOKUP(A72,'2022_PAPI_Indicators'!A67:B247,2,) -> 0.18616684 | E72: =VLOOKUP(A72,'2022_PAPI_Indicators'!A67:C247,3,FALSE) -> 0.16528803 | F72: =VLOOKUP(A72,'2022_PAPI_Indicators'!A67:D247,4,FALSE) -> 0.17125373 | G72: =VLOOKUP(A72,'2022_PAPI_Indicators'!A67:E247,5,FALSE) -> 0.23108684 | H72: =VLOOKUP(A72,'2022_PAPI_Indicators'!A67:F247,6,FALSE) -> 0.28272849 | I72: =VLOOKUP(A72,'2022_PAPI_Indicators'!A67:G247,7,FALSE) -> 0.23175487 | J72: =VLOOKUP(A72,'2022_PAPI_Indicators'!A67:H247,8,FALSE) -> 0.22016783 | K72: =VLOOKUP(A72,'2022_PAPI_Indicators'!A67:I247,9,FALSE) -> 0.25865245 | L72: =VLOOKUP(A72,'2022_PAPI_Indicators'!A67:J247,10,FALSE) -> 0.38315904 | M72: =VLOOKUP(A72,'2022_PAPI_Indicators'!A67:K247,11,FALSE) -> 0.21716416 | N72: =VLOOKUP(A72,'2022_PAPI_Indicators'!A67:L247,12,FALSE) -> 0.25179023 | O72: =VLOOKUP(A72,'2022_PAPI_Indicators'!A67:M247,13,FALSE) -> 0.2818625 | P72: =VLOOKUP(A72,'2022_PAPI_Indicators'!A67:N247,14,FALSE) -> 0.24841718 | Q72: =VLOOKUP(A72,'2022_PAPI_Indicators'!A67:O247,15,FALSE) -> 0.1896583 | R72: =VLOOKUP(A72,'2022_PAPI_Indicators'!A67:P247,16,FALSE) -> 0.27304107 | S72: =VLOOKUP(A72,'2022_PAPI_Indicators'!A67:R247,17,FALSE) -> 0.25966817 | T72: =VLOOKUP(A72,'2022_PAPI_Indicators'!A67:S247,18,FALSE) -> 0.19189917 | U72: =VLOOKUP(A72,'2022_PAPI_Indicators'!A67:T247,19,FALSE) -> 0 | V72: =VLOOKUP(A72,'2022_PAPI_Indicators'!A67:U247,20,FALSE) -> 0.16550347 | W72: =VLOOKUP(A72,'2022_PAPI_Indicators'!A67:V247,21,FALSE) -> 0.19168642 | X72: =VLOOKUP(A72,'2022_PAPI_Indicators'!A67:W247,22,FALSE) -> 0.20599113 | Y72: =VLOOKUP(A72,'2022_PAPI_Indicators'!A67:X247,23,FALSE) -> 0.17302088 | Z72: =VLOOKUP(A72,'2022_PAPI_Indicators'!A67:Y247,24,FALSE) -> 0.19684534 | AA72: =VLOOKUP(A72,'2022_PAPI_Indicators'!A67:Z247,25,FALSE) -> 0.2494832 | AB72: =VLOOKUP(A72,'2022_PAPI_Indicators'!A67:AA247,26,FALSE) -> 0.18640688 | AC72: =VLOOKUP(A72,'2022_PAPI_Indicators'!A67:AB247,27,FALSE) -> 0.37070057 | AD72: =VLOOKUP(A72,'2022_PAPI_Indicators'!A67:AC247,28,FALSE) -> 0.30927351 | AE72: =VLOOKUP(A72,'2022_PAPI_Indicators'!A67:AD247,29,FALSE) -> 0.34926248 | AF72: =VLOOKUP(A72,'2022_PAPI_Indicators'!A67:AE247,30,FALSE) -> 0.47586623 | AG72: =VLOOKUP(A72,'2022_PAPI_Indicators'!A67:AF247,31,FALSE) -> 0.34353569 | AH72: =VLOOKUP(A72,'2022_PAPI_Indicators'!A67:AG247,32,FALSE) -> 0.27320406 | AI72: =VLOOKUP(A72,'2022_PAPI_Indicators'!A67:AH247,33,FALSE) -> 0.11455216 | AJ72: =VLOOKUP(A72,'2022_PAPI_Indicators'!A67:AI247,34,FALSE) -> 0.21892646 | AK72: =VLOOKUP(A72,'2022_PAPI_Indicators'!A67:AJ247,35,FALSE) -> 0.21575622 | AL72: =VLOOKUP(A72,'2022_PAPI_Indicators'!A67:AK247,36,FALSE) -> 0.16227601 | AM72: =VLOOKUP(A72,'2022_PAPI_Indicators'!A67:AL247,37,FALSE) -> 0.20772171 | AN72: =VLOOKUP(A72,'2022_PAPI_Indicators'!A67:AM247,38,FALSE) -> 0.14358133 | AO72: =VLOOKUP(A72,'2022_PAPI_Indicators'!A67:AN247,39,FALSE) -> 0.21526001 | AP72: =VLOOKUP(A72,'2022_PAPI_Indicators'!A67:AO247,40,FALSE) -> 0.22282656 | AQ72: =VLOOKUP(A72,'2022_PAPI_Indicators'!A67:AP247,41,FALSE) -> 0.23093145 | AR72: =VLOOKUP(A72,'2022_PAPI_Indicators'!A67:AQ247,42,FALSE) -> 0.20456079 | AS72: =VLOOKUP(A72,'2022_PAPI_Indicators'!A67:AR247,43,FALSE) -> 0.16016006 | AT72: =VLOOKUP(A72,'2022_PAPI_Indicators'!A67:AS247,44,FALSE) -> 0.28271458 | AU72: =VLOOKUP(A72,'2022_PAPI_Indicators'!A67:AT247,45,FALSE) -> 0.18439066 | AV72: =VLOOKUP(A72,'2022_PAPI_Indicators'!A67:AU247,46,FALSE) -> 0.17649399 | AW72: =VLOOKUP(A72,'2022_PAPI_Indicators'!A67:AV247,47,FALSE) -> 0.10941667 | AX72: =VLOOKUP(A72,'2022_PAPI_Indicators'!A67:AW247,48,FALSE) -> 0.18957958 | AY72: =VLOOKUP(A72,'2022_PAPI_Indicators'!A67:AX247,49,FALSE) -> 0.15631089 | AZ72: =VLOOKUP(A72,'2022_PAPI_Indicators'!A67:AY247,50,FALSE) -> 0.20295617 | BA72: =VLOOKUP(A72,'2022_PAPI_Indicators'!A67:AZ247,51,FALSE) -> 0.11168695 | BB72: =VLOOKUP(A72,'2022_PAPI_Indicators'!A67:BA247,52,FALSE) -> 0.1756828 | BC72: =VLOOKUP(A72,'2022_PAPI_Indicators'!A67:BB247,53,FALSE) -> 0.12533693 | BD72: =VLOOKUP(A72,'2022_PAPI_Indicators'!A67:BC247,54,FALSE) -> 0.18072423 | BE72: =VLOOKUP(A72,'2022_PAPI_Indicators'!A67:BD247,55,FALSE) -> 0.21920243 | BF72: =VLOOKUP(A72,'2022_PAPI_Indicators'!A67:BE247,56,FALSE) -> 0.24341685 | BG72: =VLOOKUP(A72,'2022_PAPI_Indicators'!A67:BF247,57,FALSE) -> 0.15540116 | BH72: =VLOOKUP(A72,'2022_PAPI_Indicators'!A67:BG247,58,FALSE) -> 0.08019755 | BI72: =VLOOKUP(A72,'2022_PAPI_Indicators'!A67:BH247,59,FALSE) -> 0.15562639 | BJ72: =VLOOKUP(A72,'2022_PAPI_Indicators'!A67:BI247,60,FALSE) -> 0.11829916 | BK72: =VLOOKUP(A72,'2022_PAPI_Indicators'!A67:BJ247,61,FALSE) -> 0.16318412 | BL72: =VLOOKUP(A72,'2022_PAPI_Indicators'!A67:BK247,62,FALSE) -> 0.11945305 | BM72: =VLOOKUP(A72,'2022_PAPI_Indicators'!A67:BL247,63,FALSE) -> 0.26457089 | BN72: =VLOOKUP(A72,'2022_PAPI_Indicators'!A67:BM247,64,FALSE) -> 0.28551686
